Workbook

Sheet OWNED
A1: name | B1: bgg_id | C1: label | D1: check_unique | E1: bgg_name | F1: check_name | G1: category | H1: lib_cat_chk | I1: nz_desgn | O1: {=IFERROR(_xlfn._xlws.FILTER(OWNED[bgg_id], ISNA(MATCH(OWNED[bgg_id], library_data[bgg_id], 0))),"OWNED AND LIBRARY MATCH")} -> 247367
A2: 7 Wonders | B2: 68448 | D2: =COUNTIF(OWNED[bgg_id],OWNED[[#This Row],[bgg_id]]) -> 1 | E2: =_xlfn.XLOOKUP(OWNED[[#This Row],[bgg_id]],bgg_cache[id],bgg_cache[title]) -> 7 Wonders | F2: =EXACT(OWNED[[#This Row],[name]],OWNED[[#This Row],[bgg_name]]) -> TRUE | G2: GATEWAY_STRATEGY | H2: =_xlfn.XLOOKUP(OWNED[[#This Row],[bgg_id]],library_data[bgg_id],library_data[mana_meeple_category])=OWNED[[#This Row],[category]] -> TRUE | I2: =COUNTIF(nzdesgn[NAME],OWNED[[#This Row],[bgg_name]]) -> 0 | O2: 155426
A3: 7 Wonders Duel | B3: 173346 | D3: =COUNTIF(OWNED[bgg_id],OWNED[[#This Row],[bgg_id]]) -> 1 | E3: =_xlfn.XLOOKUP(OWNED[[#This Row],[bgg_id]],bgg_cache[id],bgg_cache[title]) -> 7 Wonders Duel | F3: =EXACT(OWNED[[#This Row],[name]],OWNED[[#This Row],[bgg_name]]) -> TRUE | G3: GATEWAY_STRATEGY | H3: =_xlfn.XLOOKUP(OWNED[[#This Row],[bgg_id]],library_data[bgg_id],library_data[mana_meeple_category])=OWNED[[#This Row],[category]] -> TRUE | I3: =COUNTIF(nzdesgn[NAME],OWNED[[#This Row],[bgg_name]]) -> 0 | O3: 348096
A4: A Feast for Odin | B4: 177736 | D4: =COUNTIF(OWNED[bgg_id],OWNED[[#This Row],[bgg_id]]) -> 1 | E4: =_xlfn.XLOOKUP(OWNED[[#This Row],[bgg_id]],bgg_cache[id],bgg_cache[title]) -> A Feast for Odin | F4: =EXACT(OWNED[[#This Row],[name]],OWNED[[#This Row],[bgg_name]]) -> TRUE | G4: CORE_STRATEGY | H4: =_xlfn.XLOOKUP(OWNED[[#This Row],[bgg_id]],library_data[bgg_id],library_data[mana_meeple_category])=OWNED[[#This Row],[category]] -> TRUE | I4: =COUNTIF(nzdesgn[NAME],OWNED[[#This Row],[bgg_name]]) -> 0 | O4: 312484
A5: Abandon All Artichokes | B5: 302260 | D5: =COUNTIF(OWNED[bgg_id],OWNED[[#This Row],[bgg_id]]) -> 1 | E5: =_xlfn.XLOOKUP(OWNED[[#This Row],[bgg_id]],bgg_cache[id],bgg_cache[title]) -> Abandon All Artichokes | F5: =EXACT(OWNED[[#This Row],[name]],OWNED[[#This Row],[bgg_name]]) -> TRUE | G5: KIDS_FAMILIES | H5: =_xlfn.XLOOKUP(OWNED[[#This Row],[bgg_id]],library_data[bgg_id],library_data[mana_meeple_category])=OWNED[[#This Row],[category]] -> TRUE | I5: =COUNTIF(nzdesgn[NAME],OWNED[[#This Row],[bgg_name]]) -> 0 | O5: 156546
A6: =_xlfn.XLOOKUP(OWNED[[#This Row],[bgg_id]],bgg_cache[id],bgg_cache[title]) -> Air, Land, & Sea | B6: 247367 | C6: 1 | D6: =COUNTIF(OWNED[bgg_id],OWNED[[#This Row],[bgg_id]]) -> 1 | E6: =_xlfn.XLOOKUP(OWNED[[#This Row],[bgg_id]],bgg_cache[id],bgg_cache[title]) -> Air, Land, & Sea | F6: =EXACT(OWNED[[#This Row],[name]],OWNED[[#This Row],[bgg_name]]) -> TRUE | H6: =_xlfn.XLOOKUP(OWNED[[#This Row],[bgg_id]],library_data[bgg_id],library_data[mana_meeple_category])=OWNED[[#This Row],[category]] -> #N/A | I6: =COUNTIF(nzdesgn[NAME],OWNED[[#This Row],[bgg_name]]) -> 0 | L6: Row Labels | M6: Count of NAME | O6: 353545
A7: Akropolis | B7: 357563 | D7: =COUNTIF(OWNED[bgg_id],OWNED[[#This Row],[bgg_id]]) -> 1 | E7: =_xlfn.XLOOKUP(OWNED[[#This Row],[bgg_id]],bgg_cache[id],bgg_cache[title]) -> Akropolis | F7: =EXACT(OWNED[[#This Row],[name]],OWNED[[#This Row],[bgg_name]]) -> TRUE | G7: GATEWAY_STRATEGY | H7: =_xlfn.XLOOKUP(OWNED[[#This Row],[bgg_id]],library_data[bgg_id],library_data[mana_meeple_category])=OWNED[[#This Row],[category]] -> TRUE | I7: =COUNTIF(nzdesgn[NAME],OWNED[[#This Row],[bgg_name]]) -> 0 | L7: COOP_ADVENTURE | M7: 36 | O7: 367272
A8: Animal Upon Animal | B8: 17329 | D8: =COUNTIF(OWNED[bgg_id],OWNED[[#This Row],[bgg_id]]) -> 1 | E8: =_xlfn.XLOOKUP(OWNED[[#This Row],[bgg_id]],bgg_cache[id],bgg_cache[title]) -> Animal Upon Animal | F8: =EXACT(OWNED[[#This Row],[name]],OWNED[[#This Row],[bgg_name]]) -> TRUE | G8: KIDS_FAMILIES | H8: =_xlfn.XLOOKUP(OWNED[[#This Row],[bgg_id]],library_data[bgg_id],library_data[mana_meeple_category])=OWNED[[#This Row],[category]] -> TRUE | I8: =COUNTIF(nzdesgn[NAME],OWNED[[#This Row],[bgg_name]]) -> 0 | L8: CORE_STRATEGY | M8: 25 | O8: 305682
A9: Anomia | B9: 67877 | D9: =COUNTIF(OWNED[bgg_id],OWNED[[#This Row],[bgg_id]]) -> 1 | E9: =_xlfn.XLOOKUP(OWNED[[#This Row],[bgg_id]],bgg_cache[id],bgg_cache[title]) -> Anomia | F9: =EXACT(OWNED[[#This Row],[name]],OWNED[[#This Row],[bgg_name]]) -> TRUE | G9: PARTY_ICEBREAKERS | H9: =_xlfn.XLOOKUP(OWNED[[#This Row],[bgg_id]],library_data[bgg_id],library_data[mana_meeple_category])=OWNED[[#This Row],[category]] -> TRUE | I9: =COUNTIF(nzdesgn[NAME],OWNED[[#This Row],[bgg_name]]) -> 0 | L9: GATEWAY_STRATEGY | M9: 49 | O9: 284083
A10: Ascension: Deckbuilding Game | B10: 69789 | D10: =COUNTIF(OWNED[bgg_id],OWNED[[#This Row],[bgg_id]]) -> 1 | E10: =_xlfn.XLOOKUP(OWNED[[#This Row],[bgg_id]],bgg_cache[id],bgg_cache[title]) -> Ascension: Deckbuilding Game | F10: =EXACT(OWNED[[#This Row],[name]],OWNED[[#This Row],[bgg_name]]) -> TRUE | G10: GATEWAY_STRATEGY | H10: =_xlfn.XLOOKUP(OWNED[[#This Row],[bgg_id]],library_data[bgg_id],library_data[mana_meeple_category])=OWNED[[#This Row],[category]] -> TRUE | I10: =COUNTIF(nzdesgn[NAME],OWNED[[#This Row],[bgg_name]]) -> 0 | L10: KIDS_FAMILIES | M10: 25 | O10: 314421
A11: Azul | B11: 230802 | D11: =COUNTIF(OWNED[bgg_id],OWNED[[#This Row],[bgg_id]]) -> 1 | E11: =_xlfn.XLOOKUP(OWNED[[#This Row],[bgg_id]],bgg_cache[id],bgg_cache[title]) -> Azul | F11: =EXACT(OWNED[[#This Row],[name]],OWNED[[#This Row],[bgg_name]]) -> TRUE | G11: GATEWAY_STRATEGY | H11: =_xlfn.XLOOKUP(OWNED[[#This Row],[bgg_id]],library_data[bgg_id],library_data[mana_meeple_category])=OWNED[[#This Row],[category]] -> TRUE | I11: =COUNTIF(nzdesgn[NAME],OWNED[[#This Row],[bgg_name]]) -> 0 | L11: PARTY_ICEBREAKERS | M11: 51 | O11: 257527
A12: Battlestar Galactica: The Board Game | B12: 37111 | D12: =COUNTIF(OWNED[bgg_id],OWNED[[#This Row],[bgg_id]]) -> 1 | E12: =_xlfn.XLOOKUP(OWNED[[#This Row],[bgg_id]],bgg_cache[id],bgg_cache[title]) -> Battlestar Galactica: The Board Game | F12: =EXACT(OWNED[[#This Row],[name]],OWNED[[#This Row],[bgg_name]]) -> TRUE | G12: CORE_STRATEGY | H12: =_xlfn.XLOOKUP(OWNED[[#This Row],[bgg_id]],library_data[bgg_id],library_data[mana_meeple_category])=OWNED[[#This Row],[category]] -> TRUE | I12: =COUNTIF(nzdesgn[NAME],OWNED[[#This Row],[bgg_name]]) -> 0 | L12: (blank) | M12: 18 | O12: 233867
A13: Bohnanza | B13: 11 | D13: =COUNTIF(OWNED[bgg_id],OWNED[[#This Row],[bgg_id]]) -> 1 | E13: =_xlfn.XLOOKUP(OWNED[[#This Row],[bgg_id]],bgg_cache[id],bgg_cache[title]) -> Bohnanza | F13: =EXACT(OWNED[[#This Row],[name]],OWNED[[#This Row],[bgg_name]]) -> TRUE | G13: GATEWAY_STRATEGY | H13: =_xlfn.XLOOKUP(OWNED[[#This Row],[bgg_id]],library_data[bgg_id],library_data[mana_meeple_category])=OWNED[[#This Row],[category]] -> TRUE | I13: =COUNTIF(nzdesgn[NAME],OWNED[[#This Row],[bgg_name]]) -> 0 | L13: Grand Total | M13: 204 | O13: 9209
A14: BUILDZI | B14: 326243 | D14: =COUNTIF(OWNED[bgg_id],OWNED[[#This Row],[bgg_id]]) -> 1 | E14: =_xlfn.XLOOKUP(OWNED[[#This Row],[bgg_id]],bgg_cache[id],bgg_cache[title]) -> BUILDZI | F14: =EXACT(OWNED[[#This Row],[name]],OWNED[[#This Row],[bgg_name]]) -> TRUE | G14: KIDS_FAMILIES | H14: =_xlfn.XLOOKUP(OWNED[[#This Row],[bgg_id]],library_data[bgg_id],library_data[mana_meeple_category])=OWNED[[#This Row],[category]] -> TRUE | I14: =COUNTIF(nzdesgn[NAME],OWNED[[#This Row],[bgg_name]]) -> 0 | O14: 304783
A15: Calico | B15: 283155 | D15: =COUNTIF(OWNED[bgg_id],OWNED[[#This Row],[bgg_id]]) -> 1 | E15: =_xlfn.XLOOKUP(OWNED[[#This Row],[bgg_id]],bgg_cache[id],bgg_cache[title]) -> Calico | F15: =EXACT(OWNED[[#This Row],[name]],OWNED[[#This Row],[bgg_name]]) -> TRUE | G15: GATEWAY_STRATEGY | H15: =_xlfn.XLOOKUP(OWNED[[#This Row],[bgg_id]],library_data[bgg_id],library_data[mana_meeple_category])=OWNED[[#This Row],[category]] -> TRUE | I15: =COUNTIF(nzdesgn[NAME],OWNED[[#This Row],[bgg_name]]) -> 0 | O15: 329839
A16: Camel Up (Second Edition) | B16: 260605 | D16: =COUNTIF(OWNED[bgg_id],OWNED[[#This Row],[bgg_id]]) -> 1 | E16: =_xlfn.XLOOKUP(OWNED[[#This Row],[bgg_id]],bgg_cache[id],bgg_cache[title]) -> Camel Up (Second Edition) | F16: =EXACT(OWNED[[#This Row],[name]],OWNED[[#This Row],[bgg_name]]) -> TRUE | G16: PARTY_ICEBREAKERS | H16: =_xlfn.XLOOKUP(OWNED[[#This Row],[bgg_id]],library_data[bgg_id],library_data[mana_meeple_category])=OWNED[[#This Row],[category]] -> TRUE | I16: =COUNTIF(nzdesgn[NAME],OWNED[[#This Row],[bgg_name]]) -> 0 | O16: 223278
A17: Captain Sonar | B17: 171131 | D17: =COUNTIF(OWNED[bgg_id],OWNED[[#This Row],[bgg_id]]) -> 1 | E17: =_xlfn.XLOOKUP(OWNED[[#This Row],[bgg_id]],bgg_cache[id],bgg_cache[title]) -> Captain Sonar | F17: =EXACT(OWNED[[#This Row],[name]],OWNED[[#This Row],[bgg_name]]) -> TRUE | G17: COOP_ADVENTURE | H17: =_xlfn.XLOOKUP(OWNED[[#This Row],[bgg_id]],library_data[bgg_id],library_data[mana_meeple_category])=OWNED[[#This Row],[category]] -> TRUE | I17: =COUNTIF(nzdesgn[NAME],OWNED[[#This Row],[bgg_name]]) -> 0 | O17: 48726
A18: Carcassonne | B18: 822 | D18: =COUNTIF(OWNED[bgg_id],OWNED[[#This Row],[bgg_id]]) -> 1 | E18: =_xlfn.XLOOKUP(OWNED[[#This Row],[bgg_id]],bgg_cache[id],bgg_cache[title]) -> Carcassonne | F18: =EXACT(OWNED[[#This Row],[name]],OWNED[[#This Row],[bgg_name]]) -> TRUE | G18: GATEWAY_STRATEGY | H18: =_xlfn.XLOOKUP(OWNED[[#This Row],[bgg_id]],library_data[bgg_id],library_data[mana_meeple_category])=OWNED[[#This Row],[category]] -> TRUE | I18: =COUNTIF(nzdesgn[NAME],OWNED[[#This Row],[bgg_name]]) -> 0
A19: Cartographers | B19: 263918 | D19: =COUNTIF(OWNED[bgg_id],OWNED[[#This Row],[bgg_id]]) -> 1 | E19: =_xlfn.XLOOKUP(OWNED[[#This Row],[bgg_id]],bgg_cache[id],bgg_cache[title]) -> Cartographers | F19: =EXACT(OWNED[[#This Row],[name]],OWNED[[#This Row],[bgg_name]]) -> TRUE | G19: GATEWAY_STRATEGY | H19: =_xlfn.XLOOKUP(OWNED[[#This Row],[bgg_id]],library_data[bgg_id],library_data[mana_meeple_category])=OWNED[[#This Row],[category]] -> TRUE | I19: =COUNTIF(nzdesgn[NAME],OWNED[[#This Row],[bgg_name]]) -> 0
A20: Cascadia | B20: 295947 | D20: =COUNTIF(OWNED[bgg_id],OWNED[[#This Row],[bgg_id]]) -> 1 | E20: =_xlfn.XLOOKUP(OWNED[[#This Row],[bgg_id]],bgg_cache[id],bgg_cache[title]) -> Cascadia | F20: =EXACT(OWNED[[#This Row],[name]],OWNED[[#This Row],[bgg_name]]) -> TRUE | G20: GATEWAY_STRATEGY | H20: =_xlfn.XLOOKUP(OWNED[[#This Row],[bgg_id]],library_data[bgg_id],library_data[mana_meeple_category])=OWNED[[#This Row],[category]] -> TRUE | I20: =COUNTIF(nzdesgn[NAME],OWNED[[#This Row],[bgg_name]]) -> 0
A21: Castles of Mad King Ludwig | B21: 155426 | C21: 1 | D21: =COUNTIF(OWNED[bgg_id],OWNED[[#This Row],[bgg_id]]) -> 1 | E21: =_xlfn.XLOOKUP(OWNED[[#This Row],[bgg_id]],bgg_cache[id],bgg_cache[title]) -> #N/A | F21: =EXACT(OWNED[[#This Row],[name]],OWNED[[#This Row],[bgg_name]]) -> #N/A | H21: =_xlfn.XLOOKUP(OWNED[[#This Row],[bgg_id]],library_data[bgg_id],library_data[mana_meeple_category])=OWNED[[#This Row],[category]] -> #N/A | I21: =COUNTIF(nzdesgn[NAME],OWNED[[#This Row],[bgg_name]]) -> 0
A22: CATAN | B22: 13 | D22: =COUNTIF(OWNED[bgg_id],OWNED[[#This Row],[bgg_id]]) -> 1 | E22: =_xlfn.XLOOKUP(OWNED[[#This Row],[bgg_id]],bgg_cache[id],bgg_cache[title]) -> CATAN | F22: =EXACT(OWNED[[#This Row],[name]],OWNED[[#This Row],[bgg_name]]) -> TRUE | G22: GATEWAY_STRATEGY | H22: =_xlfn.XLOOKUP(OWNED[[#This Row],[bgg_id]],library_data[bgg_id],library_data[mana_meeple_category])=OWNED[[#This Row],[category]] -> TRUE | I22: =COUNTIF(nzdesgn[NAME],OWNED[[#This Row],[bgg_name]]) -> 0
A23: Category 5 aka. 6 nimmt! aka. Take 5 | B23: 432 | D23: =COUNTIF(OWNED[bgg_id],OWNED[[#This Row],[bgg_id]]) -> 1 | E23: =_xlfn.XLOOKUP(OWNED[[#This Row],[bgg_id]],bgg_cache[id],bgg_cache[title]) -> Take 5 | F23: =EXACT(OWNED[[#This Row],[name]],OWNED[[#This Row],[bgg_name]]) -> FALSE | G23: PARTY_ICEBREAKERS | H23: =_xlfn.XLOOKUP(OWNED[[#This Row],[bgg_id]],library_data[bgg_id],library_data[mana_meeple_category])=OWNED[[#This Row],[category]] -> TRUE | I23: =COUNTIF(nzdesgn[NAME],OWNED[[#This Row],[bgg_name]]) -> 0
A24: Cathedral | B24: 7 | D24: =COUNTIF(OWNED[bgg_id],OWNED[[#This Row],[bgg_id]]) -> 1 | E24: =_xlfn.XLOOKUP(OWNED[[#This Row],[bgg_id]],bgg_cache[id],bgg_cache[title]) -> Cathedral | F24: =EXACT(OWNED[[#This Row],[name]],OWNED[[#This Row],[bgg_name]]) -> TRUE | G24: GATEWAY_STRATEGY | H24: =_xlfn.XLOOKUP(OWNED[[#This Row],[bgg_id]],library_data[bgg_id],library_data[mana_meeple_category])=OWNED[[#This Row],[category]] -> TRUE | I24: =COUNTIF(nzdesgn[NAME],OWNED[[#This Row],[bgg_name]]) -> 1
A25: Caverna: The Cave Farmers | B25: 102794 | D25: =COUNTIF(OWNED[bgg_id],OWNED[[#This Row],[bgg_id]]) -> 1 | E25: =_xlfn.XLOOKUP(OWNED[[#This Row],[bgg_id]],bgg_cache[id],bgg_cache[title]) -> Caverna: The Cave Farmers | F25: =EXACT(OWNED[[#This Row],[name]],OWNED[[#This Row],[bgg_name]]) -> TRUE | G25: CORE_STRATEGY | H25: =_xlfn.XLOOKUP(OWNED[[#This Row],[bgg_id]],library_data[bgg_id],library_data[mana_meeple_category])=OWNED[[#This Row],[category]] -> TRUE | I25: =COUNTIF(nzdesgn[NAME],OWNED[[#This Row],[bgg_name]]) -> 0
A26: Chronicles of Crime | B26: 239188 | D26: =COUNTIF(OWNED[bgg_id],OWNED[[#This Row],[bgg_id]]) -> 1 | E26: =_xlfn.XLOOKUP(OWNED[[#This Row],[bgg_id]],bgg_cache[id],bgg_cache[title]) -> Chronicles of Crime | F26: =EXACT(OWNED[[#This Row],[name]],OWNED[[#This Row],[bgg_name]]) -> TRUE | G26: COOP_ADVENTURE | H26: =_xlfn.XLOOKUP(OWNED[[#This Row],[bgg_id]],library_data[bgg_id],library_data[mana_meeple_category])=OWNED[[#This Row],[category]] -> TRUE | I26: =COUNTIF(nzdesgn[NAME],OWNED[[#This Row],[bgg_name]]) -> 0
A27: Citadels | B27: 205398 | D27: =COUNTIF(OWNED[bgg_id],OWNED[[#This Row],[bgg_id]]) -> 1 | E27: =_xlfn.XLOOKUP(OWNED[[#This Row],[bgg_id]],bgg_cache[id],bgg_cache[title]) -> Citadels | F27: =EXACT(OWNED[[#This Row],[name]],OWNED[[#This Row],[bgg_name]]) -> TRUE | G27: GATEWAY_STRATEGY | H27: =_xlfn.XLOOKUP(OWNED[[#This Row],[bgg_id]],library_data[bgg_id],library_data[mana_meeple_category])=OWNED[[#This Row],[category]] -> TRUE | I27: =COUNTIF(nzdesgn[NAME],OWNED[[#This Row],[bgg_name]]) -> 0
A28: Cockroach Soup | B28: 38391 | D28: =COUNTIF(OWNED[bgg_id],OWNED[[#This Row],[bgg_id]]) -> 1 | E28: =_xlfn.XLOOKUP(OWNED[[#This Row],[bgg_id]],bgg_cache[id],bgg_cache[title]) -> Kakerlakensuppe | F28: =EXACT(OWNED[[#This Row],[name]],OWNED[[#This Row],[bgg_name]]) -> FALSE | G28: KIDS_FAMILIES | H28: =_xlfn.XLOOKUP(OWNED[[#This Row],[bgg_id]],library_data[bgg_id],library_data[mana_meeple_category])=OWNED[[#This Row],[category]] -> TRUE | I28: =COUNTIF(nzdesgn[NAME],OWNED[[#This Row],[bgg_name]]) -> 0
A29: Codenames | B29: 178900 | D29: =COUNTIF(OWNED[bgg_id],OWNED[[#This Row],[bgg_id]]) -> 1 | E29: =_xlfn.XLOOKUP(OWNED[[#This Row],[bgg_id]],bgg_cache[id],bgg_cache[title]) -> Codenames | F29: =EXACT(OWNED[[#This Row],[name]],OWNED[[#This Row],[bgg_name]]) -> TRUE | G29: PARTY_ICEBREAKERS | H29: =_xlfn.XLOOKUP(OWNED[[#This Row],[bgg_id]],library_data[bgg_id],library_data[mana_meeple_category])=OWNED[[#This Row],[category]] -> TRUE | I29: =COUNTIF(nzdesgn[NAME],OWNED[[#This Row],[bgg_name]]) -> 0
A30: Coloretto | B30: 5782 | D30: =COUNTIF(OWNED[bgg_id],OWNED[[#This Row],[bgg_id]]) -> 1 | E30: =_xlfn.XLOOKUP(OWNED[[#This Row],[bgg_id]],bgg_cache[id],bgg_cache[title]) -> Coloretto | F30: =EXACT(OWNED[[#This Row],[name]],OWNED[[#This Row],[bgg_name]]) -> TRUE | G30: PARTY_ICEBREAKERS | H30: =_xlfn.XLOOKUP(OWNED[[#This Row],[bgg_id]],library_data[bgg_id],library_data[mana_meeple_category])=OWNED[[#This Row],[category]] -> TRUE | I30: =COUNTIF(nzdesgn[NAME],OWNED[[#This Row],[bgg_name]]) -> 0
A31: Concept | B31: 147151 | D31: =COUNTIF(OWNED[bgg_id],OWNED[[#This Row],[bgg_id]]) -> 1 | E31: =_xlfn.XLOOKUP(OWNED[[#This Row],[bgg_id]],bgg_cache[id],bgg_cache[title]) -> Concept | F31: =EXACT(OWNED[[#This Row],[name]],OWNED[[#This Row],[bgg_name]]) -> TRUE | G31: PARTY_ICEBREAKERS | H31: =_xlfn.XLOOKUP(OWNED[[#This Row],[bgg_id]],library_data[bgg_id],library_data[mana_meeple_category])=OWNED[[#This Row],[category]] -> TRUE | I31: =COUNTIF(nzdesgn[NAME],OWNED[[#This Row],[bgg_name]]) -> 0
A32: Cosmolancer | B32: 119 | D32: =COUNTIF(OWNED[bgg_id],OWNED[[#This Row],[bgg_id]]) -> 1 | E32: =_xlfn.XLOOKUP(OWNED[[#This Row],[bgg_id]],bgg_cache[id],bgg_cache[title]) -> Cosmolancer | F32: =EXACT(OWNED[[#This Row],[name]],OWNED[[#This Row],[bgg_name]]) -> TRUE | G32: PARTY_ICEBREAKERS | H32: =_xlfn.XLOOKUP(OWNED[[#This Row],[bgg_id]],library_data[bgg_id],library_data[mana_meeple_category])=OWNED[[#This Row],[category]] -> TRUE | I32: =COUNTIF(nzdesgn[NAME],OWNED[[#This Row],[bgg_name]]) -> 0
A33: Dead of Winter: A Crossroads Game | B33: 150376 | D33: =COUNTIF(OWNED[bgg_id],OWNED[[#This Row],[bgg_id]]) -> 1 | E33: =_xlfn.XLOOKUP(OWNED[[#This Row],[bgg_id]],bgg_cache[id],bgg_cache[title]) -> Dead of Winter: A Crossroads Game | F33: =EXACT(OWNED[[#This Row],[name]],OWNED[[#This Row],[bgg_name]]) -> TRUE | G33: COOP_ADVENTURE | H33: =_xlfn.XLOOKUP(OWNED[[#This Row],[bgg_id]],library_data[bgg_id],library_data[mana_meeple_category])=OWNED[[#This Row],[category]] -> TRUE | I33: =COUNTIF(nzdesgn[NAME],OWNED[[#This Row],[bgg_name]]) -> 0
A34: Dead of Winter: The Long Night | B34: 193037 | D34: =COUNTIF(OWNED[bgg_id],OWNED[[#This Row],[bgg_id]]) -> 1 | E34: =_xlfn.XLOOKUP(OWNED[[#This Row],[bgg_id]],bgg_cache[id],bgg_cache[title]) -> Dead of Winter: The Long Night | F34: =EXACT(OWNED[[#This Row],[name]],OWNED[[#This Row],[bgg_name]]) -> TRUE | G34: COOP_ADVENTURE | H34: =_xlfn.XLOOKUP(OWNED[[#This Row],[bgg_id]],library_data[bgg_id],library_data[mana_meeple_category])=OWNED[[#This Row],[category]] -> TRUE | I34: =COUNTIF(nzdesgn[NAME],OWNED[[#This Row],[bgg_name]]) -> 0
A35: Deception: Murder in Hong Kong | B35: 156129 | C35: 1 | D35: =COUNTIF(OWNED[bgg_id],OWNED[[#This Row],[bgg_id]]) -> 1 | E35: =_xlfn.XLOOKUP(OWNED[[#This Row],[bgg_id]],bgg_cache[id],bgg_cache[title]) -> Deception: Murder in Hong Kong | F35: =EXACT(OWNED[[#This Row],[name]],OWNED[[#This Row],[bgg_name]]) -> TRUE | G35: PARTY_ICEBREAKERS | H35: =_xlfn.XLOOKUP(OWNED[[#This Row],[bgg_id]],library_data[bgg_id],library_data[mana_meeple_category])=OWNED[[#This Row],[category]] -> TRUE | I35: =COUNTIF(nzdesgn[NAME],OWNED[[#This Row],[bgg_name]]) -> 0
A36: Decrypto | B36: 225694 | D36: =COUNTIF(OWNED[bgg_id],OWNED[[#This Row],[bgg_id]]) -> 1 | E36: =_xlfn.XLOOKUP(OWNED[[#This Row],[bgg_id]],bgg_cache[id],bgg_cache[title]) -> Decrypto | F36: =EXACT(OWNED[[#This Row],[name]],OWNED[[#This Row],[bgg_name]]) -> TRUE | G36: PARTY_ICEBREAKERS | H36: =_xlfn.XLOOKUP(OWNED[[#This Row],[bgg_id]],library_data[bgg_id],library_data[mana_meeple_category])=OWNED[[#This Row],[category]] -> TRUE | I36: =COUNTIF(nzdesgn[NAME],OWNED[[#This Row],[bgg_name]]) -> 0
A37: Descent: Legends of the Dark | B37: 322708 | D37: =COUNTIF(OWNED[bgg_id],OWNED[[#This Row],[bgg_id]]) -> 1 | E37: =_xlfn.XLOOKUP(OWNED[[#This Row],[bgg_id]],bgg_cache[id],bgg_cache[title]) -> Descent: Legends of the Dark | F37: =EXACT(OWNED[[#This Row],[name]],OWNED[[#This Row],[bgg_name]]) -> TRUE | G37: COOP_ADVENTURE | H37: =_xlfn.XLOOKUP(OWNED[[#This Row],[bgg_id]],library_data[bgg_id],library_data[mana_meeple_category])=OWNED[[#This Row],[category]] -> TRUE | I37: =COUNTIF(nzdesgn[NAME],OWNED[[#This Row],[bgg_name]]) -> 0
A38: Dinosaur World | B38: 317457 | C38: 1 | D38: =COUNTIF(OWNED[bgg_id],OWNED[[#This Row],[bgg_id]]) -> 1 | E38: =_xlfn.XLOOKUP(OWNED[[#This Row],[bgg_id]],bgg_cache[id],bgg_cache[title]) -> Dinosaur World | F38: =EXACT(OWNED[[#This Row],[name]],OWNED[[#This Row],[bgg_name]]) -> TRUE | G38: CORE_STRATEGY | H38: =_xlfn.XLOOKUP(OWNED[[#This Row],[bgg_id]],library_data[bgg_id],library_data[mana_meeple_category])=OWNED[[#This Row],[category]] -> TRUE | I38: =COUNTIF(nzdesgn[NAME],OWNED[[#This Row],[bgg_name]]) -> 0
A39: Dixit | B39: 39856 | D39: =COUNTIF(OWNED[bgg_id],OWNED[[#This Row],[bgg_id]]) -> 1 | E39: =_xlfn.XLOOKUP(OWNED[[#This Row],[bgg_id]],bgg_cache[id],bgg_cache[title]) -> Dixit | F39: =EXACT(OWNED[[#This Row],[name]],OWNED[[#This Row],[bgg_name]]) -> TRUE | G39: PARTY_ICEBREAKERS | H39: =_xlfn.XLOOKUP(OWNED[[#This Row],[bgg_id]],library_data[bgg_id],library_data[mana_meeple_category])=OWNED[[#This Row],[category]] -> TRUE | I39: =COUNTIF(nzdesgn[NAME],OWNED[[#This Row],[bgg_name]]) -> 0
A40: Dominion: Intrigue | B40: 40834 | D40: =COUNTIF(OWNED[bgg_id],OWNED[[#This Row],[bgg_id]]) -> 1 | E40: =_xlfn.XLOOKUP(OWNED[[#This Row],[bgg_id]],bgg_cache[id],bgg_cache[title]) -> Dominion: Intrigue | F40: =EXACT(OWNED[[#This Row],[name]],OWNED[[#This Row],[bgg_name]]) -> TRUE | G40: CORE_STRATEGY | H40: =_xlfn.XLOOKUP(OWNED[[#This Row],[bgg_id]],library_data[bgg_id],library_data[mana_meeple_category])=OWNED[[#This Row],[category]] -> TRUE | I40: =COUNTIF(nzdesgn[NAME],OWNED[[#This Row],[bgg_name]]) -> 0
A41: Dorfromantik: The Board Game | B41: 370591 | D41: =COUNTIF(OWNED[bgg_id],OWNED[[#This Row],[bgg_id]]) -> 1 | E41: =_xlfn.XLOOKUP(OWNED[[#This Row],[bgg_id]],bgg_cache[id],bgg_cache[title]) -> Dorfromantik: The Board Game | F41: =EXACT(OWNED[[#This Row],[name]],OWNED[[#This Row],[bgg_name]]) -> TRUE | G41: COOP_ADVENTURE | H41: =_xlfn.XLOOKUP(OWNED[[#This Row],[bgg_id]],library_data[bgg_id],library_data[mana_meeple_category])=OWNED[[#This Row],[category]] -> TRUE | I41: =COUNTIF(nzdesgn[NAME],OWNED[[#This Row],[bgg_name]]) -> 0
A42: Downforce | B42: 215311 | D42: =COUNTIF(OWNED[bgg_id],OWNED[[#This Row],[bgg_id]]) -> 1 | E42: =_xlfn.XLOOKUP(OWNED[[#This Row],[bgg_id]],bgg_cache[id],bgg_cache[title]) -> Downforce | F42: =EXACT(OWNED[[#This Row],[name]],OWNED[[#This Row],[bgg_name]]) -> TRUE | G42: GATEWAY_STRATEGY | H42: =_xlfn.XLOOKUP(OWNED[[#This Row],[bgg_id]],library_data[bgg_id],library_data[mana_meeple_category])=OWNED[[#This Row],[category]] -> TRUE | I42: =COUNTIF(nzdesgn[NAME],OWNED[[#This Row],[bgg_name]]) -> 0
A43: Dragomino | B43: 300010 | D43: =COUNTIF(OWNED[bgg_id],OWNED[[#This Row],[bgg_id]]) -> 1 | E43: =_xlfn.XLOOKUP(OWNED[[#This Row],[bgg_id]],bgg_cache[id],bgg_cache[title]) -> Dragomino | F43: =EXACT(OWNED[[#This Row],[name]],OWNED[[#This Row],[bgg_name]]) -> TRUE | G43: KIDS_FAMILIES | H43: =_xlfn.XLOOKUP(OWNED[[#This Row],[bgg_id]],library_data[bgg_id],library_data[mana_meeple_category])=OWNED[[#This Row],[category]] -> TRUE | I43: =COUNTIF(nzdesgn[NAME],OWNED[[#This Row],[bgg_name]]) -> 0
A44: Drop It | B44: 244916 | D44: =COUNTIF(OWNED[bgg_id],OWNED[[#This Row],[bgg_id]]) -> 1 | E44: =_xlfn.XLOOKUP(OWNED[[#This Row],[bgg_id]],bgg_cache[id],bgg_cache[title]) -> Drop It | F44: =EXACT(OWNED[[#This Row],[name]],OWNED[[#This Row],[bgg_name]]) -> TRUE | G44: KIDS_FAMILIES | H44: =_xlfn.XLOOKUP(OWNED[[#This Row],[bgg_id]],library_data[bgg_id],library_data[mana_meeple_category])=OWNED[[#This Row],[category]] -> TRUE | I44: =COUNTIF(nzdesgn[NAME],OWNED[[#This Row],[bgg_name]]) -> 0
A45: Dungeons & Dragons: Waterdeep – Dungeon of the Mad Mage Board Game | B45: 264196 | D45: =COUNTIF(OWNED[bgg_id],OWNED[[#This Row],[bgg_id]]) -> 1 | E45: =_xlfn.XLOOKUP(OWNED[[#This Row],[bgg_id]],bgg_cache[id],bgg_cache[title]) -> Dungeons & Dragons: Waterdeep – Dungeon of the Mad Mage Board Game | F45: =EXACT(OWNED[[#This Row],[name]],OWNED[[#This Row],[bgg_name]]) -> TRUE | G45: COOP_ADVENTURE | H45: =_xlfn.XLOOKUP(OWNED[[#This Row],[bgg_id]],library_data[bgg_id],library_data[mana_meeple_category])=OWNED[[#This Row],[category]] -> TRUE | I45: =COUNTIF(nzdesgn[NAME],OWNED[[#This Row],[bgg_name]]) -> 0
A46: Eclipse: New Dawn for the Galaxy | B46: 72125 | D46: =COUNTIF(OWNED[bgg_id],OWNED[[#This Row],[bgg_id]]) -> 1 | E46: =_xlfn.XLOOKUP(OWNED[[#This Row],[bgg_id]],bgg_cache[id],bgg_cache[title]) -> Eclipse: New Dawn for the Galaxy | F46: =EXACT(OWNED[[#This Row],[name]],OWNED[[#This Row],[bgg_name]]) -> TRUE | G46: CORE_STRATEGY | H46: =_xlfn.XLOOKUP(OWNED[[#This Row],[bgg_id]],library_data[bgg_id],library_data[mana_meeple_category])=OWNED[[#This Row],[category]] -> TRUE | I46: =COUNTIF(nzdesgn[NAME],OWNED[[#This Row],[bgg_name]]) -> 0
A47: Elder Sign | B47: 100423 | D47: =COUNTIF(OWNED[bgg_id],OWNED[[#This Row],[bgg_id]]) -> 1 | E47: =_xlfn.XLOOKUP(OWNED[[#This Row],[bgg_id]],bgg_cache[id],bgg_cache[title]) -> Elder Sign | F47: =EXACT(OWNED[[#This Row],[name]],OWNED[[#This Row],[bgg_name]]) -> TRUE | G47: COOP_ADVENTURE | H47: =_xlfn.XLOOKUP(OWNED[[#This Row],[bgg_id]],library_data[bgg_id],library_data[mana_meeple_category])=OWNED[[#This Row],[category]] -> TRUE | I47: =COUNTIF(nzdesgn[NAME],OWNED[[#This Row],[bgg_name]]) -> 0
A48: Escape Room: The Game | B48: 204836 | D48: =COUNTIF(OWNED[bgg_id],OWNED[[#This Row],[bgg_id]]) -> 1 | E48: =_xlfn.XLOOKUP(OWNED[[#This Row],[bgg_id]],bgg_cache[id],bgg_cache[title]) -> Escape Room: The Game | F48: =EXACT(OWNED[[#This Row],[name]],OWNED[[#This Row],[bgg_name]]) -> TRUE | G48: COOP_ADVENTURE | H48: =_xlfn.XLOOKUP(OWNED[[#This Row],[bgg_id]],library_data[bgg_id],library_data[mana_meeple_category])=OWNED[[#This Row],[category]] -> TRUE | I48: =COUNTIF(nzdesgn[NAME],OWNED[[#This Row],[bgg_name]]) -> 0
A49: Exploding Kittens: The Board Game | B49: 447244 | D49: =COUNTIF(OWNED[bgg_id],OWNED[[#This Row],[bgg_id]]) -> 1 | E49: =_xlfn.XLOOKUP(OWNED[[#This Row],[bgg_id]],bgg_cache[id],bgg_cache[title]) -> Exploding Kittens: The Board Game | F49: =EXACT(OWNED[[#This Row],[name]],OWNED[[#This Row],[bgg_name]]) -> TRUE | G49: PARTY_ICEBREAKERS | H49: =_xlfn.XLOOKUP(OWNED[[#This Row],[bgg_id]],library_data[bgg_id],library_data[mana_meeple_category])=OWNED[[#This Row],[category]] -> TRUE | I49: =COUNTIF(nzdesgn[NAME],OWNED[[#This Row],[bgg_name]]) -> 0
A50: Finca | B50: 261720 | D50: =COUNTIF(OWNED[bgg_id],OWNED[[#This Row],[bgg_id]]) -> 1 | E50: =_xlfn.XLOOKUP(OWNED[[#This Row],[bgg_id]],bgg_cache[id],bgg_cache[title]) -> Finca | F50: =EXACT(OWNED[[#This Row],[name]],OWNED[[#This Row],[bgg_name]]) -> TRUE | G50: GATEWAY_STRATEGY | H50: =_xlfn.XLOOKUP(OWNED[[#This Row],[bgg_id]],library_data[bgg_id],library_data[mana_meeple_category])=OWNED[[#This Row],[category]] -> TRUE | I50: =COUNTIF(nzdesgn[NAME],OWNED[[#This Row],[bgg_name]]) -> 0
A51: Five Crowns | B51: 1472 | C51: 1 | D51: =COUNTIF(OWNED[bgg_id],OWNED[[#This Row],[bgg_id]]) -> 1 | E51: =_xlfn.XLOOKUP(OWNED[[#This Row],[bgg_id]],bgg_cache[id],bgg_cache[title]) -> Five Crowns | F51: =EXACT(OWNED[[#This Row],[name]],OWNED[[#This Row],[bgg_name]]) -> TRUE | G51: KIDS_FAMILIES | H51: =_xlfn.XLOOKUP(OWNED[[#This Row],[bgg_id]],library_data[bgg_id],library_data[mana_meeple_category])=OWNED[[#This Row],[category]] -> TRUE | I51: =COUNTIF(nzdesgn[NAME],OWNED[[#This Row],[bgg_name]]) -> 0
A52: Five Tribes: The Djinns of Naqala | B52: 157354 | D52: =COUNTIF(OWNED[bgg_id],OWNED[[#This Row],[bgg_id]]) -> 1 | E52: =_xlfn.XLOOKUP(OWNED[[#This Row],[bgg_id]],bgg_cache[id],bgg_cache[title]) -> Five Tribes: The Djinns of Naqala | F52: =EXACT(OWNED[[#This Row],[name]],OWNED[[#This Row],[bgg_name]]) -> TRUE | G52: CORE_STRATEGY | H52: =_xlfn.XLOOKUP(OWNED[[#This Row],[bgg_id]],library_data[bgg_id],library_data[mana_meeple_category])=OWNED[[#This Row],[category]] -> TRUE | I52: =COUNTIF(nzdesgn[NAME],OWNED[[#This Row],[bgg_name]]) -> 0
A53: Flaming Pyramids | B53: 236639 | D53: =COUNTIF(OWNED[bgg_id],OWNED[[#This Row],[bgg_id]]) -> 1 | E53: =_xlfn.XLOOKUP(OWNED[[#This Row],[bgg_id]],bgg_cache[id],bgg_cache[title]) -> Flaming Pyramids | F53: =EXACT(OWNED[[#This Row],[name]],OWNED[[#This Row],[bgg_name]]) -> TRUE | G53: PARTY_ICEBREAKERS | H53: =_xlfn.XLOOKUP(OWNED[[#This Row],[bgg_id]],library_data[bgg_id],library_data[mana_meeple_category])=OWNED[[#This Row],[category]] -> TRUE | I53: =COUNTIF(nzdesgn[NAME],OWNED[[#This Row],[bgg_name]]) -> 1
A54: Flip 7 | B54: 420087 | D54: =COUNTIF(OWNED[bgg_id],OWNED[[#This Row],[bgg_id]]) -> 1 | E54: =_xlfn.XLOOKUP(OWNED[[#This Row],[bgg_id]],bgg_cache[id],bgg_cache[title]) -> Flip 7 | F54: =EXACT(OWNED[[#This Row],[name]],OWNED[[#This Row],[bgg_name]]) -> TRUE | G54: PARTY_ICEBREAKERS | H54: =_xlfn.XLOOKUP(OWNED[[#This Row],[bgg_id]],library_data[bgg_id],library_data[mana_meeple_category])=OWNED[[#This Row],[category]] -> TRUE | I54: =COUNTIF(nzdesgn[NAME],OWNED[[#This Row],[bgg_name]]) -> 0
A55: Flipology | B55: 261140 | D55: =COUNTIF(OWNED[bgg_id],OWNED[[#This Row],[bgg_id]]) -> 1 | E55: =_xlfn.XLOOKUP(OWNED[[#This Row],[bgg_id]],bgg_cache[id],bgg_cache[title]) -> Flipology | F55: =EXACT(OWNED[[#This Row],[name]],OWNED[[#This Row],[bgg_name]]) -> TRUE | G55: PARTY_ICEBREAKERS | H55: =_xlfn.XLOOKUP(OWNED[[#This Row],[bgg_id]],library_data[bgg_id],library_data[mana_meeple_category])=OWNED[[#This Row],[category]] -> TRUE | I55: =COUNTIF(nzdesgn[NAME],OWNED[[#This Row],[bgg_name]]) -> 1
A56: Floating Floors | B56: 334712 | D56: =COUNTIF(OWNED[bgg_id],OWNED[[#This Row],[bgg_id]]) -> 1 | E56: =_xlfn.XLOOKUP(OWNED[[#This Row],[bgg_id]],bgg_cache[id],bgg_cache[title]) -> Floating Floors | F56: =EXACT(OWNED[[#This Row],[name]],OWNED[[#This Row],[bgg_name]]) -> TRUE | G56: KIDS_FAMILIES | H56: =_xlfn.XLOOKUP(OWNED[[#This Row],[bgg_id]],library_data[bgg_id],library_data[mana_meeple_category])=OWNED[[#This Row],[category]] -> TRUE | I56: =COUNTIF(nzdesgn[NAME],OWNED[[#This Row],[bgg_name]]) -> 0
A57: Fluxx | B57: 258 | D57: =COUNTIF(OWNED[bgg_id],OWNED[[#This Row],[bgg_id]]) -> 1 | E57: =_xlfn.XLOOKUP(OWNED[[#This Row],[bgg_id]],bgg_cache[id],bgg_cache[title]) -> Fluxx | F57: =EXACT(OWNED[[#This Row],[name]],OWNED[[#This Row],[bgg_name]]) -> TRUE | G57: PARTY_ICEBREAKERS | H57: =_xlfn.XLOOKUP(OWNED[[#This Row],[bgg_id]],library_data[bgg_id],library_data[mana_meeple_category])=OWNED[[#This Row],[category]] -> TRUE | I57: =COUNTIF(nzdesgn[NAME],OWNED[[#This Row],[bgg_name]]) -> 0
A58: For Sale | B58: 172 | D58: =COUNTIF(OWNED[bgg_id],OWNED[[#This Row],[bgg_id]]) -> 1 | E58: =_xlfn.XLOOKUP(OWNED[[#This Row],[bgg_id]],bgg_cache[id],bgg_cache[title]) -> For Sale | F58: =EXACT(OWNED[[#This Row],[name]],OWNED[[#This Row],[bgg_name]]) -> TRUE | G58: PARTY_ICEBREAKERS | H58: =_xlfn.XLOOKUP(OWNED[[#This Row],[bgg_id]],library_data[bgg_id],library_data[mana_meeple_category])=OWNED[[#This Row],[category]] -> TRUE | I58: =COUNTIF(nzdesgn[NAME],OWNED[[#This Row],[bgg_name]]) -> 0
A59: Forbidden Island | B59: 65244 | D59: =COUNTIF(OWNED[bgg_id],OWNED[[#This Row],[bgg_id]]) -> 1 | E59: =_xlfn.XLOOKUP(OWNED[[#This Row],[bgg_id]],bgg_cache[id],bgg_cache[title]) -> Forbidden Island | F59: =EXACT(OWNED[[#This Row],[name]],OWNED[[#This Row],[bgg_name]]) -> TRUE | G59: COOP_ADVENTURE | H59: =_xlfn.XLOOKUP(OWNED[[#This Row],[bgg_id]],library_data[bgg_id],library_data[mana_meeple_category])=OWNED[[#This Row],[category]] -> TRUE | I59: =COUNTIF(nzdesgn[NAME],OWNED[[#This Row],[bgg_name]]) -> 0
A60: Forgotten Waters | B60: 302723 | C60: 1 | D60: =COUNTIF(OWNED[bgg_id],OWNED[[#This Row],[bgg_id]]) -> 1 | E60: =_xlfn.XLOOKUP(OWNED[[#This Row],[bgg_id]],bgg_cache[id],bgg_cache[title]) -> Forgotten Waters | F60: =EXACT(OWNED[[#This Row],[name]],OWNED[[#This Row],[bgg_name]]) -> TRUE | G60: COOP_ADVENTURE | H60: =_xlfn.XLOOKUP(OWNED[[#This Row],[bgg_id]],library_data[bgg_id],library_data[mana_meeple_category])=OWNED[[#This Row],[category]] -> TRUE | I60: =COUNTIF(nzdesgn[NAME],OWNED[[#This Row],[bgg_name]]) -> 0
A61: Fort | B61: 296912 | D61: =COUNTIF(OWNED[bgg_id],OWNED[[#This Row],[bgg_id]]) -> 1 | E61: =_xlfn.XLOOKUP(OWNED[[#This Row],[bgg_id]],bgg_cache[id],bgg_cache[title]) -> Fort | F61: =EXACT(OWNED[[#This Row],[name]],OWNED[[#This Row],[bgg_name]]) -> TRUE | G61: GATEWAY_STRATEGY | H61: =_xlfn.XLOOKUP(OWNED[[#This Row],[bgg_id]],library_data[bgg_id],library_data[mana_meeple_category])=OWNED[[#This Row],[category]] -> TRUE | I61: =COUNTIF(nzdesgn[NAME],OWNED[[#This Row],[bgg_name]]) -> 0
A62: Gardeners | B62: 361840 | D62: =COUNTIF(OWNED[bgg_id],OWNED[[#This Row],[bgg_id]]) -> 1 | E62: =_xlfn.XLOOKUP(OWNED[[#This Row],[bgg_id]],bgg_cache[id],bgg_cache[title]) -> Gardeners | F62: =EXACT(OWNED[[#This Row],[name]],OWNED[[#This Row],[bgg_name]]) -> TRUE | G62: COOP_ADVENTURE | H62: =_xlfn.XLOOKUP(OWNED[[#This Row],[bgg_id]],library_data[bgg_id],library_data[mana_meeple_category])=OWNED[[#This Row],[category]] -> TRUE | I62: =COUNTIF(nzdesgn[NAME],OWNED[[#This Row],[bgg_name]]) -> 0
A63: Give Me the Brain! | B63: 176 | D63: =COUNTIF(OWNED[bgg_id],OWNED[[#This Row],[bgg_id]]) -> 1 | E63: =_xlfn.XLOOKUP(OWNED[[#This Row],[bgg_id]],bgg_cache[id],bgg_cache[title]) -> Give Me the Brain! | F63: =EXACT(OWNED[[#This Row],[name]],OWNED[[#This Row],[bgg_name]]) -> TRUE | G63: PARTY_ICEBREAKERS | H63: =_xlfn.XLOOKUP(OWNED[[#This Row],[bgg_id]],library_data[bgg_id],library_data[mana_meeple_category])=OWNED[[#This Row],[category]] -> TRUE | I63: =COUNTIF(nzdesgn[NAME],OWNED[[#This Row],[bgg_name]]) -> 0
A64: Glimstone Grab | B64: 303929 | D64: =COUNTIF(OWNED[bgg_id],OWNED[[#This Row],[bgg_id]]) -> 1 | E64: =_xlfn.XLOOKUP(OWNED[[#This Row],[bgg_id]],bgg_cache[id],bgg_cache[title]) -> Glimstone Grab | F64: =EXACT(OWNED[[#This Row],[name]],OWNED[[#This Row],[bgg_name]]) -> TRUE | G64: KIDS_FAMILIES | H64: =_xlfn.XLOOKUP(OWNED[[#This Row],[bgg_id]],library_data[bgg_id],library_data[mana_meeple_category])=OWNED[[#This Row],[category]] -> TRUE | I64: =COUNTIF(nzdesgn[NAME],OWNED[[#This Row],[bgg_name]]) -> 1
A65: Gloomhaven | B65: 174430 | D65: =COUNTIF(OWNED[bgg_id],OWNED[[#This Row],[bgg_id]]) -> 1 | E65: =_xlfn.XLOOKUP(OWNED[[#This Row],[bgg_id]],bgg_cache[id],bgg_cache[title]) -> Gloomhaven | F65: =EXACT(OWNED[[#This Row],[name]],OWNED[[#This Row],[bgg_name]]) -> TRUE | G65: COOP_ADVENTURE | H65: =_xlfn.XLOOKUP(OWNED[[#This Row],[bgg_id]],library_data[bgg_id],library_data[mana_meeple_category])=OWNED[[#This Row],[category]] -> TRUE | I65: =COUNTIF(nzdesgn[NAME],OWNED[[#This Row],[bgg_name]]) -> 0
A66: Granny Wars: A Game of Tit for Tat | B66: 146765 | D66: =COUNTIF(OWNED[bgg_id],OWNED[[#This Row],[bgg_id]]) -> 1 | E66: =_xlfn.XLOOKUP(OWNED[[#This Row],[bgg_id]],bgg_cache[id],bgg_cache[title]) -> Granny Wars: A Game of Tit for Tat | F66: =EXACT(OWNED[[#This Row],[name]],OWNED[[#This Row],[bgg_name]]) -> TRUE | G66: PARTY_ICEBREAKERS | H66: =_xlfn.XLOOKUP(OWNED[[#This Row],[bgg_id]],library_data[bgg_id],library_data[mana_meeple_category])=OWNED[[#This Row],[category]] -> TRUE | I66: =COUNTIF(nzdesgn[NAME],OWNED[[#This Row],[bgg_name]]) -> 0
A67: Hanabi | B67: 98778 | D67: =COUNTIF(OWNED[bgg_id],OWNED[[#This Row],[bgg_id]]) -> 1 | E67: =_xlfn.XLOOKUP(OWNED[[#This Row],[bgg_id]],bgg_cache[id],bgg_cache[title]) -> Hanabi | F67: =EXACT(OWNED[[#This Row],[name]],OWNED[[#This Row],[bgg_name]]) -> TRUE | G67: COOP_ADVENTURE | H67: =_xlfn.XLOOKUP(OWNED[[#This Row],[bgg_id]],library_data[bgg_id],library_data[mana_meeple_category])=OWNED[[#This Row],[category]] -> TRUE | I67: =COUNTIF(nzdesgn[NAME],OWNED[[#This Row],[bgg_name]]) -> 0
A68: Heat: Pedal to the Metal | B68: 366013 | D68: =COUNTIF(OWNED[bgg_id],OWNED[[#This Row],[bgg_id]]) -> 1 | E68: =_xlfn.XLOOKUP(OWNED[[#This Row],[bgg_id]],bgg_cache[id],bgg_cache[title]) -> Heat: Pedal to the Metal | F68: =EXACT(OWNED[[#This Row],[name]],OWNED[[#This Row],[bgg_name]]) -> TRUE | G68: GATEWAY_STRATEGY | H68: =_xlfn.XLOOKUP(OWNED[[#This Row],[bgg_id]],library_data[bgg_id],library_data[mana_meeple_category])=OWNED[[#This Row],[category]] -> TRUE | I68: =COUNTIF(nzdesgn[NAME],OWNED[[#This Row],[bgg_name]]) -> 0
A69: Herd Mentality | B69: 311322 | D69: =COUNTIF(OWNED[bgg_id],OWNED[[#This Row],[bgg_id]]) -> 1 | E69: =_xlfn.XLOOKUP(OWNED[[#This Row],[bgg_id]],bgg_cache[id],bgg_cache[title]) -> Herd Mentality | F69: =EXACT(OWNED[[#This Row],[name]],OWNED[[#This Row],[bgg_name]]) -> TRUE | G69: PARTY_ICEBREAKERS | H69: =_xlfn.XLOOKUP(OWNED[[#This Row],[bgg_id]],library_data[bgg_id],library_data[mana_meeple_category])=OWNED[[#This Row],[category]] -> TRUE | I69: =COUNTIF(nzdesgn[NAME],OWNED[[#This Row],[bgg_name]]) -> 0
A70: Hive | B70: 2655 | D70: =COUNTIF(OWNED[bgg_id],OWNED[[#This Row],[bgg_id]]) -> 1 | E70: =_xlfn.XLOOKUP(OWNED[[#This Row],[bgg_id]],bgg_cache[id],bgg_cache[title]) -> Hive | F70: =EXACT(OWNED[[#This Row],[name]],OWNED[[#This Row],[bgg_name]]) -> TRUE | G70: GATEWAY_STRATEGY | H70: =_xlfn.XLOOKUP(OWNED[[#This Row],[bgg_id]],library_data[bgg_id],library_data[mana_meeple_category])=OWNED[[#This Row],[category]] -> TRUE | I70: =COUNTIF(nzdesgn[NAME],OWNED[[#This Row],[bgg_name]]) -> 0
A71: Hoard | B71: 180471 | D71: =COUNTIF(OWNED[bgg_id],OWNED[[#This Row],[bgg_id]]) -> 1 | E71: =_xlfn.XLOOKUP(OWNED[[#This Row],[bgg_id]],bgg_cache[id],bgg_cache[title]) -> Hoard | F71: =EXACT(OWNED[[#This Row],[name]],OWNED[[#This Row],[bgg_name]]) -> TRUE | G71: GATEWAY_STRATEGY | H71: =_xlfn.XLOOKUP(OWNED[[#This Row],[bgg_id]],library_data[bgg_id],library_data[mana_meeple_category])=OWNED[[#This Row],[category]] -> TRUE | I71: =COUNTIF(nzdesgn[NAME],OWNED[[#This Row],[bgg_name]]) -> 1
A72: Horrified | B72: 282524 | D72: =COUNTIF(OWNED[bgg_id],OWNED[[#This Row],[bgg_id]]) -> 1 | E72: =_xlfn.XLOOKUP(OWNED[[#This Row],[bgg_id]],bgg_cache[id],bgg_cache[title]) -> Horrified | F72: =EXACT(OWNED[[#This Row],[name]],OWNED[[#This Row],[bgg_name]]) -> TRUE | G72: COOP_ADVENTURE | H72: =_xlfn.XLOOKUP(OWNED[[#This Row],[bgg_id]],library_data[bgg_id],library_data[mana_meeple_category])=OWNED[[#This Row],[category]] -> TRUE | I72: =COUNTIF(nzdesgn[NAME],OWNED[[#This Row],[bgg_name]]) -> 0
... A83: Kingdomino Duel | B83: 281960 | D83: =COUNTIF(OWNED[bgg_id],OWNED[[#This Row],[bgg_id]]) -> 1 | E83: =_xlfn.XLOOKUP(OWNED[[#This Row],[bgg_id]],bgg_cache[id],bgg_cache[title]) -> Kingdomino Duel | F83: =EXACT(OWNED[[#This Row],[name]],OWNED[[#This Row],[bgg_name]]) -> TRUE | G83: GATEWAY_STRATEGY | H83: =_xlfn.XLOOKUP(OWNED[[#This Row],[bgg_id]],library_data[bgg_id],library_data[mana_meeple_category])=OWNED[[#This Row],[category]] -> TRUE | I83: =COUNTIF(nzdesgn[NAME],OWNED[[#This Row],[bgg_name]]) -> 0
A84: Kites | B84: 348096 | C84: 1 | D84: =COUNTIF(OWNED[bgg_id],OWNED[[#This Row],[bgg_id]]) -> 1 | E84: =_xlfn.XLOOKUP(OWNED[[#This Row],[bgg_id]],bgg_cache[id],bgg_cache[title]) -> Kites | F84: =EXACT(OWNED[[#This Row],[name]],OWNED[[#This Row],[bgg_name]]) -> TRUE | H84: =_xlfn.XLOOKUP(OWNED[[#This Row],[bgg_id]],library_data[bgg_id],library_data[mana_meeple_category])=OWNED[[#This Row],[category]] -> #N/A | I84: =COUNTIF(nzdesgn[NAME],OWNED[[#This Row],[bgg_name]]) -> 0
A85: KLASK | B85: 165722 | D85: =COUNTIF(OWNED[bgg_id],OWNED[[#This Row],[bgg_id]]) -> 1 | E85: =_xlfn.XLOOKUP(OWNED[[#This Row],[bgg_id]],bgg_cache[id],bgg_cache[title]) -> KLASK | F85: =EXACT(OWNED[[#This Row],[name]],OWNED[[#This Row],[bgg_name]]) -> TRUE | G85: KIDS_FAMILIES | H85: =_xlfn.XLOOKUP(OWNED[[#This Row],[bgg_id]],library_data[bgg_id],library_data[mana_meeple_category])=OWNED[[#This Row],[category]] -> TRUE | I85: =COUNTIF(nzdesgn[NAME],OWNED[[#This Row],[bgg_name]]) -> 0
A86: Komodo | B86: 124992 | D86: =COUNTIF(OWNED[bgg_id],OWNED[[#This Row],[bgg_id]]) -> 1 | E86: =_xlfn.XLOOKUP(OWNED[[#This Row],[bgg_id]],bgg_cache[id],bgg_cache[title]) -> Komodo | F86: =EXACT(OWNED[[#This Row],[name]],OWNED[[#This Row],[bgg_name]]) -> TRUE | G86: GATEWAY_STRATEGY | H86: =_xlfn.XLOOKUP(OWNED[[#This Row],[bgg_id]],library_data[bgg_id],library_data[mana_meeple_category])=OWNED[[#This Row],[category]] -> TRUE | I86: =COUNTIF(nzdesgn[NAME],OWNED[[#This Row],[bgg_name]]) -> 1
A87: Lanterns: The Harvest Festival | B87: 160851 | D87: =COUNTIF(OWNED[bgg_id],OWNED[[#This Row],[bgg_id]]) -> 1 | E87: =_xlfn.XLOOKUP(OWNED[[#This Row],[bgg_id]],bgg_cache[id],bgg_cache[title]) -> Lanterns: The Harvest Festival | F87: =EXACT(OWNED[[#This Row],[name]],OWNED[[#This Row],[bgg_name]]) -> TRUE | G87: GATEWAY_STRATEGY | H87: =_xlfn.XLOOKUP(OWNED[[#This Row],[bgg_id]],library_data[bgg_id],library_data[mana_meeple_category])=OWNED[[#This Row],[category]] -> TRUE | I87: =COUNTIF(nzdesgn[NAME],OWNED[[#This Row],[bgg_name]]) -> 0
A88: Leaping Lemmings | B88: 29687 | D88: =COUNTIF(OWNED[bgg_id],OWNED[[#This Row],[bgg_id]]) -> 1 | E88: =_xlfn.XLOOKUP(OWNED[[#This Row],[bgg_id]],bgg_cache[id],bgg_cache[title]) -> Leaping Lemmings | F88: =EXACT(OWNED[[#This Row],[name]],OWNED[[#This Row],[bgg_name]]) -> TRUE | G88: GATEWAY_STRATEGY | H88: =_xlfn.XLOOKUP(OWNED[[#This Row],[bgg_id]],library_data[bgg_id],library_data[mana_meeple_category])=OWNED[[#This Row],[category]] -> TRUE | I88: =COUNTIF(nzdesgn[NAME],OWNED[[#This Row],[bgg_name]]) -> 0
A89: Libertalia: Winds of Galecrest | B89: 356033 | D89: =COUNTIF(OWNED[bgg_id],OWNED[[#This Row],[bgg_id]]) -> 1 | E89: =_xlfn.XLOOKUP(OWNED[[#This Row],[bgg_id]],bgg_cache[id],bgg_cache[title]) -> Libertalia: Winds of Galecrest | F89: =EXACT(OWNED[[#This Row],[name]],OWNED[[#This Row],[bgg_name]]) -> TRUE | G89: CORE_STRATEGY | H89: =_xlfn.XLOOKUP(OWNED[[#This Row],[bgg_id]],library_data[bgg_id],library_data[mana_meeple_category])=OWNED[[#This Row],[category]] -> TRUE | I89: =COUNTIF(nzdesgn[NAME],OWNED[[#This Row],[bgg_name]]) -> 0
A90: Lindyhop | B90: 367829 | D90: =COUNTIF(OWNED[bgg_id],OWNED[[#This Row],[bgg_id]]) -> 1 | E90: =_xlfn.XLOOKUP(OWNED[[#This Row],[bgg_id]],bgg_cache[id],bgg_cache[title]) -> Lindyhop | F90: =EXACT(OWNED[[#This Row],[name]],OWNED[[#This Row],[bgg_name]]) -> TRUE | G90: PARTY_ICEBREAKERS | H90: =_xlfn.XLOOKUP(OWNED[[#This Row],[bgg_id]],library_data[bgg_id],library_data[mana_meeple_category])=OWNED[[#This Row],[category]] -> TRUE | I90: =COUNTIF(nzdesgn[NAME],OWNED[[#This Row],[bgg_name]]) -> 1
A91: Little Town | B91: 241266 | D91: =COUNTIF(OWNED[bgg_id],OWNED[[#This Row],[bgg_id]]) -> 1 | E91: =_xlfn.XLOOKUP(OWNED[[#This Row],[bgg_id]],bgg_cache[id],bgg_cache[title]) -> Little Town | F91: =EXACT(OWNED[[#This Row],[name]],OWNED[[#This Row],[bgg_name]]) -> TRUE | G91: GATEWAY_STRATEGY | H91: =_xlfn.XLOOKUP(OWNED[[#This Row],[bgg_id]],library_data[bgg_id],library_data[mana_meeple_category])=OWNED[[#This Row],[category]] -> TRUE | I91: =COUNTIF(nzdesgn[NAME],OWNED[[#This Row],[bgg_name]]) -> 0
A92: Long Shot: The Dice Game | B92: 295374 | D92: =COUNTIF(OWNED[bgg_id],OWNED[[#This Row],[bgg_id]]) -> 1 | E92: =_xlfn.XLOOKUP(OWNED[[#This Row],[bgg_id]],bgg_cache[id],bgg_cache[title]) -> Long Shot: The Dice Game | F92: =EXACT(OWNED[[#This Row],[name]],OWNED[[#This Row],[bgg_name]]) -> TRUE | G92: PARTY_ICEBREAKERS | H92: =_xlfn.XLOOKUP(OWNED[[#This Row],[bgg_id]],library_data[bgg_id],library_data[mana_meeple_category])=OWNED[[#This Row],[category]] -> TRUE | I92: =COUNTIF(nzdesgn[NAME],OWNED[[#This Row],[bgg_name]]) -> 0
A93: Lost Ruins of Arnak | B93: 312484 | C93: 1 | D93: =COUNTIF(OWNED[bgg_id],OWNED[[#This Row],[bgg_id]]) -> 1 | E93: =_xlfn.XLOOKUP(OWNED[[#This Row],[bgg_id]],bgg_cache[id],bgg_cache[title]) -> Lost Ruins of Arnak | F93: =EXACT(OWNED[[#This Row],[name]],OWNED[[#This Row],[bgg_name]]) -> TRUE | H93: =_xlfn.XLOOKUP(OWNED[[#This Row],[bgg_id]],library_data[bgg_id],library_data[mana_meeple_category])=OWNED[[#This Row],[category]] -> #N/A | I93: =COUNTIF(nzdesgn[NAME],OWNED[[#This Row],[bgg_name]]) -> 0
A94: Love Letter | B94: 277085 | D94: =COUNTIF(OWNED[bgg_id],OWNED[[#This Row],[bgg_id]]) -> 1 | E94: =_xlfn.XLOOKUP(OWNED[[#This Row],[bgg_id]],bgg_cache[id],bgg_cache[title]) -> Love Letter | F94: =EXACT(OWNED[[#This Row],[name]],OWNED[[#This Row],[bgg_name]]) -> TRUE | G94: PARTY_ICEBREAKERS | H94: =_xlfn.XLOOKUP(OWNED[[#This Row],[bgg_id]],library_data[bgg_id],library_data[mana_meeple_category])=OWNED[[#This Row],[category]] -> TRUE | I94: =COUNTIF(nzdesgn[NAME],OWNED[[#This Row],[bgg_name]]) -> 0
A95: Lunar | B95: 383452 | D95: =COUNTIF(OWNED[bgg_id],OWNED[[#This Row],[bgg_id]]) -> 1 | E95: =_xlfn.XLOOKUP(OWNED[[#This Row],[bgg_id]],bgg_cache[id],bgg_cache[title]) -> Lunar | F95: =EXACT(OWNED[[#This Row],[name]],OWNED[[#This Row],[bgg_name]]) -> TRUE | G95: GATEWAY_STRATEGY | H95: =_xlfn.XLOOKUP(OWNED[[#This Row],[bgg_id]],library_data[bgg_id],library_data[mana_meeple_category])=OWNED[[#This Row],[category]] -> TRUE | I95: =COUNTIF(nzdesgn[NAME],OWNED[[#This Row],[bgg_name]]) -> 0
A96: Mage Knight Board Game | B96: 96848 | D96: =COUNTIF(OWNED[bgg_id],OWNED[[#This Row],[bgg_id]]) -> 1 | E96: =_xlfn.XLOOKUP(OWNED[[#This Row],[bgg_id]],bgg_cache[id],bgg_cache[title]) -> Mage Knight Board Game | F96: =EXACT(OWNED[[#This Row],[name]],OWNED[[#This Row],[bgg_name]]) -> TRUE | G96: CORE_STRATEGY | H96: =_xlfn.XLOOKUP(OWNED[[#This Row],[bgg_id]],library_data[bgg_id],library_data[mana_meeple_category])=OWNED[[#This Row],[category]] -> TRUE | I96: =COUNTIF(nzdesgn[NAME],OWNED[[#This Row],[bgg_name]]) -> 0
A97: Magic Maze | B97: 209778 | D97: =COUNTIF(OWNED[bgg_id],OWNED[[#This Row],[bgg_id]]) -> 1 | E97: =_xlfn.XLOOKUP(OWNED[[#This Row],[bgg_id]],bgg_cache[id],bgg_cache[title]) -> Magic Maze | F97: =EXACT(OWNED[[#This Row],[name]],OWNED[[#This Row],[bgg_name]]) -> TRUE | G97: COOP_ADVENTURE | H97: =_xlfn.XLOOKUP(OWNED[[#This Row],[bgg_id]],library_data[bgg_id],library_data[mana_meeple_category])=OWNED[[#This Row],[category]] -> TRUE | I97: =COUNTIF(nzdesgn[NAME],OWNED[[#This Row],[bgg_name]]) -> 0
A98: Magic: The Gathering – Arena of the Planeswalkers | B98: 167698 | D98: =COUNTIF(OWNED[bgg_id],OWNED[[#This Row],[bgg_id]]) -> 1 | E98: =_xlfn.XLOOKUP(OWNED[[#This Row],[bgg_id]],bgg_cache[id],bgg_cache[title]) -> Magic: The Gathering – Arena of the Planeswalkers | F98: =EXACT(OWNED[[#This Row],[name]],OWNED[[#This Row],[bgg_name]]) -> TRUE | G98: CORE_STRATEGY | H98: =_xlfn.XLOOKUP(OWNED[[#This Row],[bgg_id]],library_data[bgg_id],library_data[mana_meeple_category])=OWNED[[#This Row],[category]] -> TRUE | I98: =COUNTIF(nzdesgn[NAME],OWNED[[#This Row],[bgg_name]]) -> 0
A99: Manifest | B99: 152471 | D99: =COUNTIF(OWNED[bgg_id],OWNED[[#This Row],[bgg_id]]) -> 1 | E99: =_xlfn.XLOOKUP(OWNED[[#This Row],[bgg_id]],bgg_cache[id],bgg_cache[title]) -> Manifest | F99: =EXACT(OWNED[[#This Row],[name]],OWNED[[#This Row],[bgg_name]]) -> TRUE | G99: CORE_STRATEGY | H99: =_xlfn.XLOOKUP(OWNED[[#This Row],[bgg_id]],library_data[bgg_id],library_data[mana_meeple_category])=OWNED[[#This Row],[category]] -> TRUE | I99: =COUNTIF(nzdesgn[NAME],OWNED[[#This Row],[bgg_name]]) -> 1
A100: Mansions of Madness: Second Edition | B100: 205059 | D100: =COUNTIF(OWNED[bgg_id],OWNED[[#This Row],[bgg_id]]) -> 1 | E100: =_xlfn.XLOOKUP(OWNED[[#This Row],[bgg_id]],bgg_cache[id],bgg_cache[title]) -> Mansions of Madness: Second Edition | F100: =EXACT(OWNED[[#This Row],[name]],OWNED[[#This Row],[bgg_name]]) -> TRUE | G100: COOP_ADVENTURE | H100: =_xlfn.XLOOKUP(OWNED[[#This Row],[bgg_id]],library_data[bgg_id],library_data[mana_meeple_category])=OWNED[[#This Row],[category]] -> TRUE | I100: =COUNTIF(nzdesgn[NAME],OWNED[[#This Row],[bgg_name]]) -> 0
A101: Meadow | B101: 314491 | D101: =COUNTIF(OWNED[bgg_id],OWNED[[#This Row],[bgg_id]]) -> 1 | E101: =_xlfn.XLOOKUP(OWNED[[#This Row],[bgg_id]],bgg_cache[id],bgg_cache[title]) -> Meadow | F101: =EXACT(OWNED[[#This Row],[name]],OWNED[[#This Row],[bgg_name]]) -> TRUE | G101: GATEWAY_STRATEGY | H101: =_xlfn.XLOOKUP(OWNED[[#This Row],[bgg_id]],library_data[bgg_id],library_data[mana_meeple_category])=OWNED[[#This Row],[category]] -> TRUE | I101: =COUNTIF(nzdesgn[NAME],OWNED[[#This Row],[bgg_name]]) -> 0
A102: Meeple Circus | B102: 193214 | D102: =COUNTIF(OWNED[bgg_id],OWNED[[#This Row],[bgg_id]]) -> 1 | E102: =_xlfn.XLOOKUP(OWNED[[#This Row],[bgg_id]],bgg_cache[id],bgg_cache[title]) -> Meeple Circus | F102: =EXACT(OWNED[[#This Row],[name]],OWNED[[#This Row],[bgg_name]]) -> TRUE | G102: KIDS_FAMILIES | H102: =_xlfn.XLOOKUP(OWNED[[#This Row],[bgg_id]],library_data[bgg_id],library_data[mana_meeple_category])=OWNED[[#This Row],[category]] -> TRUE | I102: =COUNTIF(nzdesgn[NAME],OWNED[[#This Row],[bgg_name]]) -> 0
A103: Mermaid Island | B103: 94486 | D103: =COUNTIF(OWNED[bgg_id],OWNED[[#This Row],[bgg_id]]) -> 1 | E103: =_xlfn.XLOOKUP(OWNED[[#This Row],[bgg_id]],bgg_cache[id],bgg_cache[title]) -> Mermaid Island | F103: =EXACT(OWNED[[#This Row],[name]],OWNED[[#This Row],[bgg_name]]) -> TRUE | G103: KIDS_FAMILIES | H103: =_xlfn.XLOOKUP(OWNED[[#This Row],[bgg_id]],library_data[bgg_id],library_data[mana_meeple_category])=OWNED[[#This Row],[category]] -> TRUE | I103: =COUNTIF(nzdesgn[NAME],OWNED[[#This Row],[bgg_name]]) -> 0
A104: Minecraft: Builders & Biomes | B104: 269603 | D104: =COUNTIF(OWNED[bgg_id],OWNED[[#This Row],[bgg_id]]) -> 1 | E104: =_xlfn.XLOOKUP(OWNED[[#This Row],[bgg_id]],bgg_cache[id],bgg_cache[title]) -> Minecraft: Builders & Biomes | F104: =EXACT(OWNED[[#This Row],[name]],OWNED[[#This Row],[bgg_name]]) -> TRUE | G104: GATEWAY_STRATEGY | H104: =_xlfn.XLOOKUP(OWNED[[#This Row],[bgg_id]],library_data[bgg_id],library_data[mana_meeple_category])=OWNED[[#This Row],[category]] -> TRUE | I104: =COUNTIF(nzdesgn[NAME],OWNED[[#This Row],[bgg_name]]) -> 0
A105: Modern Art | B105: 118 | D105: =COUNTIF(OWNED[bgg_id],OWNED[[#This Row],[bgg_id]]) -> 1 | E105: =_xlfn.XLOOKUP(OWNED[[#This Row],[bgg_id]],bgg_cache[id],bgg_cache[title]) -> Modern Art | F105: =EXACT(OWNED[[#This Row],[name]],OWNED[[#This Row],[bgg_name]]) -> TRUE | G105: GATEWAY_STRATEGY | H105: =_xlfn.XLOOKUP(OWNED[[#This Row],[bgg_id]],library_data[bgg_id],library_data[mana_meeple_category])=OWNED[[#This Row],[category]] -> TRUE | I105: =COUNTIF(nzdesgn[NAME],OWNED[[#This Row],[bgg_name]]) -> 0
A106: Monikers | B106: 156546 | C106: 1 | D106: =COUNTIF(OWNED[bgg_id],OWNED[[#This Row],[bgg_id]]) -> 1 | E106: =_xlfn.XLOOKUP(OWNED[[#This Row],[bgg_id]],bgg_cache[id],bgg_cache[title]) -> Monikers | F106: =EXACT(OWNED[[#This Row],[name]],OWNED[[#This Row],[bgg_name]]) -> TRUE | H106: =_xlfn.XLOOKUP(OWNED[[#This Row],[bgg_id]],library_data[bgg_id],library_data[mana_meeple_category])=OWNED[[#This Row],[category]] -> #N/A | I106: =COUNTIF(nzdesgn[NAME],OWNED[[#This Row],[bgg_name]]) -> 0
A107: My City | B107: 295486 | D107: =COUNTIF(OWNED[bgg_id],OWNED[[#This Row],[bgg_id]]) -> 1 | E107: =_xlfn.XLOOKUP(OWNED[[#This Row],[bgg_id]],bgg_cache[id],bgg_cache[title]) -> My City | F107: =EXACT(OWNED[[#This Row],[name]],OWNED[[#This Row],[bgg_name]]) -> TRUE | G107: GATEWAY_STRATEGY | H107: =_xlfn.XLOOKUP(OWNED[[#This Row],[bgg_id]],library_data[bgg_id],library_data[mana_meeple_category])=OWNED[[#This Row],[category]] -> TRUE | I107: =COUNTIF(nzdesgn[NAME],OWNED[[#This Row],[bgg_name]]) -> 0
A108: My First Bohnanza | B108: 171419 | D108: =COUNTIF(OWNED[bgg_id],OWNED[[#This Row],[bgg_id]]) -> 1 | E108: =_xlfn.XLOOKUP(OWNED[[#This Row],[bgg_id]],bgg_cache[id],bgg_cache[title]) -> My First Bohnanza | F108: =EXACT(OWNED[[#This Row],[name]],OWNED[[#This Row],[bgg_name]]) -> TRUE | G108: KIDS_FAMILIES | H108: =_xlfn.XLOOKUP(OWNED[[#This Row],[bgg_id]],library_data[bgg_id],library_data[mana_meeple_category])=OWNED[[#This Row],[category]] -> TRUE | I108: =COUNTIF(nzdesgn[NAME],OWNED[[#This Row],[bgg_name]]) -> 0
A109: My First Castle Panic | B109: 267314 | D109: =COUNTIF(OWNED[bgg_id],OWNED[[#This Row],[bgg_id]]) -> 1 | E109: =_xlfn.XLOOKUP(OWNED[[#This Row],[bgg_id]],bgg_cache[id],bgg_cache[title]) -> My First Castle Panic | F109: =EXACT(OWNED[[#This Row],[name]],OWNED[[#This Row],[bgg_name]]) -> TRUE | G109: KIDS_FAMILIES | H109: =_xlfn.XLOOKUP(OWNED[[#This Row],[bgg_id]],library_data[bgg_id],library_data[mana_meeple_category])=OWNED[[#This Row],[category]] -> TRUE | I109: =COUNTIF(nzdesgn[NAME],OWNED[[#This Row],[bgg_name]]) -> 0
A110: My First Stone Age | B110: 191004 | D110: =COUNTIF(OWNED[bgg_id],OWNED[[#This Row],[bgg_id]]) -> 1 | E110: =_xlfn.XLOOKUP(OWNED[[#This Row],[bgg_id]],bgg_cache[id],bgg_cache[title]) -> My First Stone Age | F110: =EXACT(OWNED[[#This Row],[name]],OWNED[[#This Row],[bgg_name]]) -> TRUE | G110: KIDS_FAMILIES | H110: =_xlfn.XLOOKUP(OWNED[[#This Row],[bgg_id]],library_data[bgg_id],library_data[mana_meeple_category])=OWNED[[#This Row],[category]] -> TRUE | I110: =COUNTIF(nzdesgn[NAME],OWNED[[#This Row],[bgg_name]]) -> 0
...

Sheet BUY LIST
A1: RANK | B1: NAME | C1: Column1 | D1: BGG ID | E1: LPG_Status | F1: LPG_RRP | G1: Low | H1: Mean | I1: BEST | J1: Discount | K1: Delta | L1: QF | M1: STORE | N1: BGO LINK | O1: HAVE | P1: DUP
A2: 1 | B2: =IFERROR(_xlfn.XLOOKUP(BUYLIST10[[#This Row],[BGG ID]],bgg_cache[id],bgg_cache[title]),_xlfn.XLOOKUP(BUYLIST10[[#This Row],[BGG ID]],manual_bgg!B:B,manual_bgg!D:D)) -> Terraforming Mars | C2: =_xlfn.IMAGE(_xlfn.XLOOKUP(BUYLIST10[[#This Row],[BGG ID]],bgg_cache[id],bgg_cache[thumbnail_url]),,3,80) -> #VALUE! | D2: 167791 | E2: =_xlfn.XLOOKUP(BUYLIST10[[#This Row],[BGG ID]],STOREURL[BGG ID],STOREURL[STATUS]) -> AVAILABLE | F2: =_xlfn.XLOOKUP(BUYLIST10[[#This Row],[BGG ID]],STOREURL[BGG ID],STOREURL[LPG_RRP]) -> 179.99 | G2: =_xlfn.XLOOKUP(BUYLIST10[[#This Row],[NAME]],summary_prices[game],summary_prices[site_low_nzd]) -> 99 | H2: =_xlfn.XLOOKUP(BUYLIST10[[#This Row],[NAME]],summary_prices[game],summary_prices[site_mean_nzd]) -> 148.06 | I2: =_xlfn.XLOOKUP(BUYLIST10[[#This Row],[NAME]],summary_prices[game],summary_prices[best_in_stock_nzd]) -> 124.9 | J2: =IFERROR(_xlfn.XLOOKUP(BUYLIST10[[#This Row],[NAME]],summary_prices[game],summary_prices[discount_pct_vs_site_mean]),-99) -> 15.64 | K2: =_xlfn.XLOOKUP(BUYLIST10[[#This Row],[NAME]],summary_prices[game],summary_prices[delta_vs_site_disc_mean_pp]) -> -17.5 | L2: {=_xlfn.LET( _xlpm.b, BUYLIST10[[#This Row],[BEST]], _xlpm.s, BUYLIST10[[#This Row],[LPG_Status]], _xlpm.r, BUYLIST10[[#This Row],[LPG_RRP]], _xlpm.d, BUYLIST10[[#This Row],[Discount]], OR( AND( OR(_xlpm.s={"AVAILABLE","BACK_ORDER"}), IF(ISNUMBER(_xlpm.b), AND(_xlpm.b<>0, _xlpm.b*2<=_xlpm.r), FALSE) ), AND( OR(_xlpm.s={"NOT_FOUND","BACK_ORDER_OOS"}), _xlpm.d>30 ) ) )} -> FALSE | M2: =_xlfn.XLOOKUP(BUYLIST10[[#This Row],[NAME]],summary_prices[game],summary_prices[best_in_stock_store]) -> Vagabond | N2: =HYPERLINK(_xlfn.XLOOKUP(BUYLIST10[[#This Row],[BGG ID]],STOREURL[BGG ID],STOREURL[BGO LINK])) -> https://www.boardgameoracle.com/en-NZ/boardgame/price/DJXkZt9Z_z/terraforming-mars | O2: =COUNTIF(OWNED[bgg_id],BUYLIST10[[#This Row],[BGG ID]]) -> 0 | P2: =COUNTIF(BUYLIST10[NAME],BUYLIST10[[#This Row],[NAME]]) -> 1
A3: 2 | B3: =IFERROR(_xlfn.XLOOKUP(BUYLIST10[[#This Row],[BGG ID]],bgg_cache[id],bgg_cache[title]),_xlfn.XLOOKUP(BUYLIST10[[#This Row],[BGG ID]],manual_bgg!B:B,manual_bgg!D:D)) -> Ark Nova | C3: =_xlfn.IMAGE(_xlfn.XLOOKUP(BUYLIST10[[#This Row],[BGG ID]],bgg_cache[id],bgg_cache[thumbnail_url]),,3,80) -> #VALUE! | D3: 342942 | E3: =_xlfn.XLOOKUP(BUYLIST10[[#This Row],[BGG ID]],STOREURL[BGG ID],STOREURL[STATUS]) -> AVAILABLE | F3: =_xlfn.XLOOKUP(BUYLIST10[[#This Row],[BGG ID]],STOREURL[BGG ID],STOREURL[LPG_RRP]) -> 164.99 | G3: =_xlfn.XLOOKUP(BUYLIST10[[#This Row],[NAME]],summary_prices[game],summary_prices[site_low_nzd]) -> 98 | H3: =_xlfn.XLOOKUP(BUYLIST10[[#This Row],[NAME]],summary_prices[game],summary_prices[site_mean_nzd]) -> 152.01 | I3: =_xlfn.XLOOKUP(BUYLIST10[[#This Row],[NAME]],summary_prices[game],summary_prices[best_in_stock_nzd]) -> 98 | J3: =IFERROR(_xlfn.XLOOKUP(BUYLIST10[[#This Row],[NAME]],summary_prices[game],summary_prices[discount_pct_vs_site_mean]),-99) -> 35.53 | K3: =_xlfn.XLOOKUP(BUYLIST10[[#This Row],[NAME]],summary_prices[game],summary_prices[delta_vs_site_disc_mean_pp]) -> 0 | L3: {=_xlfn.LET( _xlpm.b, BUYLIST10[[#This Row],[BEST]], _xlpm.s, BUYLIST10[[#This Row],[LPG_Status]], _xlpm.r, BUYLIST10[[#This Row],[LPG_RRP]], _xlpm.d, BUYLIST10[[#This Row],[Discount]], OR( AND( OR(_xlpm.s={"AVAILABLE","BACK_ORDER"}), IF(ISNUMBER(_xlpm.b), AND(_xlpm.b<>0, _xlpm.b*2<=_xlpm.r), FALSE) ), AND( OR(_xlpm.s={"NOT_FOUND","BACK_ORDER_OOS"}), _xlpm.d>30 ) ) )} -> FALSE | M3: =_xlfn.XLOOKUP(BUYLIST10[[#This Row],[NAME]],summary_prices[game],summary_prices[best_in_stock_store]) -> EB Games NZ | N3: =HYPERLINK(_xlfn.XLOOKUP(BUYLIST10[[#This Row],[BGG ID]],STOREURL[BGG ID],STOREURL[BGO LINK])) -> https://www.boardgameoracle.com/en-NZ/boardgame/price/yKEg3oOK67/ark-nova | O3: =COUNTIF(OWNED[bgg_id],BUYLIST10[[#This Row],[BGG ID]]) -> 0 | P3: =COUNTIF(BUYLIST10[NAME],BUYLIST10[[#This Row],[NAME]]) -> 1
A4: 3 | B4: =IFERROR(_xlfn.XLOOKUP(BUYLIST10[[#This Row],[BGG ID]],bgg_cache[id],bgg_cache[title]),_xlfn.XLOOKUP(BUYLIST10[[#This Row],[BGG ID]],manual_bgg!B:B,manual_bgg!D:D)) -> Dune: Imperium – Uprising | C4: =_xlfn.IMAGE(_xlfn.XLOOKUP(BUYLIST10[[#This Row],[BGG ID]],bgg_cache[id],bgg_cache[thumbnail_url]),,3,80) -> #VALUE! | D4: 397598 | E4: =_xlfn.XLOOKUP(BUYLIST10[[#This Row],[BGG ID]],STOREURL[BGG ID],STOREURL[STATUS]) -> AVAILABLE | F4: =_xlfn.XLOOKUP(BUYLIST10[[#This Row],[BGG ID]],STOREURL[BGG ID],STOREURL[LPG_RRP]) -> 134.99 | G4: =_xlfn.XLOOKUP(BUYLIST10[[#This Row],[NAME]],summary_prices[game],summary_prices[site_low_nzd]) -> 108.47 | H4: =_xlfn.XLOOKUP(BUYLIST10[[#This Row],[NAME]],summary_prices[game],summary_prices[site_mean_nzd]) -> 129.56 | I4: =_xlfn.XLOOKUP(BUYLIST10[[#This Row],[NAME]],summary_prices[game],summary_prices[best_in_stock_nzd]) -> 109.1 | J4: =IFERROR(_xlfn.XLOOKUP(BUYLIST10[[#This Row],[NAME]],summary_prices[game],summary_prices[discount_pct_vs_site_mean]),-99) -> 15.79 | K4: =_xlfn.XLOOKUP(BUYLIST10[[#This Row],[NAME]],summary_prices[game],summary_prices[delta_vs_site_disc_mean_pp]) -> -0.49 | L4: {=_xlfn.LET( _xlpm.b, BUYLIST10[[#This Row],[BEST]], _xlpm.s, BUYLIST10[[#This Row],[LPG_Status]], _xlpm.r, BUYLIST10[[#This Row],[LPG_RRP]], _xlpm.d, BUYLIST10[[#This Row],[Discount]], OR( AND( OR(_xlpm.s={"AVAILABLE","BACK_ORDER"}), IF(ISNUMBER(_xlpm.b), AND(_xlpm.b<>0, _xlpm.b*2<=_xlpm.r), FALSE) ), AND( OR(_xlpm.s={"NOT_FOUND","BACK_ORDER_OOS"}), _xlpm.d>30 ) ) )} -> FALSE | M4: =_xlfn.XLOOKUP(BUYLIST10[[#This Row],[NAME]],summary_prices[game],summary_prices[best_in_stock_store]) -> Gameology | N4: =HYPERLINK(_xlfn.XLOOKUP(BUYLIST10[[#This Row],[BGG ID]],STOREURL[BGG ID],STOREURL[BGO LINK])) -> https://www.boardgameoracle.com/en-NZ/boardgame/price/NfBhb2GnXh/dune-imperium-uprising | O4: =COUNTIF(OWNED[bgg_id],BUYLIST10[[#This Row],[BGG ID]]) -> 0 | P4: =COUNTIF(BUYLIST10[NAME],BUYLIST10[[#This Row],[NAME]]) -> 1
A5: 4 | B5: =IFERROR(_xlfn.XLOOKUP(BUYLIST10[[#This Row],[BGG ID]],bgg_cache[id],bgg_cache[title]),_xlfn.XLOOKUP(BUYLIST10[[#This Row],[BGG ID]],manual_bgg!B:B,manual_bgg!D:D)) -> Brass: Birmingham | C5: =_xlfn.IMAGE(_xlfn.XLOOKUP(BUYLIST10[[#This Row],[BGG ID]],bgg_cache[id],bgg_cache[thumbnail_url]),,3,80) -> #VALUE! | D5: 224517 | E5: =_xlfn.XLOOKUP(BUYLIST10[[#This Row],[BGG ID]],STOREURL[BGG ID],STOREURL[STATUS]) -> AVAILABLE | F5: =_xlfn.XLOOKUP(BUYLIST10[[#This Row],[BGG ID]],STOREURL[BGG ID],STOREURL[LPG_RRP]) -> 179.99 | G5: =_xlfn.XLOOKUP(BUYLIST10[[#This Row],[NAME]],summary_prices[game],summary_prices[site_low_nzd]) -> 110 | H5: =_xlfn.XLOOKUP(BUYLIST10[[#This Row],[NAME]],summary_prices[game],summary_prices[site_mean_nzd]) -> 167.53 | I5: =_xlfn.XLOOKUP(BUYLIST10[[#This Row],[NAME]],summary_prices[game],summary_prices[best_in_stock_nzd]) -> 137.99 | J5: =IFERROR(_xlfn.XLOOKUP(BUYLIST10[[#This Row],[NAME]],summary_prices[game],summary_prices[discount_pct_vs_site_mean]),-99) -> 17.63 | K5: =_xlfn.XLOOKUP(BUYLIST10[[#This Row],[NAME]],summary_prices[game],summary_prices[delta_vs_site_disc_mean_pp]) -> -16.71 | L5: {=_xlfn.LET( _xlpm.b, BUYLIST10[[#This Row],[BEST]], _xlpm.s, BUYLIST10[[#This Row],[LPG_Status]], _xlpm.r, BUYLIST10[[#This Row],[LPG_RRP]], _xlpm.d, BUYLIST10[[#This Row],[Discount]], OR( AND( OR(_xlpm.s={"AVAILABLE","BACK_ORDER"}), IF(ISNUMBER(_xlpm.b), AND(_xlpm.b<>0, _xlpm.b*2<=_xlpm.r), FALSE) ), AND( OR(_xlpm.s={"NOT_FOUND","BACK_ORDER_OOS"}), _xlpm.d>30 ) ) )} -> FALSE | M5: =_xlfn.XLOOKUP(BUYLIST10[[#This Row],[NAME]],summary_prices[game],summary_prices[best_in_stock_store]) -> The Board Gamer NZ | N5: =HYPERLINK(_xlfn.XLOOKUP(BUYLIST10[[#This Row],[BGG ID]],STOREURL[BGG ID],STOREURL[BGO LINK])) -> https://www.boardgameoracle.com/en-NZ/boardgame/price/K2tNPgSWOC/brass-birmingham | O5: =COUNTIF(OWNED[bgg_id],BUYLIST10[[#This Row],[BGG ID]]) -> 0 | P5: =COUNTIF(BUYLIST10[NAME],BUYLIST10[[#This Row],[NAME]]) -> 1
A6: 5 | B6: =IFERROR(_xlfn.XLOOKUP(BUYLIST10[[#This Row],[BGG ID]],bgg_cache[id],bgg_cache[title]),_xlfn.XLOOKUP(BUYLIST10[[#This Row],[BGG ID]],manual_bgg!B:B,manual_bgg!D:D)) -> Spirit Island | C6: =_xlfn.IMAGE(_xlfn.XLOOKUP(BUYLIST10[[#This Row],[BGG ID]],bgg_cache[id],bgg_cache[thumbnail_url]),,3,80) -> #VALUE! | D6: 162886 | E6: =_xlfn.XLOOKUP(BUYLIST10[[#This Row],[BGG ID]],STOREURL[BGG ID],STOREURL[STATUS]) -> AVAILABLE | F6: =_xlfn.XLOOKUP(BUYLIST10[[#This Row],[BGG ID]],STOREURL[BGG ID],STOREURL[LPG_RRP]) -> 194.99 | G6: =_xlfn.XLOOKUP(BUYLIST10[[#This Row],[NAME]],summary_prices[game],summary_prices[site_low_nzd]) -> 142.75 | H6: =_xlfn.XLOOKUP(BUYLIST10[[#This Row],[NAME]],summary_prices[game],summary_prices[site_mean_nzd]) -> 183.72 | I6: =_xlfn.XLOOKUP(BUYLIST10[[#This Row],[NAME]],summary_prices[game],summary_prices[best_in_stock_nzd]) -> 143.57 | J6: =IFERROR(_xlfn.XLOOKUP(BUYLIST10[[#This Row],[NAME]],summary_prices[game],summary_prices[discount_pct_vs_site_mean]),-99) -> 21.85 | K6: =_xlfn.XLOOKUP(BUYLIST10[[#This Row],[NAME]],summary_prices[game],summary_prices[delta_vs_site_disc_mean_pp]) -> -0.45 | L6: {=_xlfn.LET( _xlpm.b, BUYLIST10[[#This Row],[BEST]], _xlpm.s, BUYLIST10[[#This Row],[LPG_Status]], _xlpm.r, BUYLIST10[[#This Row],[LPG_RRP]], _xlpm.d, BUYLIST10[[#This Row],[Discount]], OR( AND( OR(_xlpm.s={"AVAILABLE","BACK_ORDER"}), IF(ISNUMBER(_xlpm.b), AND(_xlpm.b<>0, _xlpm.b*2<=_xlpm.r), FALSE) ), AND( OR(_xlpm.s={"NOT_FOUND","BACK_ORDER_OOS"}), _xlpm.d>30 ) ) )} -> FALSE | M6: =_xlfn.XLOOKUP(BUYLIST10[[#This Row],[NAME]],summary_prices[game],summary_prices[best_in_stock_store]) -> Gameology | N6: =HYPERLINK(_xlfn.XLOOKUP(BUYLIST10[[#This Row],[BGG ID]],STOREURL[BGG ID],STOREURL[BGO LINK])) -> https://www.boardgameoracle.com/en-NZ/boardgame/price/dqzBAt2yEb/spirit-island | O6: =COUNTIF(OWNED[bgg_id],BUYLIST10[[#This Row],[BGG ID]]) -> 0 | P6: =COUNTIF(BUYLIST10[NAME],BUYLIST10[[#This Row],[NAME]]) -> 1
A7: 6 | B7: =IFERROR(_xlfn.XLOOKUP(BUYLIST10[[#This Row],[BGG ID]],bgg_cache[id],bgg_cache[title]),_xlfn.XLOOKUP(BUYLIST10[[#This Row],[BGG ID]],manual_bgg!B:B,manual_bgg!D:D)) -> Concordia | C7: =_xlfn.IMAGE(_xlfn.XLOOKUP(BUYLIST10[[#This Row],[BGG ID]],bgg_cache[id],bgg_cache[thumbnail_url]),,3,80) -> #VALUE! | D7: 124361 | E7: =_xlfn.XLOOKUP(BUYLIST10[[#This Row],[BGG ID]],STOREURL[BGG ID],STOREURL[STATUS]) -> AVAILABLE | F7: =_xlfn.XLOOKUP(BUYLIST10[[#This Row],[BGG ID]],STOREURL[BGG ID],STOREURL[LPG_RRP]) -> 144.99 | G7: =_xlfn.XLOOKUP(BUYLIST10[[#This Row],[NAME]],summary_prices[game],summary_prices[site_low_nzd]) -> 110.12 | H7: =_xlfn.XLOOKUP(BUYLIST10[[#This Row],[NAME]],summary_prices[game],summary_prices[site_mean_nzd]) -> 129.75 | I7: =_xlfn.XLOOKUP(BUYLIST10[[#This Row],[NAME]],summary_prices[game],summary_prices[best_in_stock_nzd]) -> 110.87 | J7: =IFERROR(_xlfn.XLOOKUP(BUYLIST10[[#This Row],[NAME]],summary_prices[game],summary_prices[discount_pct_vs_site_mean]),-99) -> 14.55 | K7: =_xlfn.XLOOKUP(BUYLIST10[[#This Row],[NAME]],summary_prices[game],summary_prices[delta_vs_site_disc_mean_pp]) -> -0.58 | L7: {=_xlfn.LET( _xlpm.b, BUYLIST10[[#This Row],[BEST]], _xlpm.s, BUYLIST10[[#This Row],[LPG_Status]], _xlpm.r, BUYLIST10[[#This Row],[LPG_RRP]], _xlpm.d, BUYLIST10[[#This Row],[Discount]], OR( AND( OR(_xlpm.s={"AVAILABLE","BACK_ORDER"}), IF(ISNUMBER(_xlpm.b), AND(_xlpm.b<>0, _xlpm.b*2<=_xlpm.r), FALSE) ), AND( OR(_xlpm.s={"NOT_FOUND","BACK_ORDER_OOS"}), _xlpm.d>30 ) ) )} -> FALSE | M7: =_xlfn.XLOOKUP(BUYLIST10[[#This Row],[NAME]],summary_prices[game],summary_prices[best_in_stock_store]) -> Amazon AU | N7: =HYPERLINK(_xlfn.XLOOKUP(BUYLIST10[[#This Row],[BGG ID]],STOREURL[BGG ID],STOREURL[BGO LINK])) -> https://www.boardgameoracle.com/en-NZ/boardgame/price/lWFkM-ljpv/concordia | O7: =COUNTIF(OWNED[bgg_id],BUYLIST10[[#This Row],[BGG ID]]) -> 0 | P7: =COUNTIF(BUYLIST10[NAME],BUYLIST10[[#This Row],[NAME]]) -> 1
A8: 7 | B8: =IFERROR(_xlfn.XLOOKUP(BUYLIST10[[#This Row],[BGG ID]],bgg_cache[id],bgg_cache[title]),_xlfn.XLOOKUP(BUYLIST10[[#This Row],[BGG ID]],manual_bgg!B:B,manual_bgg!D:D)) -> Great Western Trail: New Zealand | C8: =_xlfn.IMAGE(_xlfn.XLOOKUP(BUYLIST10[[#This Row],[BGG ID]],bgg_cache[id],bgg_cache[thumbnail_url]),,3,80) -> #VALUE! | D8: 380607 | E8: =_xlfn.XLOOKUP(BUYLIST10[[#This Row],[BGG ID]],STOREURL[BGG ID],STOREURL[STATUS]) -> NOT_FOUND | F8: =_xlfn.XLOOKUP(BUYLIST10[[#This Row],[BGG ID]],STOREURL[BGG ID],STOREURL[LPG_RRP]) -> 0 | G8: =_xlfn.XLOOKUP(BUYLIST10[[#This Row],[NAME]],summary_prices[game],summary_prices[site_low_nzd]) -> 101.25 | H8: =_xlfn.XLOOKUP(BUYLIST10[[#This Row],[NAME]],summary_prices[game],summary_prices[site_mean_nzd]) -> 137.73 | I8: =_xlfn.XLOOKUP(BUYLIST10[[#This Row],[NAME]],summary_prices[game],summary_prices[best_in_stock_nzd]) -> 120.59 | J8: =IFERROR(_xlfn.XLOOKUP(BUYLIST10[[#This Row],[NAME]],summary_prices[game],summary_prices[discount_pct_vs_site_mean]),-99) -> 12.44 | K8: =_xlfn.XLOOKUP(BUYLIST10[[#This Row],[NAME]],summary_prices[game],summary_prices[delta_vs_site_disc_mean_pp]) -> -14.04 | L8: {=_xlfn.LET( _xlpm.b, BUYLIST10[[#This Row],[BEST]], _xlpm.s, BUYLIST10[[#This Row],[LPG_Status]], _xlpm.r, BUYLIST10[[#This Row],[LPG_RRP]], _xlpm.d, BUYLIST10[[#This Row],[Discount]], OR( AND( OR(_xlpm.s={"AVAILABLE","BACK_ORDER"}), IF(ISNUMBER(_xlpm.b), AND(_xlpm.b<>0, _xlpm.b*2<=_xlpm.r), FALSE) ), AND( OR(_xlpm.s={"NOT_FOUND","BACK_ORDER_OOS"}), _xlpm.d>30 ) ) )} -> FALSE | M8: =_xlfn.XLOOKUP(BUYLIST10[[#This Row],[NAME]],summary_prices[game],summary_prices[best_in_stock_store]) -> Gameology | N8: =HYPERLINK(_xlfn.XLOOKUP(BUYLIST10[[#This Row],[BGG ID]],STOREURL[BGG ID],STOREURL[BGO LINK])) -> https://www.boardgameoracle.com/en-NZ/boardgame/price/pDrG0cjAJY/great-western-trail-new-zealand | O8: =COUNTIF(OWNED[bgg_id],BUYLIST10[[#This Row],[BGG ID]]) -> 0 | P8: =COUNTIF(BUYLIST10[NAME],BUYLIST10[[#This Row],[NAME]]) -> 1
A9: 8 | B9: =IFERROR(_xlfn.XLOOKUP(BUYLIST10[[#This Row],[BGG ID]],bgg_cache[id],bgg_cache[title]),_xlfn.XLOOKUP(BUYLIST10[[#This Row],[BGG ID]],manual_bgg!B:B,manual_bgg!D:D)) -> Quacks | C9: =_xlfn.IMAGE(_xlfn.XLOOKUP(BUYLIST10[[#This Row],[BGG ID]],bgg_cache[id],bgg_cache[thumbnail_url]),,3,80) -> #VALUE! | D9: 244521 | E9: =_xlfn.XLOOKUP(BUYLIST10[[#This Row],[BGG ID]],STOREURL[BGG ID],STOREURL[STATUS]) -> AVAILABLE | F9: =_xlfn.XLOOKUP(BUYLIST10[[#This Row],[BGG ID]],STOREURL[BGG ID],STOREURL[LPG_RRP]) -> 139.99 | G9: =_xlfn.XLOOKUP(BUYLIST10[[#This Row],[NAME]],summary_prices[game],summary_prices[site_low_nzd]) -> 79 | H9: =_xlfn.XLOOKUP(BUYLIST10[[#This Row],[NAME]],summary_prices[game],summary_prices[site_mean_nzd]) -> 95.66 | I9: =_xlfn.XLOOKUP(BUYLIST10[[#This Row],[NAME]],summary_prices[game],summary_prices[best_in_stock_nzd]) -> 80.37 | J9: =IFERROR(_xlfn.XLOOKUP(BUYLIST10[[#This Row],[NAME]],summary_prices[game],summary_prices[discount_pct_vs_site_mean]),-99) -> 15.98 | K9: =_xlfn.XLOOKUP(BUYLIST10[[#This Row],[NAME]],summary_prices[game],summary_prices[delta_vs_site_disc_mean_pp]) -> -1.43 | L9: {=_xlfn.LET( _xlpm.b, BUYLIST10[[#This Row],[BEST]], _xlpm.s, BUYLIST10[[#This Row],[LPG_Status]], _xlpm.r, BUYLIST10[[#This Row],[LPG_RRP]], _xlpm.d, BUYLIST10[[#This Row],[Discount]], OR( AND( OR(_xlpm.s={"AVAILABLE","BACK_ORDER"}), IF(ISNUMBER(_xlpm.b), AND(_xlpm.b<>0, _xlpm.b*2<=_xlpm.r), FALSE) ), AND( OR(_xlpm.s={"NOT_FOUND","BACK_ORDER_OOS"}), _xlpm.d>30 ) ) )} -> FALSE | M9: =_xlfn.XLOOKUP(BUYLIST10[[#This Row],[NAME]],summary_prices[game],summary_prices[best_in_stock_store]) -> Gameology | N9: =HYPERLINK(_xlfn.XLOOKUP(BUYLIST10[[#This Row],[BGG ID]],STOREURL[BGG ID],STOREURL[BGO LINK])) -> https://www.boardgameoracle.com/en-NZ/boardgame/price/bD0EsHvlcZ/quacks | O9: =COUNTIF(OWNED[bgg_id],BUYLIST10[[#This Row],[BGG ID]]) -> 0 | P9: =COUNTIF(BUYLIST10[NAME],BUYLIST10[[#This Row],[NAME]]) -> 1
A10: 9 | B10: =IFERROR(_xlfn.XLOOKUP(BUYLIST10[[#This Row],[BGG ID]],bgg_cache[id],bgg_cache[title]),_xlfn.XLOOKUP(BUYLIST10[[#This Row],[BGG ID]],manual_bgg!B:B,manual_bgg!D:D)) -> Everdell | C10: =_xlfn.IMAGE(_xlfn.XLOOKUP(BUYLIST10[[#This Row],[BGG ID]],bgg_cache[id],bgg_cache[thumbnail_url]),,3,80) -> #VALUE! | D10: 199792 | E10: =_xlfn.XLOOKUP(BUYLIST10[[#This Row],[BGG ID]],STOREURL[BGG ID],STOREURL[STATUS]) -> AVAILABLE | F10: =_xlfn.XLOOKUP(BUYLIST10[[#This Row],[BGG ID]],STOREURL[BGG ID],STOREURL[LPG_RRP]) -> 159.99 | G10: =_xlfn.XLOOKUP(BUYLIST10[[#This Row],[NAME]],summary_prices[game],summary_prices[site_low_nzd]) -> 95.76 | H10: =_xlfn.XLOOKUP(BUYLIST10[[#This Row],[NAME]],summary_prices[game],summary_prices[site_mean_nzd]) -> 136.37 | I10: =_xlfn.XLOOKUP(BUYLIST10[[#This Row],[NAME]],summary_prices[game],summary_prices[best_in_stock_nzd]) -> 114.27 | J10: =IFERROR(_xlfn.XLOOKUP(BUYLIST10[[#This Row],[NAME]],summary_prices[game],summary_prices[discount_pct_vs_site_mean]),-99) -> 16.21 | K10: =_xlfn.XLOOKUP(BUYLIST10[[#This Row],[NAME]],summary_prices[game],summary_prices[delta_vs_site_disc_mean_pp]) -> -13.57 | L10: {=_xlfn.LET( _xlpm.b, BUYLIST10[[#This Row],[BEST]], _xlpm.s, BUYLIST10[[#This Row],[LPG_Status]], _xlpm.r, BUYLIST10[[#This Row],[LPG_RRP]], _xlpm.d, BUYLIST10[[#This Row],[Discount]], OR( AND( OR(_xlpm.s={"AVAILABLE","BACK_ORDER"}), IF(ISNUMBER(_xlpm.b), AND(_xlpm.b<>0, _xlpm.b*2<=_xlpm.r), FALSE) ), AND( OR(_xlpm.s={"NOT_FOUND","BACK_ORDER_OOS"}), _xlpm.d>30 ) ) )} -> FALSE | M10: =_xlfn.XLOOKUP(BUYLIST10[[#This Row],[NAME]],summary_prices[game],summary_prices[best_in_stock_store]) -> Gameology | N10: =HYPERLINK(_xlfn.XLOOKUP(BUYLIST10[[#This Row],[BGG ID]],STOREURL[BGG ID],STOREURL[BGO LINK])) -> https://www.boardgameoracle.com/en-NZ/boardgame/price/vhcYsCqPMP/everdell | O10: =COUNTIF(OWNED[bgg_id],BUYLIST10[[#This Row],[BGG ID]]) -> 0 | P10: =COUNTIF(BUYLIST10[NAME],BUYLIST10[[#This Row],[NAME]]) -> 1
A11: 10 | B11: =IFERROR(_xlfn.XLOOKUP(BUYLIST10[[#This Row],[BGG ID]],bgg_cache[id],bgg_cache[title]),_xlfn.XLOOKUP(BUYLIST10[[#This Row],[BGG ID]],manual_bgg!B:B,manual_bgg!D:D)) -> Clank!: A Deck-Building Adventure | C11: =_xlfn.IMAGE(_xlfn.XLOOKUP(BUYLIST10[[#This Row],[BGG ID]],bgg_cache[id],bgg_cache[thumbnail_url]),,3,80) -> #VALUE! | D11: 201808 | E11: =_xlfn.XLOOKUP(BUYLIST10[[#This Row],[BGG ID]],STOREURL[BGG ID],STOREURL[STATUS]) -> AVAILABLE | F11: =_xlfn.XLOOKUP(BUYLIST10[[#This Row],[BGG ID]],STOREURL[BGG ID],STOREURL[LPG_RRP]) -> 134.99 | G11: =_xlfn.XLOOKUP(BUYLIST10[[#This Row],[NAME]],summary_prices[game],summary_prices[site_low_nzd]) -> #N/A | H11: =_xlfn.XLOOKUP(BUYLIST10[[#This Row],[NAME]],summary_prices[game],summary_prices[site_mean_nzd]) -> #N/A | I11: =_xlfn.XLOOKUP(BUYLIST10[[#This Row],[NAME]],summary_prices[game],summary_prices[best_in_stock_nzd]) -> #N/A | J11: =IFERROR(_xlfn.XLOOKUP(BUYLIST10[[#This Row],[NAME]],summary_prices[game],summary_prices[discount_pct_vs_site_mean]),-99) -> -99 | K11: =_xlfn.XLOOKUP(BUYLIST10[[#This Row],[NAME]],summary_prices[game],summary_prices[delta_vs_site_disc_mean_pp]) -> #N/A | L11: {=_xlfn.LET( _xlpm.b, BUYLIST10[[#This Row],[BEST]], _xlpm.s, BUYLIST10[[#This Row],[LPG_Status]], _xlpm.r, BUYLIST10[[#This Row],[LPG_RRP]], _xlpm.d, BUYLIST10[[#This Row],[Discount]], OR( AND( OR(_xlpm.s={"AVAILABLE","BACK_ORDER"}), IF(ISNUMBER(_xlpm.b), AND(_xlpm.b<>0, _xlpm.b*2<=_xlpm.r), FALSE) ), AND( OR(_xlpm.s={"NOT_FOUND","BACK_ORDER_OOS"}), _xlpm.d>30 ) ) )} -> FALSE | M11: =_xlfn.XLOOKUP(BUYLIST10[[#This Row],[NAME]],summary_prices[game],summary_prices[best_in_stock_store]) -> #N/A | N11: =HYPERLINK(_xlfn.XLOOKUP(BUYLIST10[[#This Row],[BGG ID]],STOREURL[BGG ID],STOREURL[BGO LINK])) -> https://www.boardgameoracle.com/en-NZ/boardgame/price/455SQydqa0/clank-a-deck-building-adventure | O11: =COUNTIF(OWNED[bgg_id],BUYLIST10[[#This Row],[BGG ID]]) -> 0 | P11: =COUNTIF(BUYLIST10[NAME],BUYLIST10[[#This Row],[NAME]]) -> 1
A12: 11 | B12: =IFERROR(_xlfn.XLOOKUP(BUYLIST10[[#This Row],[BGG ID]],bgg_cache[id],bgg_cache[title]),_xlfn.XLOOKUP(BUYLIST10[[#This Row],[BGG ID]],manual_bgg!B:B,manual_bgg!D:D)) -> The Quest for El Dorado | C12: =_xlfn.IMAGE(_xlfn.XLOOKUP(BUYLIST10[[#This Row],[BGG ID]],bgg_cache[id],bgg_cache[thumbnail_url]),,3,80) -> #N/A | D12: 217372 | E12: =_xlfn.XLOOKUP(BUYLIST10[[#This Row],[BGG ID]],STOREURL[BGG ID],STOREURL[STATUS]) -> NOT_FOUND | F12: =_xlfn.XLOOKUP(BUYLIST10[[#This Row],[BGG ID]],STOREURL[BGG ID],STOREURL[LPG_RRP]) -> 0 | G12: =_xlfn.XLOOKUP(BUYLIST10[[#This Row],[NAME]],summary_prices[game],summary_prices[site_low_nzd]) -> 78.77 | H12: =_xlfn.XLOOKUP(BUYLIST10[[#This Row],[NAME]],summary_prices[game],summary_prices[site_mean_nzd]) -> 80.56 | I12: =_xlfn.XLOOKUP(BUYLIST10[[#This Row],[NAME]],summary_prices[game],summary_prices[best_in_stock_nzd]) -> 79.22 | J12: =IFERROR(_xlfn.XLOOKUP(BUYLIST10[[#This Row],[NAME]],summary_prices[game],summary_prices[discount_pct_vs_site_mean]),-99) -> 1.66 | K12: =_xlfn.XLOOKUP(BUYLIST10[[#This Row],[NAME]],summary_prices[game],summary_prices[delta_vs_site_disc_mean_pp]) -> -0.56 | L12: {=_xlfn.LET( _xlpm.b, BUYLIST10[[#This Row],[BEST]], _xlpm.s, BUYLIST10[[#This Row],[LPG_Status]], _xlpm.r, BUYLIST10[[#This Row],[LPG_RRP]], _xlpm.d, BUYLIST10[[#This Row],[Discount]], OR( AND( OR(_xlpm.s={"AVAILABLE","BACK_ORDER"}), IF(ISNUMBER(_xlpm.b), AND(_xlpm.b<>0, _xlpm.b*2<=_xlpm.r), FALSE) ), AND( OR(_xlpm.s={"NOT_FOUND","BACK_ORDER_OOS"}), _xlpm.d>30 ) ) )} -> FALSE | M12: =_xlfn.XLOOKUP(BUYLIST10[[#This Row],[NAME]],summary_prices[game],summary_prices[best_in_stock_store]) -> Gameology | N12: =HYPERLINK(_xlfn.XLOOKUP(BUYLIST10[[#This Row],[BGG ID]],STOREURL[BGG ID],STOREURL[BGO LINK])) -> https://www.boardgameoracle.com/en-NZ/boardgame/price/ZZsrjOqQFe/the-quest-for-el-dorado | O12: =COUNTIF(OWNED[bgg_id],BUYLIST10[[#This Row],[BGG ID]]) -> 0 | P12: =COUNTIF(BUYLIST10[NAME],BUYLIST10[[#This Row],[NAME]]) -> 1
A13: 12 | B13: =IFERROR(_xlfn.XLOOKUP(BUYLIST10[[#This Row],[BGG ID]],bgg_cache[id],bgg_cache[title]),_xlfn.XLOOKUP(BUYLIST10[[#This Row],[BGG ID]],manual_bgg!B:B,manual_bgg!D:D)) -> Orléans | C13: =_xlfn.IMAGE(_xlfn.XLOOKUP(BUYLIST10[[#This Row],[BGG ID]],bgg_cache[id],bgg_cache[thumbnail_url]),,3,80) -> #VALUE! | D13: 164928 | E13: =_xlfn.XLOOKUP(BUYLIST10[[#This Row],[BGG ID]],STOREURL[BGG ID],STOREURL[STATUS]) -> BACK_ORDER_OOS | F13: =_xlfn.XLOOKUP(BUYLIST10[[#This Row],[BGG ID]],STOREURL[BGG ID],STOREURL[LPG_RRP]) -> 124.99 | G13: =_xlfn.XLOOKUP(BUYLIST10[[#This Row],[NAME]],summary_prices[game],summary_prices[site_low_nzd]) -> 68.49 | H13: =_xlfn.XLOOKUP(BUYLIST10[[#This Row],[NAME]],summary_prices[game],summary_prices[site_mean_nzd]) -> 106.19 | I13: =_xlfn.XLOOKUP(BUYLIST10[[#This Row],[NAME]],summary_prices[game],summary_prices[best_in_stock_nzd]) -> 68.88 | J13: =IFERROR(_xlfn.XLOOKUP(BUYLIST10[[#This Row],[NAME]],summary_prices[game],summary_prices[discount_pct_vs_site_mean]),-99) -> 35.14 | K13: =_xlfn.XLOOKUP(BUYLIST10[[#This Row],[NAME]],summary_prices[game],summary_prices[delta_vs_site_disc_mean_pp]) -> -0.36 | L13: {=_xlfn.LET( _xlpm.b, BUYLIST10[[#This Row],[BEST]], _xlpm.s, BUYLIST10[[#This Row],[LPG_Status]], _xlpm.r, BUYLIST10[[#This Row],[LPG_RRP]], _xlpm.d, BUYLIST10[[#This Row],[Discount]], OR( AND( OR(_xlpm.s={"AVAILABLE","BACK_ORDER"}), IF(ISNUMBER(_xlpm.b), AND(_xlpm.b<>0, _xlpm.b*2<=_xlpm.r), FALSE) ), AND( OR(_xlpm.s={"NOT_FOUND","BACK_ORDER_OOS"}), _xlpm.d>30 ) ) )} -> TRUE | M13: =_xlfn.XLOOKUP(BUYLIST10[[#This Row],[NAME]],summary_prices[game],summary_prices[best_in_stock_store]) -> Gameology | N13: =HYPERLINK(_xlfn.XLOOKUP(BUYLIST10[[#This Row],[BGG ID]],STOREURL[BGG ID],STOREURL[BGO LINK])) -> https://www.boardgameoracle.com/en-NZ/boardgame/price/01S6no2BbD/orleans | O13: =COUNTIF(OWNED[bgg_id],BUYLIST10[[#This Row],[BGG ID]]) -> 0 | P13: =COUNTIF(BUYLIST10[NAME],BUYLIST10[[#This Row],[NAME]]) -> 1
... A95: 99 | B95: =IFERROR(_xlfn.XLOOKUP(BUYLIST10[[#This Row],[BGG ID]],bgg_cache[id],bgg_cache[title]),_xlfn.XLOOKUP(BUYLIST10[[#This Row],[BGG ID]],manual_bgg!B:B,manual_bgg!D:D)) -> El Grande: Big Box | C95: =_xlfn.IMAGE(_xlfn.XLOOKUP(BUYLIST10[[#This Row],[BGG ID]],bgg_cache[id],bgg_cache[thumbnail_url]),,3,80) -> #N/A | D95: 171908 | E95: =_xlfn.XLOOKUP(BUYLIST10[[#This Row],[BGG ID]],STOREURL[BGG ID],STOREURL[STATUS]) -> NOT_FOUND | F95: =_xlfn.XLOOKUP(BUYLIST10[[#This Row],[BGG ID]],STOREURL[BGG ID],STOREURL[LPG_RRP]) -> 0 | G95: =_xlfn.XLOOKUP(BUYLIST10[[#This Row],[NAME]],summary_prices[game],summary_prices[site_low_nzd]) -> 81.52 | H95: =_xlfn.XLOOKUP(BUYLIST10[[#This Row],[NAME]],summary_prices[game],summary_prices[site_mean_nzd]) -> 90.26 | I95: =_xlfn.XLOOKUP(BUYLIST10[[#This Row],[NAME]],summary_prices[game],summary_prices[best_in_stock_nzd]) -> 0 | J95: =IFERROR(_xlfn.XLOOKUP(BUYLIST10[[#This Row],[NAME]],summary_prices[game],summary_prices[discount_pct_vs_site_mean]),-99) -> 0 | K95: =_xlfn.XLOOKUP(BUYLIST10[[#This Row],[NAME]],summary_prices[game],summary_prices[delta_vs_site_disc_mean_pp]) -> 0 | L95: {=_xlfn.LET( _xlpm.b, BUYLIST10[[#This Row],[BEST]], _xlpm.s, BUYLIST10[[#This Row],[LPG_Status]], _xlpm.r, BUYLIST10[[#This Row],[LPG_RRP]], _xlpm.d, BUYLIST10[[#This Row],[Discount]], OR( AND( OR(_xlpm.s={"AVAILABLE","BACK_ORDER"}), IF(ISNUMBER(_xlpm.b), AND(_xlpm.b<>0, _xlpm.b*2<=_xlpm.r), FALSE) ), AND( OR(_xlpm.s={"NOT_FOUND","BACK_ORDER_OOS"}), _xlpm.d>30 ) ) )} -> FALSE | M95: =_xlfn.XLOOKUP(BUYLIST10[[#This Row],[NAME]],summary_prices[game],summary_prices[best_in_stock_store]) | N95: =HYPERLINK(_xlfn.XLOOKUP(BUYLIST10[[#This Row],[BGG ID]],STOREURL[BGG ID],STOREURL[BGO LINK])) -> https://www.boardgameoracle.com/en-NZ/boardgame/price/-IO6W6K0sN/el-grande | O95: =COUNTIF(OWNED[bgg_id],BUYLIST10[[#This Row],[BGG ID]]) -> 0 | P95: =COUNTIF(BUYLIST10[NAME],BUYLIST10[[#This Row],[NAME]]) -> 1

Sheet LIBRARY
A1: id | B1: title | C1: categories | D1: year | E1: players_min | F1: players_max | G1: playtime_min | H1: playtime_max | I1: thumbnail_url | J1: image | K1: created_at | L1: bgg_id | M1: thumbnail_file | N1: mana_meeple_category | O1: description | P1: designers | Q1: publishers | R1: mechanics | S1: artists | T1: average_rating | U1: complexity | V1: bgg_rank | W1: users_rated | X1: min_age | Y1: is_cooperative | Z1: nz_designer | AA1: game_type | AB1: in_owned
A2: 1 | B2: Azul | C2: Abstract Strategy, Renaissance | D2: 2017 | E2: 2 | F2: 4 | G2: 30 | H2: 45 | I2: /thumbs/1-azul.png | J2: https://cf.geekdo-images.com/aPSHJO0d0XOpQR5X-wJonw__original/img/AkbtYVc6xXJF3c9EUrakklcclKw=/0x0/filters:format(png)/pic6973671.png | K2: 2025-09-16T00:47:26.336168 | L2: 230802 | M2: 1-azul.png | N2: GATEWAY_STRATEGY | O2: Introduced by the Moors, azulejos (originally white and blue ceramic tiles) were fully embraced by the Portuguese when their king Manuel I, on a visit to the Alhambra palace in Southern Spain, was mesmerized by the stunning beauty of the Moorish decorative tiles. The king, awestruck by the interior beauty of the Alhambra, immediately ordered that his own palace in Portugal be decorated with similar wall tiles. As a tile-laying artist, you have been challenged to embellish the walls of the Royal Palace of Evora. In the game Azul, players take turns drafting colored tiles from suppliers to their player board. Later in the round, players score points based on how they've placed their tiles to decorate the palace. Extra points are scored for specific patterns and completing sets; wasted supplies harm the player's score. The player with the most points at the end of the game wins. | P2: ["Michael Kiesling"] | Q2: ["Next Move Games", "Plan B Games", "asmodee", "Belleville (\u0411\u0435\u043b\u044c\u0432\u0456\u043b\u044c)", "Broadway Toys LTD", "Divercentro", "Gal\u00e1pagos Jogos", "G\u00e9m Klub Kft.", "Ghenos Games", "Green Elephant Games", "Hobby Japan", "KADABRA", "Kaissa Chess & Games", "Korea Boardgames", "Lacerta", "MINDOK", "MIPL", "Orangutan Games", "Pegasus Spiele", "Rebel Sp. z o.o.", "SuperHeated Neurons", "Tower Tactic Games", "TWOPLUS Games", "Zvezda"] | R2: ["Chaining", "End Game Bonuses", "Grid Coverage", "Open Drafting", "Pattern Building", "Set Collection", "Square Grid", "Tile Placement", "Turn Order: Claim Action"] | S2: ["Philippe Gu\u00e9rin", "Chris Quilliams"] | T2: 7.72407 | U2: 1.7742 | V2: 91 | W2: 102534 | X2: 8 | Y2: FALSE | Z2: FALSE | AA2: Abstract • Family | AB2: =COUNTIF(OWNED[bgg_id],library_data[[#This Row],[bgg_id]]) -> 1
A3: 2 | B3: Wingspan | C3: Animals, Card Game, Educational | D3: 2019 | E3: 1 | F3: 5 | G3: 40 | H3: 70 | I3: /thumbs/2-wingspan.jpg | J3: https://cf.geekdo-images.com/yLZJCVLlIx4c7eJEWUNJ7w__original/img/cI782Zis9cT66j2MjSHKJGnFPNw=/0x0/filters:format(jpeg)/pic4458123.jpg | K3: 2025-09-16T00:59:01.484382 | L3: 266192 | M3: 2-wingspan.jpg | N3: CORE_STRATEGY | O3: Wingspan is a competitive, medium-weight, card-driven, engine-building board game from Stonemaier Games. It's designed by Elizabeth Hargrave and features 180 birds illustrated by Natalia Rojas and Ana Maria Martinez. You are bird enthusiasts—researchers, bird watchers, ornithologists, and collectors—seeking to discover and attract the best birds to your network of wildlife preserves. Each bird extends a chain of powerful combinations in one of your habitats (actions). These habitats focus on several key aspects of growth: Gain food tokens via custom dice in a birdfeeder dice tower Lay eggs using egg miniatures in a variety of colors Draw from hundreds of unique bird cards and play them The winner is the player with the most points after 4 rounds. —description from the publisher From the 7th printing on, the base game box includes Wingspan: Swift-Start Promo Pack. | P3: ["Elizabeth Hargrave"] | Q3: ["Stonemaier Games", "999 Games", "Angry Lion Games", "Arclight Games", "asmodee", "Automa Factory", "Bluebird Games", "Brain Games", "Delta Vision Publishing", "Divercentro", "Feuerland Spiele", "Ghenos Games", "Green Elephant Games", "Grok Games", "Kaissa Chess & Games", "Korea Boardgames", "Lautapelit.fi", "Lavka Games", "Ludofy Creative", "Maldito Games", "Matagot", "MINDOK", "MIPL", "NeoTroy Games", "Rebel Sp. z o.o.", "Regatul Jocurilor", "Siam Board Games", "Surfin' Meeple China", "\u0406\u0433\u0440\u043e\u043c\u0430\u0433"] | R3: ["Action Queue", "Dice Rolling", "End Game Bonuses", "Hand Management", "Once-Per-Game Abilities", "Open Drafting", "Set Collection", "Solo / Solitaire Game", "Turn Order: Progressive"] | S3: ["Ana Maria Martinez Jaramillo", "Natalia Rojas", "Elizabeth Hargrave", "Greg May", "Beth Sobel"] | T3: 8.01138 | U3: 2.4754 | V3: 38 | W3: 106577 | X3: 10 | Y3: FALSE | Z3: FALSE | AA3: Family • Strategy | AB3: =COUNTIF(OWNED[bgg_id],library_data[[#This Row],[bgg_id]]) -> 1
A4: 3 | B4: Cascadia | C4: Animals, Environmental | D4: 2021 | E4: 1 | F4: 4 | G4: 30 | H4: 45 | I4: /thumbs/3-cascadia.jpg | J4: https://cf.geekdo-images.com/MjeJZfulbsM1DSV3DrGJYA__original/img/B374C04Eip7fmQBGJzgiOTp-jyQ=/0x0/filters:format(jpeg)/pic5100691.jpg | K4: 2025-09-16T00:59:18.753257 | L4: 295947 | M4: 3-cascadia.jpg | N4: GATEWAY_STRATEGY | O4: Cascadia is a puzzly tile-laying and token-drafting game featuring the habitats and wildlife of the Pacific Northwest. In the game, you take turns building out your own terrain area and populating it with wildlife. You start with three hexagonal habitat tiles (with the five types of habitat in the game), and on a turn you choose a new habitat tile that's paired with a wildlife token, then place that tile next to your other ones and place the wildlife token on an appropriate habitat. (Each tile depicts 1-3 types of wildlife from the five types in the game, and you can place at most one tile on a habitat.) Four tiles are on display, with each tile being paired at random with a wildlife token, so you must make the best of what's available — unless you have a nature token to spend so that you can pick your choice of each item. Ideally you can place habitat tiles to create matching terrain that reduces fragmentation and creates wildlife corridors, mostly because you score for the largest area of each type of habitat at game's end, with a bonus if your group is larger than each other player's. At the same time, you want to place wildlife tokens so that you can maximize the number of points scored by them, with the wildlife goals being determined at random by one of the four scoring cards for each type of wildlife. Maybe hawks want to be separate from other hawks, while foxes want lots of different animals surrounding them and bears want to be in pairs. Can you make it happen? | P4: ["Randy Flynn"] | Q4: ["Flatout Games", "Alderac Entertainment Group", "Boardgame Mall", "CMON Global Limited", "CrowD Games", "Delirium Games", "Fantasmagoria", "Gaming Library", "G\u00e9m Klub Kft.", "Grok Games", "Hid Konem (\u0425\u0456\u0434 \u041a\u043e\u043d\u0435\u043c)", "Kaissa Chess & Games", "KOSMOS", "Little Rocket Games", "Lord of Boards", "Lucky Duck Games", "MINDOK", "MIPL", "NeoTroy Games", "Regatul Jocurilor", "Salta da Caixa", "Terra Publica", "Tower Tactic Games", "White Goblin Games", "\u682a\u5f0f\u4f1a\u793e\u30b1\u30f3\u30d3\u30eb (KenBill)"] | R4: ["End Game Bonuses", "Hexagon Grid", "Open Drafting", "Pattern Building", "Solo / Solitaire Game", "Tile Placement", "Variable Set-up"] | S4: ["Beth Sobel"] | T4: 7.90913 | U4: 1.8495 | V4: 54 | W4: 50152 | X4: 10 | Y4: FALSE | Z4: FALSE | AA4: Abstract • Family | AB4: =COUNTIF(OWNED[bgg_id],library_data[[#This Row],[bgg_id]]) -> 1
A5: 4 | B5: 7 Wonders | C5: Ancient, Card Game, City Building, Civilization, Economic | D5: 2010 | E5: 2 | F5: 7 | G5: 30 | H5: 30 | I5: /thumbs/4-7-wonders.jpg | J5: https://cf.geekdo-images.com/35h9Za_JvMMMtx_92kT0Jg__original/img/jt70jJDZ1y1FWJs4ZQf5FI8APVY=/0x0/filters:format(jpeg)/pic7149798.jpg | K5: 2025-09-16T22:42:10.050302 | L5: 68448 | M5: 4-7-wonders.jpg | N5: GATEWAY_STRATEGY | O5: You are the leader of one of the 7 great cities of the Ancient World. Gather resources, develop commercial routes, and affirm your military supremacy. Build your city and erect an architectural wonder which will transcend future times. 7 Wonders lasts three ages. In each age, players receive seven cards from a particular deck, choose one of those cards, then pass the remainder to an adjacent player. Players reveal their cards simultaneously, paying resources if needed or collecting resources or interacting with other players in various ways. (Players have individual boards with special powers on which to organize their cards, and the boards are double-sided). Each player then chooses another card from the deck they were passed, and the process repeats until players have six cards in play from that age. After three ages, the game ends. In essence, 7 Wonders is a card development game. Some cards have immediate effects, while others provide bonuses or upgrades later in the game. Some cards provide discounts on future purchases. Some provide military strength to overpower your neighbors and others give nothing but victory points. Each card is played immediately after being drafted, so you'll know which cards your neighbor is receiving and how her choices might affect what you've already built up. Cards are passed left-right-left over the three ages, so you need to keep an eye on the neighbors in both directions. Though the box of earlier editions is listed as being for 3–7 players, there is an official 2-player variant included in the instructions. | P5: ["Antoine Bauza"] | Q5: ["Repos Production", "ADC Blackfire Entertainment", "Asterion Press", "Gal\u00e1pagos Jogos", "G\u00e9m Klub Kft.", "Hobby Japan", "Kaissa Chess & Games", "Korea Boardgames", "Lautapelit.fi", "Lifestyle Boardgames Ltd", "NeoTroy Games", "Rebel Sp. z o.o.", "Siam Board Games"] | R5: ["Closed Drafting", "End Game Bonuses", "Hand Management", "Melding and Splaying", "Multi-Use Cards", "Neighbor Scope", "Once-Per-Game Abilities", "Score-and-Reset Game", "Set Collection", "Simultaneous Action Selection", "Tags", "Tech Trees / Tech Tracks", "Variable Player Powers", "Variable Set-up"] | S5: ["Dimitri Chappuis", "Miguel Coimbra", "Etienne Hebinger", "Cyril Nouvel"] | T5: 7.66798 | U5: 2.3149 | V5: 111 | W5: 110129 | X5: 10 | Y5: FALSE | Z5: FALSE | AA5: Family • Strategy | AB5: =COUNTIF(OWNED[bgg_id],library_data[[#This Row],[bgg_id]]) -> 1
A6: 5 | B6: 7 Wonders Duel | C6: Ancient, Card Game, City Building, Civilization, Economic | D6: 2015 | E6: 2 | F6: 2 | G6: 30 | H6: 30 | I6: /thumbs/5-7-wonders-duel.jpg | J6: https://cf.geekdo-images.com/zdagMskTF7wJBPjX74XsRw__original/img/Ju836WNSaW7Mab9Vjq2TJ_FqhWQ=/0x0/filters:format(jpeg)/pic2576399.jpg | K6: 2025-09-16T22:42:10.660472 | L6: 173346 | M6: 5-7-wonders-duel.jpg | N6: GATEWAY_STRATEGY | O6: In many ways 7 Wonders Duel resembles its parent game 7 Wonders. Over three ages, players acquire cards that provide resources or advance their military or scientific development in order to develop a civilization and complete wonders. What's different about 7 Wonders Duel is that, as the title suggests, the game is solely for two players. Players do not draft cards simultaneously from decks of cards, but from a display of face-down and face-up cards arranged at the start of a round. A player can take a card only if it's not covered by any others, so timing comes into play, as it can with bonus moves that allow the player to take a second card immediately. As in the original game, each acquired card can be built, discarded for coins, or used to construct a wonder. Each player also starts with four wonder cards, and the construction of a wonder provides its owner with a special ability. Only seven wonders can be built, though, so one player will end up short. Players can purchase resources at any time from the bank, or they can gain cards during the game that provide them with resources for future building; as they are acquired, the cost for those resources increases for the opponent, representing the owner's dominance in this area. You can win 7 Wonders Duel in one of three ways: each time you acquire a military card, you advance the military marker toward your opponent's capital (also giving you a bonus at certain positions). If you reach the opponent's capital, you win the game immediately. Or if you acquire six of seven different scientific symbols, you achieve scientific dominance and win immediately. If none of these situations occurs, then the player with the most points at the end of the game wins. | P6: ["Antoine Bauza", "Bruno Cathala"] | Q6: ["Repos Production", "ADC Blackfire Entertainment", "asmodee", "Asterion Press", "Boardgame Space", "CoolPlay", "Gal\u00e1pagos Jogos", "G\u00e9m Klub Kft.", "Hobby Japan", "KADABRA", "Kaissa Chess & Games", "Korea Boardgames", "Lautapelit.fi", "Lifestyle Boardgames Ltd", "Ludicus Games", "Ponva d.o.o.", "Pridemage Games", "Rebel Sp. z o.o.", "Siam Board Games", "Sombreros Production", "\u0406\u0433\u0440\u043e\u043c\u0430\u0433"] | R6: ["End Game Bonuses", "Income", "Melding and Splaying", "Modular Board", "Multi-Use Cards", "Once-Per-Game Abilities", "Open Drafting", "Score-and-Reset Game", "Set Collection", "Sudden Death Ending", "Tags", "Tech Trees / Tech Tracks", "Track Movement", "Tug of War", "Variable Set-up"] | S6: ["Miguel Coimbra"] | T6: 8.08313 | U6: 2.227 | V6: 21 | W6: 104464 | X6: 10 | Y6: FALSE | Z6: FALSE | AA6: Strategy | AB6: =COUNTIF(OWNED[bgg_id],library_data[[#This Row],[bgg_id]]) -> 1
A7: 6 | B7: A Feast for Odin | C7: Animals, Farming, Industry / Manufacturing, Medieval, Puzzle | D7: 2016 | E7: 1 | F7: 4 | G7: 30 | H7: 120 | I7: /thumbs/6-a-feast-for-odin.png | J7: https://cf.geekdo-images.com/s9oGMCo1fcfV4Dk3EnqLZw__original/img/N1X-0JB1GapFVhl98nP4tNFXMcM=/0x0/filters:format(png)/pic3146943.png | K7: 2025-09-16T22:42:11.141119 | L7: 177736 | M7: 6-a-feast-for-odin.png | N7: CORE_STRATEGY | O7: A Feast for Odin is a saga in the form of a board game. You are reliving the cultural achievements, mercantile expeditions, and pillages of those tribes we know as Viking today — a term that was used quite differently towards the end of the first millennium. When the northerners went out for a raid, they used to say they headed out for a viking. Their Scandinavian ancestors, however, were much more than just pirates. They were explorers and founders of states. Leif Eriksson is said to be the first European in America, long before Columbus. In what is known today as Normandy, the intruders were not called Vikings but Normans. One of them is the famous William the Conqueror who invaded England in 1066. He managed to do what the king of Norway failed to do only a few years prior: conquer the Throne of England. The reason the people of these times became such strong seafarers was their unfortunate agricultural situation: crop shortfalls caused great distress. In this game, you will raid and explore new territories. You will also engage in the day-to-day activity of collecting goods with which to achieve a financially secure position in society. In the end, the player whose possessions bear the greatest value will be declared the winner. --gameplay description from @StoryBoardGamer's review: A Feast for Odin is a points-driven game, with a plethora of pathways to victory, with a range of risks balanced against rewards. A significant portion of this is your central hall, which has a whopping -86 points of squares and a major part of your game is attempting to cover these up with various tiles. Likewise, long halls and island colonies can also offer large rewards, but they will have penalties of their own. Each year follows a familiar pattern of preparation, worker placement, and then meeting the requirements of your feast. The main phase of each year is a worker placement affair. You start with a selection of Vikings, and a large action board with a whopping 61 differ | P7: ["Uwe Rosenberg"] | Q7: ["Feuerland Spiele", "Cranio Creations", "Devir", "Filosofia \u00c9ditions", "Game Harbor", "Hobby World", "Korea Boardgames", "Lacerta", "Maldito Games", "Mandala Jogos", "Rebel Sp. z o.o.", "Super Meeple", "\u30c6\u30f3\u30c7\u30a4\u30ba\u30b2\u30fc\u30e0\u30ba (TendaysGames)", "TLAMA games", "White Goblin Games", "Z-Man Games"] | R7: ["Action Points", "Automatic Resource Growth", "Dice Rolling", "Enclosure", "Grid Coverage", "Hand Management", "Income", "Layering", "Pattern Recognition", "Push Your Luck", "Solo / Solitaire Game", "Square Grid", "Tile Placement", "Turn Order: Pass Order", "Worker Placement"] | S7: ["Dennis Lohausen"] | T7: 8.16646 | U7: 3.8661 | V7: 24 | W7: 31926 | X7: 12 | Y7: FALSE | Z7: FALSE | AA7: Strategy | AB7: =COUNTIF(OWNED[bgg_id],library_data[[#This Row],[bgg_id]]) -> 1
A8: 7 | B8: Abandon All Artichokes | C8: Card Game, Farming | D8: 2020 | E8: 2 | F8: 4 | G8: 20 | H8: 20 | I8: /thumbs/7-abandon-all-artichokes.png | J8: https://cf.geekdo-images.com/qwFz_zhMjIxRjgAIx__8WQ__original/img/pxX6W95d3V38ZuynABAtorApTc8=/0x0/filters:format(png)/pic5335069.png | K8: 2025-09-16T22:42:11.632866 | L8: 302260 | M8: 7-abandon-all-artichokes.png | N8: KIDS_FAMILIES | O8: Abandon All Artichokes isn't your garden-variety card game! A bumper-crop of prickly produce has overtaken your patch, and there's only one choice: abandon all artichokes! Prune your deck by harvesting fresh vegetables, each with a special power that lets you swap, discard, or compost cards. You need luck, strategy, and a green thumb to grow a winning hand! —description from the publisher | P8: ["Emma Larkins"] | Q8: ["Gamewright", "AMIGO", "Arclight Games", "Devir", "Gigamic", "Magellan", "Popcorn Games", "Reflexshop", "uplay.it edizioni", "White Goblin Games"] | R8: ["Deck, Bag, and Pool Building", "Open Drafting", "Race"] | S8: ["Bonnie Pang"] | T8: 6.58192 | U8: 1.2639 | V8: 1915 | W8: 6024 | X8: 10 | Y8: FALSE | Z8: FALSE | AA8: Family | AB8: =COUNTIF(OWNED[bgg_id],library_data[[#This Row],[bgg_id]]) -> 1
A9: 8 | B9: Akropolis | C9: Abstract Strategy, Ancient, City Building, Territory Building | D9: 2022 | E9: 1 | F9: 4 | G9: 20 | H9: 30 | I9: /thumbs/8-akropolis.jpg | J9: https://cf.geekdo-images.com/OTb0hIJHE-U3eD0FmpBrzA__original/img/GpSyHl2wwgLJ6JHJAjPbEQk4MNU=/0x0/filters:format(jpeg)/pic6705097.jpg | K9: 2025-09-16T22:42:12.162050 | L9: 357563 | M9: 8-akropolis.jpg | N9: GATEWAY_STRATEGY | O9: The most talented architects in ancient Greece stand ready to achieve this goal. Build housing, temples, markets, gardens and barracks, so you can grow your city and ensure it triumphs over the others. Raise its prestige with harmonious planning that conforms to specific rules, and enhance it by building plazas. Stone is an essential resource, so make sure you do not neglect it. You’ll need enough quarries so you can build higher up, making your city stretch towards the sky. Choose a tile from the construction site Arrange it in your city to unlock each district's full potential Build on higher levels, increase the value of your districts and win the game —description from the publisher | P9: ["Jules Messaud"] | Q9: ["Gigamic", "BGA Plus", "Brain Games", "CMON Global Limited", "Engames", "Fox Mind Israel", "G\u00e9m Klub Kft.", "Geronimo Games", "Ghenos Games", "Hachette Boardgames Benelux", "Hachette Boardgames UK", "Hachette Boardgames USA", "Happy Color", "Kaissa Chess & Games", "Kobold Spieleverlag", "Korea Boardgames", "Lautapelit.fi", "Lifestyle Boardgames Ltd", "Lucky Duck Games", "M&V Games Distribution", "Mald\u00f3n", "MEBO Games", "PaperGames (III)", "TLAMA games", "WoodCat", "YOKA Games"] | R9: ["Auction: Dutch", "End Game Bonuses", "Layering", "Open Drafting", "Pattern Building", "Solo / Solitaire Game", "Tile Placement", "Turn Order: Progressive"] | S9: ["Pauline Detraz"] | T9: 7.4567 | U9: 1.8071 | V9: 446 | W9: 9354 | X9: 8 | Y9: FALSE | Z9: FALSE | AA9: Family | AB9: =COUNTIF(OWNED[bgg_id],library_data[[#This Row],[bgg_id]]) -> 1
A10: 9 | B10: Animal Upon Animal | C10: Action / Dexterity, Animals, Children's Game | D10: 2005 | E10: 2 | F10: 4 | G10: 15 | H10: 15 | I10: /thumbs/9-animal-upon-animal.jpg | J10: https://cf.geekdo-images.com/5RHnNYBqmNXYvDtIeJw3pA__original/img/mD1qqRY_sjE0G6ojCQwy_mkErHY=/0x0/filters:format(jpeg)/pic403502.jpg | K10: 2025-09-16T22:42:12.647771 | L10: 17329 | M10: 9-animal-upon-animal.jpg | N10: KIDS_FAMILIES | O10: The animals want to show how good they are at making tall pyramids! They must be skillfully careful: Who will position the penguin on top of the crocodile, the sheep on top of the penguin, the serpent on the sheep? The hedgehog wants to stand on top of the pyramid but the height is making him dizzy. Tier auf Tier (a.k.a. Animal Upon Animal, Pyramide d'animaux, and Dier op dier) is a simple stacking game, listed for ages 4-99, with 29 cute wooden animals. Each turn a player rolls the die and either places one or two animals on to the stack of animals, passes one of his or her animals to another player for them to place, or places an animal on the table, extending the base for other players to build upon. Of course, if any pieces fall off whilst you are building, you get up to two of them back. The first player to have used all of their animals wins. This game, intended for children, is equally popular with adults. | P10: ["Klaus Miltenberger"] | Q10: ["HABA", "Conclave Editora", "Hobby World", "Swan Panasia Co., Ltd."] | R10: ["Dice Rolling", "Stacking and Balancing", "Take That"] | S10: ["Michael Bayer", "Daniel D\u00f6bner", "Klaus Miltenberger"] | T10: 6.76998 | U10: 1.0388 | V10: 1295 | W10: 8951 | X10: 4 | Y10: FALSE | Z10: FALSE | AA10: Children's | AB10: =COUNTIF(OWNED[bgg_id],library_data[[#This Row],[bgg_id]]) -> 1
A11: 10 | B11: Anomia | C11: Party Game, Real-time, Trivia, Word Game | D11: 2010 | E11: 3 | F11: 6 | G11: 30 | H11: 30 | I11: /thumbs/10-anomia.jpg | J11: https://cf.geekdo-images.com/OvOpd-Lhl7t3h9fF_qi6lQ__original/img/0_8ukg1eYy8HxXTAwPgKptJXTeU=/0x0/filters:format(jpeg)/pic2527529.jpg | K11: 2025-09-16T22:42:13.152509 | L11: 67877 | M11: 10-anomia.jpg | N11: PARTY_ICEBREAKERS | O11: Anomia plays off the fact that our minds are positively brimming with all sorts of random information: things to eat, pop songs, websites, etc... Sure, under normal circumstances, it's easy to give an example of a frozen food or a dog breed, but you'll find that your brain works a little differently under pressure! To play, draw and reveal a card from the center pile. Does the symbol on your card match one on another player's card? If so, you must quickly face-off with the other player by giving an example of the person, place, or thing on their card before they can do the same for yours. If you blurt out a correct answer first, you win their card and the drawing continues. Sounds simple, right? Wrong! Wild cards allow non-matching symbols to match, increasing the number of things to which you must pay attention. Cascading face-offs can occur when you hand over a lost card, thereby revealing a new top card on your play pile. | P11: ["Andrew Innes"] | Q11: ["Anomia Press", "asmodee", "Broadway Toys LTD", "Cocktail Games", "Coiledspring Games", "Competo / Marektoy", "DV Games", "Happy Baobab", "KOSMOS", "L\u00fadilo", "Magellan", "Nasza Ksi\u0119garnia", "Piatnik"] | R11: ["Pattern Recognition", "Speed Matching"] | S11: ["Kinetic", "Paul Laane", "Cezary Szulc", "Peter Wocken"] | T11: 6.69519 | U11: 1.0385 | V11: 1837 | W11: 5583 | X11: 10 | Y11: FALSE | Z11: FALSE | AA11: Party | AB11: =COUNTIF(OWNED[bgg_id],library_data[[#This Row],[bgg_id]]) -> 1
A12: 11 | B12: Ascension: Deckbuilding Game | C12: Card Game, Fantasy | D12: 2010 | E12: 1 | F12: 4 | G12: 30 | H12: 30 | I12: /thumbs/11-ascension-deckbuilding-game.jpg | J12: https://cf.geekdo-images.com/DP20jf4R3RcsjJUwwV1vCw__original/img/O_DcqcBQGcWqO0HhJVojg5-VMoc=/0x0/filters:format(jpeg)/pic2382123.jpg | K12: 2025-09-16T22:42:13.644603 | L12: 69789 | M12: 11-ascension-deckbuilding-game.jpg | N12: GATEWAY_STRATEGY | O12: Ascension: Deckbuilding Game — originally released as Ascension: Chronicle of the Godslayer — is a fast-paced deck-building game designed by Magic: The Gathering Pro Tour champions Justin Gary, Rob Dougherty, and Brian Kibler, with artwork by Eric Sabee. Ascension is a deck-building game in which players spend Runes to acquire more powerful cards for their deck. It offers a dynamic play experience where players have to react and adjust their strategy accordingly. Each player starts with a small deck of cards, and uses those cards to acquire more and better cards for their deck, with the goal of earning the most Honor Points by gaining cards and defeating monsters. | P12: ["John Fiorillo", "Justin Gary", "Brian M. Kibler"] | Q12: ["Stone Blade Entertainment", "Arclight Games", "FunBox Jogos", "Marabunta"] | R12: ["Deck, Bag, and Pool Building", "Hand Management", "Open Drafting"] | S12: ["Eric Sabee"] | T12: 7.04386 | U12: 2.1379 | V12: 791 | W12: 13970 | X12: 13 | Y12: FALSE | Z12: FALSE | AA12: Strategy | AB12: =COUNTIF(OWNED[bgg_id],library_data[[#This Row],[bgg_id]]) -> 1
A13: 12 | B13: Bohnanza | C13: Card Game, Farming, Negotiation | D13: 1997 | E13: 2 | F13: 7 | G13: 45 | H13: 45 | I13: /thumbs/12-bohnanza.jpg | J13: https://cf.geekdo-images.com/8SADtu_4zBH_UJrCo935Iw__original/img/RNuAr2CDbxE3XzeJVkxj4Df3eVM=/0x0/filters:format(jpeg)/pic6348964.jpg | K13: 2025-09-16T22:42:14.139892 | L13: 11 | M13: 12-bohnanza.jpg | N13: GATEWAY_STRATEGY | O13: Bohnanza is the first in the Bohnanza family of games and has been published in several different editions, including a 2023 version with flowers. This entry lists a few different major card sets for Bohnanza: the base game for 3-5 players, the expanded game with the same name for 2-7 players (that is, first expansion included), and Bohnanza Pocket. In the game, you plant, then harvest bean cards in order to earn coins. Each player starts with a hand of random bean cards, and each card has a number on it corresponding to the number of that type of beans in the deck. Unlike in most other card games, you can't rearrange the order of cards in hand, so you must use them in the order that you've picked them up from the deck — unless you can trade them to other players, which is the heart of the game. On a turn, you must plant the first one or two cards in your hand into the "fields" in front of you. Each field can hold only one type of bean, so if you must plant a type of bean that's not in one of your fields, then you must harvest a field to make room for the new arrival. This usually isn't good! Next, you reveal two cards from the deck, and you can then trade these cards as well as any card in your hand for cards from other players. You can even make future promises for cards received right now! After all the trading is complete — and all trades on a turn must involve the active player — then you end your turn by drawing cards from the deck and placing them at the back of your hand. When you harvest beans, you receive coins based on the number of bean cards in that field and the "beanometer" for that particular type of bean. Flip over 1-4 cards from that field to transform them into coins, then place the remainder of the cards in the discard pile. When the deck runs out, shuffle the discards, playing through the deck two more times. At the end of the game, everyone can harvest their fields, then whoever has earned the most coins wins. The original German edition s | P13: ["Uwe Rosenberg"] | Q13: ["AMIGO", "999 Games", "Brain Games", "Broadway Toys LTD", "Copag Cards (Copag)", "Corfix", "Fractal Juegos", "G3", "Gigamic", "Kaissa Chess & Games", "Kikigagne?", "Korea Boardgames", "Lautapelit.fi", "Lifestyle Boardgames Ltd", "Lookout Games", "Mercurio", "Midgaard Games", "M\u00f6bius Games", "Paper Iyagi", "PaperGames (III)", "Piatnik", "Rebel Sp. z o.o.", "Rio Grande Games", "Spilbr\u00e6t.dk", "Stratelibri", "Swan Panasia Co., Ltd.", "VR Distribution"] | R13: ["Hand Management", "Multi-Use Cards", "Negotiation", "Set Collection", "Trading"] | S13: ["Bj\u00f6rn Pertoft", "Klemens Franz", "Mady Nijenhuis", "Beth Sobel"] | T13: 7.07438 | U13: 1.668 | V13: 540 | W13: 49826 | X13: 12 | Y13: FALSE | Z13: FALSE | AA13: Family | AB13: =COUNTIF(OWNED[bgg_id],library_data[[#This Row],[bgg_id]]) -> 1
... A31: 30 | B31: Eclipse: New Dawn for the Galaxy | C31: Civilization, Fighting, Science Fiction, Space Exploration, Territory Building, Wargame | D31: 2011 | E31: 2 | F31: 6 | G31: 60 | H31: 180 | I31: /thumbs/30-eclipse-new-dawn-for-the-galaxy.jpg | J31: https://cf.geekdo-images.com/cnFppsVNOSTJ-W3APQFuTg__original/img/AbcjscBi-x3tVrsJsBhXq2RxLbc=/0x0/filters:format(jpeg)/pic1974056.jpg | K31: 2025-09-16T22:42:29.937388 | L31: 72125 | M31: 30-eclipse-new-dawn-for-the-galaxy.jpg | N31: CORE_STRATEGY | O31: The galaxy has been a peaceful place for many years. After the ruthless Terran–Hegemony War (30.027–33.364), much effort has been employed by all major spacefaring species to prevent the terrifying events from repeating themselves. The Galactic Council was formed to enforce precious peace, and it has taken many courageous efforts to prevent the escalation of malicious acts. Nevertheless, tension and discord are growing among the seven major species and in the Council itself. Old alliances are shattering, and hasty diplomatic treaties are made in secrecy. A confrontation of the superpowers seems inevitable – only the outcome of the galactic conflict remains to be seen. Which faction will emerge victorious and lead the galaxy under its rule? A game of Eclipse places you in control of a vast interstellar civilization, competing for success with its rivals. You will explore new star systems, research technologies, and build spaceships with which to wage war. There are many potential paths to victory, so you need to plan your strategy according to the strengths and weaknesses of your species, while paying attention to the other civilizations' endeavors. The shadows of the great civilizations are about to eclipse the galaxy. Lead your people to victory! | P31: ["Touko Tahkokallio"] | Q31: ["Lautapelit.fi", "(Self-Published)", "Asterion Press", "Korea Boardgames", "Rebel Sp. z o.o.", "Ystari Games"] | R31: ["Dice Rolling", "Grid Movement", "Hexagon Grid", "Hot Potato", "Map Addition", "Modular Board", "Player Elimination", "Tile Placement", "Variable Phase Order", "Variable Player Powers"] | S31: ["Ossi Hiekkala", "Sampo Siki\u00f6"] | T31: 7.82113 | U31: 3.706 | V31: 97 | W31: 28871 | X31: 14 | Y31: FALSE | Z31: FALSE | AA31: Strategy | AB31: =COUNTIF(OWNED[bgg_id],library_data[[#This Row],[bgg_id]]) -> 1
A32: 31 | B32: Finca | C32: Economic, Farming | D32: 2018 | E32: 2 | F32: 5 | G32: 45 | H32: 45 | I32: /thumbs/31-finca.jpg | J32: https://cf.geekdo-images.com/Wv3asVffJEVjqwFyPiOvXA__original/img/554uO8XKUlva4FiEOrOLcTMgZjc=/0x0/filters:format(jpeg)/pic7551635.jpg | K32: 2025-09-16T22:42:32.069758 | L32: 261720 | M32: 31-finca.jpg | N32: GATEWAY_STRATEGY | O32: The players take the roles of Mallorcan farmers, who strive to harvest as many of the island‘s tropical fruits: ï¬gs, almonds, olives, oranges, grapes, and lemons, as possible. The players deliver their harvested fruits to the island communities, which have constantly changing requirements during the course of the game. For these deliveries, the players receive victory points. In the end, the player with the most victory points is the winner. Note: Finca: El Razul is included in the box with versions listed under this entry. | P32: ["Wolfgang Sentker", "Ralf zur Linde"] | Q32: ["franjos Spieleverlag", "Devil Dice Games"] | R32: ["Contracts", "Mancala", "Once-Per-Game Abilities", "Rondel", "Set Collection"] | S32: ["Joan Guardiet", "Franz Vohwinkel"] | T32: 7.35861 | U32: 2.0625 | W32: 705 | X32: 10 | Y32: FALSE | Z32: FALSE | AA32: Family • Economic | AB32: =COUNTIF(OWNED[bgg_id],library_data[[#This Row],[bgg_id]]) -> 1
A33: 32 | B33: Exploding Kittens: The Board Game | C33: Animals, Comic Book / Strip, Humor, Party Game | D33: 2025 | E33: 2 | F33: 6 | G33: 20 | H33: 20 | I33: /thumbs/32-exploding-kittens-the-board-game.jpg | J33: https://cf.geekdo-images.com/3oiMV9BNAqWX0boEUWw3bg__original/img/zEWd1JMRhNLyRThG2KDQAX6gnlU=/0x0/filters:format(jpeg)/pic8905009.jpg | K33: 2025-09-16T22:42:32.136639 | L33: 447244 | M33: 32-exploding-kittens-the-board-game.jpg | N33: PARTY_ICEBREAKERS | O33: There's never been a board game like this before! Your goal is to make it to the end of the board without landing on the Exploding Kitten. To do that you'll play cards and plot strategies to sabotage your opponents. But don't get too cocky because one wrong move can cause the board to flip. This completely transforms the board to reveal a new path where every move could be your last. You have to think fast, form alliances, play smart, and avoid the Exploding Kittens at all costs. The stakes are high but the rules are simple… Just beware, danger, and betrayal, and pee your pants laughing moments lurk around every corner. What other game lets you play as a TacoCat, SushiCat, or GnomeCat? Who else would give you the power of Meatpants, a Litterbox Sandworm, or a Butterfly Punch? —description from the publisher | P33: ["Ian Clayman", "Elan Lee", "Carol Mertz"] | Q33: ["Exploding Kittens", "Rebel Sp. z o.o."] | R33: ["Take That", "Variable Player Powers"] | S33: [] | T33: 5.70385 | U33: 1 | V33: 24908 | W33: 52 | X33: 7 | Y33: FALSE | Z33: FALSE | AA33: Party | AB33: =COUNTIF(OWNED[bgg_id],library_data[[#This Row],[bgg_id]]) -> 1
A34: 33 | B34: Flip 7 | C34: Card Game, Number, Party Game | D34: 2024 | E34: 3 | F34: 18 | G34: 20 | H34: 20 | I34: /thumbs/33-flip-7.jpg | J34: https://cf.geekdo-images.com/YrQxEB9Ef0kQorRApzG5vQ__original/img/hK6k-x_GYfooemrkkRuF0bTvKxE=/0x0/filters:format(jpeg)/pic8780246.jpg | K34: 2025-09-16T22:42:34.201572 | L34: 420087 | M34: 33-flip-7.jpg | N34: PARTY_ICEBREAKERS | O34: Flip over cards one by one without flipping the same number twice. Sound easy? Think again! This isn't just any deck of cards… In Flip 7 there's only one 1 card, two 2's, three 3’s, etc plus a bunch of special cards that can score you extra points, give you a second chance, or freeze you or your opponents in your tracks. Are you the type of player to play it safe and bank points before you bust, or are you going to risk it all and go for the bonus points by flipping over seven in a row? Press your luck meets strategy in this addictive card game that's sure to be the greatest card game you’ve ever played! —description from the publisher | P34: ["Eric Olsen"] | Q34: ["The Op Games", "999 Games", "Catch Up Games", "Ghenos Games", "Kaissa Chess & Games", "KOSMOS", "MINDOK", "Randolph", "Rebel Sp. z o.o."] | R34: ["Interrupts", "Push Your Luck", "Score-and-Reset Game", "Take That"] | S34: ["O'Neil Mabile"] | T34: 7.20567 | U34: 1.0433 | V34: 659 | W34: 11438 | X34: 8 | Y34: FALSE | Z34: FALSE | AA34: Party • Family | AB34: =COUNTIF(OWNED[bgg_id],library_data[[#This Row],[bgg_id]]) -> 1
A35: 34 | B35: For Sale | C35: Card Game, Economic | D35: 1997 | E35: 3 | F35: 6 | G35: 30 | H35: 30 | I35: /thumbs/34-for-sale.jpg | J35: https://cf.geekdo-images.com/dJh9HkZC346NgPTAicJq_A__original/img/6ib2NLakSlsf69WYwCOe9NNLcsc=/0x0/filters:format(jpeg)/pic1513085.jpg | K35: 2025-09-16T22:42:36.475815 | L35: 172 | M35: 34-for-sale.jpg | N35: PARTY_ICEBREAKERS | O35: For Sale is a quick, fun game nominally about buying and selling real estate. During the game's two distinct phases, players first bid for several buildings then, after all buildings have been bought, sell the buildings for the greatest profit possible. The original Ravensburger/FX Schmid edition (1997/98) has slightly different rules than later English editions, and only 20 buildings instead of 30. The Ãœberplay 2005 Edition has new art, rules and card distribution changes, and it accommodates 3-6 players. The Gryphon 2009 Edition uses the Überplay art for the faces of the property cards, while replacing most other art. The rules are the same as the Überplay edition, with the exception of the rounding rule (which was stated in different ways in different printings of the Überplay edition). Rounding rule The rounding rule preferred by the designer Stefan Dorra is that players get back half of their bid rounded DOWN (not UP), as confirmed in correspondence with him here and here. A history of how the rounding rule has changed in different editions is documented here. | P35: ["Stefan Dorra"] | Q35: ["Eagle-Gryphon Games", "IELLO", "Ravensburger", "2 Pionki", "Albi", "AURUM, Inc.", "Baborka Games", "Brain Games", "Compaya.hu: Gamer Caf\u00e9 Kft.", "Competo / Marektoy", "F.X. Schmid", "Gabinete L\u00fadico", "Geekach LLC", "HaKubia", "Heidelberger Spieleverlag", "Jolly Thinkers", "Kaissa Chess & Games", "MEBO Games", "Meeple Virus", "NeoTroy Games", "New Games Order, LLC", "PaperGames (III)", "Portal Games", "Primigenio", "Siam Board Games", "SPIEL DAS! Verlag", "TLAMA games", "Top Toys", "\u00dcberplay", "uplay.it edizioni", "Wargames Club Publishing", "Zito! \u038f\u03c1\u03b1 \u03b3\u03b9\u03b1 \u03c0\u03b1\u03b9\u03c7\u03bd\u03af\u03b4\u03b9", "\u0412\u0437\u0440\u043e\u0441\u043b\u044b\u0435 \u0434\u0435\u0442\u0438", "\u041d\u0435\u0441\u043a\u0443\u0447\u043d\u044b\u0435 \u0438\u0433\u0440\u044b", "\u05e4\u05e8\u05e9 \u05de\u05e9\u05d7\u05e7\u05d9\u05dd: Game Knight"] | R35: ["Auction / Bidding", "Auction: Sealed Bid", "Auction: Turn Order Until Pass", "Hand Management", "Selection Order Bid"] | S35: ["\u00d3scar Aguado", "Abbas Amirabadi", "Mohammad Amir Garoosian", "Alvin Madden", "Gil Martimiano", "Mahmoud Arasteh Nasab", "Emilien Rotival", "Catell Ruz", "Dossom Studio", "Chema Vicente", "Uros Vuckovic", "Klaus Wilinski"] | T35: 7.26239 | U35: 1.2508 | V35: 352 | W35: 33316 | X35: 10 | Y35: FALSE | Z35: FALSE | AA35: Family | AB35: =COUNTIF(OWNED[bgg_id],library_data[[#This Row],[bgg_id]]) -> 1
A36: 35 | B36: Gardeners | C36: Deduction, Real-time | D36: 2023 | E36: 1 | F36: 4 | G36: 15 | H36: 15 | I36: /thumbs/35-gardeners.png | J36: https://cf.geekdo-images.com/2urn9RKuOsEGdGNKYRxG4w__original/img/AuwOYXvTPff_YWmuVSb0zCsuQ-o=/0x0/filters:format(png)/pic6991274.png | K36: 2025-09-16T22:42:38.505835 | L36: 361840 | M36: 35-gardeners.png | N36: COOP_ADVENTURE | O36: Gardeners is a simultaneous cooperative game played silently and in real time. In less than 15 minutes, players must succeed in arranging as many gardens as possible, always composed of the same 36 tiles, but responding to different rules from one round to another. Everyone must deduce the rules in force by observing where the tiles are placed and from where some are removed. A game of Gardeners is made up of an indefinite number of rounds. Each is broken down into 5 phases, as follows: Draw a Constraint card, Start the sandtimer, Arrange the garden, Check the garden, Prepare for the next round. During the game, players cannot communicate in any way about what to do or not to do to make the garden. Will you satisfy the King's whimsical desires? —description from the publisher | P36: ["Kasper Lapp"] | Q36: ["Sit Down!", "2Tomatoes Games", "HUCH!"] | R36: ["Communication Limits", "Cooperative Game", "Deduction", "Pattern Recognition", "Real-Time", "Score-and-Reset Game", "Solo / Solitaire Game", "Square Grid", "Tile Placement"] | S36: ["Anthony Moulins"] | T36: 6.37466 | U36: 2 | V36: 11106 | W36: 206 | X36: 10 | Y36: TRUE | Z36: FALSE | AA36: Social Deduction | AB36: =COUNTIF(OWNED[bgg_id],library_data[[#This Row],[bgg_id]]) -> 1
A37: 36 | B37: Granny Wars: A Game of Tit for Tat | C37: Bluffing, Card Game, Number | D37: 2013 | E37: 2 | F37: 8 | G37: 20 | H37: 20 | I37: /thumbs/36-granny-wars--a-game-of-tit-for-tat.png | J37: https://cf.geekdo-images.com/0dE03b-pcKKZ5g3Zrk-SlA__original/img/C9RJ4beOskLv9GQoz9kUUnvu05M=/0x0/filters:format(png)/pic8199109.png | K37: 2025-09-16T22:42:40.614376 | L37: 146765 | M37: 36-granny-wars--a-game-of-tit-for-tat.png | N37: PARTY_ICEBREAKERS | O37: Your Granny's position as the town's top handicrafter is threatened by upstart contenders from a new retirement community. Your task is to try to help her, while distracting and sabotaging her competitors – but if you don't keep your loyalty hidden, the other players will definitely stitch you up! At the beginning of Granny Wars: A Game of Tit for Tat, you receive a secret loyalty card matching one of the Granny cards on the table, and you are dealt ten cards which range from -5 to +5 points. The deck also includes Gold cards, which grant a special Granny power (like "Nana Nap") in addition to points. Players take turns adding cards to the Grannies, and the "Tit for Tat" mechanism allows a player to "bounce" an equal and opposite card from one pile to another, e.g., playing a +3 on a -3 lets a player move the -3 to another pile of their choice. After everyone has exhausted their 10 cards, players reveal which Granny they supported and sum the points in her pile of cards. The game can be played by 2 players, with a small modification to the rules. | P37: ["Amanda Milne", "Julia Schiller", "Brad Thompson"] | Q37: ["Cheeky Parrot Games", "SchilMil Games, Ltd."] | R37: ["Hand Management", "Memory", "Take That"] | S37: ["Kuan-Sheng Hsu"] | T37: 6.13305 | U37: 1.2 | V37: 20714 | W37: 59 | X37: 7 | Y37: FALSE | Z37: FALSE | AA37: Social Deduction | AB37: =COUNTIF(OWNED[bgg_id],library_data[[#This Row],[bgg_id]]) -> 1
A38: 37 | B38: Hive | C38: Abstract Strategy, Animals | D38: 2001 | E38: 2 | F38: 2 | G38: 20 | H38: 20 | I38: /thumbs/37-hive.jpg | J38: https://cf.geekdo-images.com/fQe85tsBZoH6ibPnm1k1UA__original/img/eqUVrCJKcMBGBhw4Gfc9_9JabYE=/0x0/filters:format(jpeg)/pic791151.jpg | K38: 2025-09-16T22:42:42.903180 | L38: 2655 | M38: 37-hive.jpg | N38: GATEWAY_STRATEGY | O38: Hive is a strategic game for two players that is not restricted by a board and can be played anywhere on any flat surface. Hive is made up of twenty two pieces, eleven black and eleven white, resembling a variety of creatures each with a unique way of moving. With no setting up to do, the game begins when the first piece is placed down. As the subsequent pieces are placed this forms a pattern that becomes the playing surface (the pieces themselves become the board). Unlike other such games, the pieces are never eliminated and not all have to be played. The object of the game is to totally surround your opponent's queen, while at the same time trying to block your opponent from doing likewise to your queen. The player to totally surround his opponent's queen wins the game. ••• Hive FAQ - please read before posting questions in the forum! | P38: ["John Yianni"] | Q38: ["Gen42 Games", "64 Ounce Games", "asmodee", "Cr\u00f3mola", "G3", "Ghenos Games", "Gigamic", "HUCH!", "Jolly Thinkers", "Ludicus Games", "Magellan", "Oficina do Aprendiz", "Productief BV", "Reflexshop", "Smart Zone Games", "Tantrix UK Ltd.", "uplay.it edizioni", "Vendetta", "Wargames Club Publishing", "Zhiyanjia"] | R38: ["Enclosure", "Grid Movement", "Hexagon Grid", "Pattern Movement", "Pieces as Map", "Three Dimensional Movement", "Tile Placement"] | S38: ["John Yianni"] | T38: 7.31756 | U38: 2.3142 | V38: 321 | W38: 39417 | X38: 9 | Y38: FALSE | Z38: FALSE | AA38: Abstract | AB38: =COUNTIF(OWNED[bgg_id],library_data[[#This Row],[bgg_id]]) -> 1
A39: 38 | B39: Hues and Cues | C39: Deduction, Party Game | D39: 2020 | E39: 3 | F39: 10 | G39: 30 | H39: 30 | I39: /thumbs/38-hues-and-cues.jpg | J39: https://cf.geekdo-images.com/jdR8WW75HkaoHGMTCIx9lA__original/img/i8nlw_c9CYgJMzixadYVh7GTTPc=/0x0/filters:format(jpeg)/pic5390676.jpg | K39: 2025-09-16T22:42:44.843969 | L39: 302520 | M39: 38-hues-and-cues.jpg | N39: PARTY_ICEBREAKERS | O39: What hue do you think of when we say “apple”? Hues and Cues is a vibrant game of colorful communication where players are challenged to make connections to colors with words. Using only one and two-word cues, players try to get others to guess a specific hue from the 480 colors on the game board. The closer the guesses are to the target, the more points you earn. Since everyone imagines colors differently, connecting colors and clues has never been this much fun! Gather around with three to ten people to play a quick and simple game with a prism of possibilities! First, a “cue giver” hides a specific color they’ve chosen out of a deck of cards. There are 480 shades on the board in front of you! After getting one- and two-word cues, everyone places their marker on which color they think is being described. “Coffee.” Is it dark brown, as in freshly brewed? “Au lait.” With milk. That means I should pick a lighter shade! Use examples from everyday life, from nature to pop culture, or materials and moods. Everyone around the table gets a turn to give cues and guess. The better your hints or guesses, the more points you earn. Play off others' experiences to narrow down what they have in mind! —description from the publisher | P39: ["Scott Brady"] | Q39: ["The Op Games", "CMON Global Limited", "Grok Games", "Lanlalen", "Ludopolis"] | R39: ["Communication Limits", "Deduction", "Score-and-Reset Game", "Targeted Clues", "Turn Order: Progressive"] | S39: [] | T39: 6.49431 | U39: 1.0682 | V39: 2323 | W39: 6058 | X39: 8 | Y39: FALSE | Z39: FALSE | AA39: Party • Family | AB39: =COUNTIF(OWNED[bgg_id],library_data[[#This Row],[bgg_id]]) -> 1
A40: 39 | B40: Escape Room: The Game | C40: Electronic, Puzzle | D40: 2016 | E40: 3 | F40: 5 | G40: 60 | H40: 60 | I40: /thumbs/39-escape-room-the-game.png | J40: https://cf.geekdo-images.com/1CIfreuv-gqcaUndxUAExw__original/img/1-lAwj58R_C50ogYHKN34mWVoR0=/0x0/filters:format(png)/pic3117400.png | K40: 2025-09-16T22:42:46.875508 | L40: 204836 | M40: 39-escape-room-the-game.png | N40: COOP_ADVENTURE | O40: Take the viral social experience of Escape Rooms to the comfort of your own home and for a fraction of the cost that you would pay! Included in this game are 4 unique 60 minute escape room puzzles that will test your cranial skills. Use images, gears, words, keys, shapes, maps and more to solve the three stages within each escape room. An analog timer on the Chrono Decoder centerpiece incessantly counts down, emitting ominous noises to create an environment shut out from the outside world. If the puzzles stump you for too long, slide a hint card into the Hint Decoder to keep your team moving. Slide 4 keys into the Chrono Decoder when you think you have the answer... but beware, if you're wrong, a precious minute will be taken from you. The 4 escape rooms vary in difficulty, designed to give any group the experience they expect and deserve. If you're craving more puzzles, Escape Room expansions will be available, but you'll need the base game first as the Chrono Decoder is essential to the experience. Included in the base game in order of difficulty is: Prison Break, Virus, Nuclear Countdown, and Temple of the Aztec Prison Break: Ten years in prison for a crime you didn't commit. Ten years of your life wasted for being in the wrong place at the wrong time, it hardly seemed fair. You know the guards will reach your cell during the rounds in an hour. Every bone in your body tells you this is the opportunity of a lifetime; you're 60 minutes away from freedom! Virus: What a time to faint! You swear you could kill your lab partner, but you know that won't be necessary. The liquid that's oozing out of the broken bottle will kill everybody in the room soon enough... Nuclear Countdown: The table is filled with all kinds of materials that send shivers down your spine. At that moment your phone rings and your worst nightmare becomes reality, the bomb threat is real! Temple of the Aztec: The stories told about the temple were numerous. Anybody that had entered the temple w | P40: ["(Uncredited)"] | Q40: ["Identity Games International B.V.", "ADC Blackfire Entertainment", "Broadway Toys LTD", "Concentra", "Cranio Creations", "Diset S. A.", "FoxMind Israel", "Gal\u00e1pagos Jogos", "Maki A/S", "Noris Spiele", "Spin Master Ltd.", "ToyRock Oy"] | R40: ["Cooperative Game", "Deduction", "Elapsed Real Time Ending"] | S40: ["Sebastian Goyke", "Roland MacDonald"] | T40: 6.87925 | U40: 2.2632 | V40: 1549 | W40: 4364 | X40: 16 | Y40: TRUE | Z40: FALSE | AA40: Family | AB40: =COUNTIF(OWNED[bgg_id],library_data[[#This Row],[bgg_id]]) -> 1
A41: 40 | B41: King of Tokyo | C41: Dice, Fighting, Movies / TV / Radio theme, Science Fiction | D41: 2011 | E41: 2 | F41: 6 | G41: 30 | H41: 30 | I41: /thumbs/40-king-of-tokyo.jpg | J41: https://cf.geekdo-images.com/m_RzXpHURC0_xLkvRSR_sw__original/img/hSvWgiRYJCTTuoLOWTW3c8sYtl8=/0x0/filters:format(jpeg)/pic3043734.jpg | K41: 2025-09-16T22:42:48.949645 | L41: 70323 | M41: 40-king-of-tokyo.jpg | N41: GATEWAY_STRATEGY | O41: In King of Tokyo, you play mutant monsters, gigantic robots, and strange aliens—all of whom are destroying Tokyo and whacking each other in order to become the one and only King of Tokyo. At the start of each turn, you roll six dice, which show the following six symbols: 1, 2, or 3 Victory Points, Energy, Heal, and Attack. Over three successive throws, choose whether to keep or discard each die in order to win victory points, gain energy, restore health, or attack other players into understanding that Tokyo is YOUR territory. The fiercest player will occupy Tokyo, and earn extra victory points, but that player can't heal and must face all the other monsters alone! Top this off with special cards purchased with energy that have a permanent or temporary effect, such as the growing of a second head which grants you an additional die, body armor, nova death ray, and more.... and it's one of the most explosive games of the year! In order to win the game, one must either destroy Tokyo by accumulating 20 victory points, or be the only surviving monster once the fighting has ended. First Game in the King of Tokyo series | P41: ["Richard Garfield"] | Q41: ["IELLO", "Boardgame Space", "Brain Games", "Bureau de Juegos", "Delta Vision Publishing", "Devir", "Egmont Polska", "Enigma (Bergsala Enigma)", "Fantasmagoria", "GaGa Games", "Gal\u00e1pagos Jogos", "GeGe Co. Ltd.", "GoKids \u73a9\u6a02\u5c0f\u5b50", "HaKubia", "Heidelberger Spieleverlag", "Hobby Japan", "Hobby World", "HomoLudicus", "Kaissa Chess & Games", "Korea Boardgames", "Lautapelit.fi", "Lex Games", "Mancalamaro", "MESAboardgames", "MIPL", "Nordic Games ehf", "Origames", "Portal Games", "Reflexshop", "REXhry", "Siam Board Games", "Smart Ltd", "uplay.it edizioni", "Venner\u00f8d Forlag AS", "\u0406\u0433\u0440\u043e\u043c\u0430\u0433"] | R41: ["Dice Rolling", "Die Icon Resolution", "King of the Hill", "Open Drafting", "Player Elimination", "Push Your Luck", "Re-rolling and Locking", "Take That"] | S41: ["Gabriel Butik", "Romain Gaschet", "Paul Mafayon", "Igor Polouchine", "Benjamin Raynal", "Jean-Baptiste Reynaud", "Jonathan Silvestre", "R\u00e9gis Torres", "Anthony Wolff"] | T41: 7.12042 | U41: 1.4859 | V41: 467 | W41: 74279 | X41: 8 | Y41: FALSE | Z41: FALSE | AA41: Family | AB41: =COUNTIF(OWNED[bgg_id],library_data[[#This Row],[bgg_id]]) -> 1
A42: 41 | B42: KLASK | C42: Action / Dexterity, Real-time | D42: 2014 | E42: 2 | F42: 2 | G42: 10 | H42: 10 | I42: /thumbs/41-klask.png | J42: https://cf.geekdo-images.com/oPNuEm_dR987BKoYEF9zGQ__original/img/ZNqEkLMKkrIPxRduZWmWC6VBgoY=/0x0/filters:format(png)/pic7414566.png | K42: 2025-09-16T22:42:51.122098 | L42: 165722 | M42: 41-klask.png | N42: KIDS_FAMILIES | O42: The KLASK game board is shaped like a ball field with two deep holes functioning as goals in each end of the field. In the middle of the field, three white magnetic pieces serve as "obstacles" – do NOT attract them to your own gaming piece! Your gaming piece is a black magnet. You control it by holding a large magnet under the board. This magnet is connected to a small magnet placed on the field. The purpose of the game is to push the small, red ball around on the field with your magnet/gaming piece, shoot the ball past the obstacles and your opponent and into the goal hole (Klask). It’s so much fun when your opponent suddenly is covered in white obstacles or you drop your gaming piece into the goal – something which might happen if you get a little too eager! Place the game board on a table between the two players. Place the three white magnetic pieces on the white fields on the board. Put two coins in each point slot next to the "0". Each player has a black magnetic gaming piece in two parts. Place the short (thin) part on top of the board and the long (thick) part under the board in such a way, so the two parts “catch” each other. Place the ball in the corner start field. Steer it with the black gaming pieces. The youngest player starts the game. You score a point if: The ball ends in your opponent's hole and stays in the hole. Two or all of the three white magnetic pieces stick to your opponent's gaming piece. The opponent accidentally pulls their gaming piece into their own goal hole. If the opponent loses their gaming piece. Each time you get a point, you must move your coin one point forward in the point slot. The player who first reaches the KLASK field wins. During the game: If one of the white magnetic pieces sticks to a gaming piece, the game continues; if two of the white magnetic pieces stick to one gaming piece, the opponent gets one point. If the ball falls over the edges of the board, you must place the ball in the co | P42: ["Mikkel Bertelsen"] | Q42: ["Klask ApS", "Big Potato Games", "Boardgame Space", "Brain Games", "CLD Distributing", "Competo / Marektoy", "Dino Toys s. r. o.", "FantasTies", "FoxMind", "G3", "Game Factory", "Ghenos Games", "Gigamic", "InterHit", "Korea Boardgames", "Lord of Boards", "MEBO Games", "Reflexshop", "Regatul Jocurilor", "VR Distribution"] | R42: ["Real-Time", "Score-and-Reset Game"] | S42: ["Mikkel Bertelsen"] | T42: 7.62718 | U42: 1.0485 | V42: 254 | W42: 11699 | X42: 8 | Y42: FALSE | Z42: FALSE | AA42: Party • Family | AB42: =COUNTIF(OWNED[bgg_id],library_data[[#This Row],[bgg_id]]) -> 1
A43: 42 | B43: Leaping Lemmings | C43: Animals, Humor | D43: 2010 | E43: 2 | F43: 6 | G43: 60 | H43: 72 | I43: /thumbs/42-leaping-lemmings.jpg | J43: https://cf.geekdo-images.com/a4iXNnKmRMGJPimWki6T_w__original/img/ti-q16xwJv-Sw5DG4tVvQEdM-e4=/0x0/filters:format(jpeg)/pic7047121.jpg | K43: 2025-09-16T22:42:53.827920 | L43: 29687 | M43: 42-leaping-lemmings.jpg | N43: GATEWAY_STRATEGY | O43: Leaping Lemmings - The Original Cliff Divers Leaping Lemmings is a humorous game for 2-6 players. Each player controls a cloned clan of lemmings that have been specially trained to compete with the other lemming clans, all trying to scurry down a canyon and hurl themselves over a cliff. Distance and style points are important. One lemming diving with style and élan is worth as many as five of the more mundane divers. But beware the hungry eagles circling overhead or your lemmings might not even make the cliff edge! Objective: The player with the most victory points wins the game. To earn victory points, players dive their lemmings over the cliff edge and/or collect Lemming Chow Pellets. The game board is a hex-based map representing the canyon down which up to six separate lemming clans will travel. The canyon ends with the cliff edge hexes, which are the lemmings' ultimate goal. Between the lemmings and their goal there are two eagles circling overhead hoping for multiple lemming snacks. Each turn a movement card is revealed which will allow for 2-5 lemming movement points. Card luck is mitigated in that all players use the same card to move that turn. Only the top lemming in each stack is allowed to move, so covering your opponents' lemmings is one tactic that is used to slow them down. The down side is that the top lemming in each stack is the only one in danger of becoming eagle chow. Special Actions allow players to briefly alter the normal rules of the game to their advantage or to their opponents' detriment. There are 16 different Special Actions in the game. Home Page: http://www.gmtgames.com/p-143-leaping-lemmings.aspx | P43: ["John Poniske", "Rick Young"] | Q43: ["GMT Games"] | R43: ["Dice Rolling", "Grid Movement", "Hand Management", "Hexagon Grid", "Push Your Luck", "Race", "Take That"] | S43: ["Rajim Harris", "Rodger B. MacGowan", "Leona Preston", "Mark Simonitch"] | T43: 6.41239 | U43: 1.8455 | V43: 4347 | W43: 1270 | X43: 13 | Y43: FALSE | Z43: FALSE | AA43: Family | AB43: =COUNTIF(OWNED[bgg_id],library_data[[#This Row],[bgg_id]]) -> 1
A44: 43 | B44: Drop It | C44: Action / Dexterity | D44: 2018 | E44: 2 | F44: 4 | G44: 30 | H44: 30 | I44: /thumbs/43-drop-it.jpg | J44: https://cf.geekdo-images.com/CwlOEAEzD-O09vdbvyD2Gw__original/img/C9b_1Wjp5-1m8AnaKlYrWmnB6NA=/0x0/filters:format(jpeg)/pic7988716.jpg | K44: 2025-09-16T22:42:56.042711 | L44: 244916 | M44: 43-drop-it.jpg | N44: KIDS_FAMILIES | O44: Circles, triangles, squares and diamonds: Drop It is about letting go, with the pieces you drop landing somewhere in the vertical game board, ideally where they'll score the most points, but the tiles bounce around and don't always land where you expect them to! In more detail, each turn the active player drops one of their pieces into the slot of the game board. The player scores points for the highest level that the piece touches and for any special locations that it touches, but if the piece touches anything of the same shape or color, then you score nothing! What's more, certain pieces are forbidden at certain spots on the edge of the playing area. The Drop It rulebook includes variant rules for simpler play or more variety from game to game. | P44: ["Bernhard Lach", "Uwe Rapp"] | Q44: ["KOSMOS", "999 Games", "Albi", "Spilbr\u00e6t.dk", "Thames & Kosmos", "Venner\u00f8d Forlag AS"] | R44: [] | S44: ["Fiore GmbH", "Andreas Resch"] | T44: 6.88471 | U44: 1.0877 | V44: 1841 | W44: 3118 | X44: 8 | Y44: FALSE | Z44: FALSE | AA44: Family | AB44: =COUNTIF(OWNED[bgg_id],library_data[[#This Row],[bgg_id]]) -> 1
... A94: 93 | B94: Give Me the Brain! | C94: Card Game, Zombies | D94: 1996 | E94: 3 | F94: 8 | G94: 15 | H94: 15 | I94: /thumbs/93-give-me-the-brain.jpg | J94: https://cf.geekdo-images.com/OlPw-qCHEgl-83A8rWf9IA__original/img/4ulSIYQhzgyhzzxlg6tKjis70kY=/0x0/filters:format(jpeg)/pic984692.jpg | K94: 2025-09-16T22:48:16.808520 | L94: 176 | M94: 93-give-me-the-brain.jpg | N94: PARTY_ICEBREAKERS | O94: Working in fast-food is hell. All the employees are zombies, and you can't find a single brain amongst them. Except for the brain part - there is, in fact, one brain - that's the premise of Give Me the Brain!, a card game in which players take on the roles of zombies in a fast-food restaurant in hell. They all have to complete a number of tasks before leaving work, and the work keeps piling on. Even worse, some of the tasks require basic intelligence and there's only one brain to go around. Note: Give Me the Brain: Superdeluxe Edition has 100 cards, instead of 112 with a few cards adjusted from previous versions. | P94: ["James Ernest"] | Q94: ["Cheapass Games", "James Ernest Games", "Steve Jackson Games", "Truant Spiele"] | R94: ["Action Points", "Auction / Bidding", "Hand Management"] | S94: ["Brian Snoddy"] | T94: 5.8341 | U94: 1.2727 | V94: 7648 | W94: 2175 | X94: 10 | Y94: FALSE | Z94: FALSE | AA94: Thematic • Family | AB94: =COUNTIF(OWNED[bgg_id],library_data[[#This Row],[bgg_id]]) -> 1
A95: 94 | B95: Glimstone Grab | C95: Fantasy | D95: 2025 | E95: 2 | F95: 4 | G95: 10 | H95: 25 | I95: /thumbs/94-glimstone-grab.jpg | J95: https://cf.geekdo-images.com/1EeG4Iw7oH6HR15Yo9waQA__original/img/DQj_Zz0AZ4jb_aQyPHDYizXu870=/0x0/filters:format(jpeg)/pic8272357.jpg | K95: 2025-09-16T22:48:17.409826 | L95: 303929 | M95: 94-glimstone-grab.jpg | N95: KIDS_FAMILIES | O95: A cooperative game for 1-4 players. Much Middling is an average place, except for the special gems (glimstones) in its forest. Children love to play with these but unfortunately, a group of trolls has settled into a glade there. They love the glimstones too and have been snatching the children for lunch. A wizard recruits Esmeralda, from the Hoard game, as he knows of her reputation stealing treasure from a dragon and hopes to put her skills to use to benefit the community. The wizard and Esmeralda set off in opposite directions, collecting glimstones which can be used to ransom snatched children and buy time. When they meet again, if they have the right combination of glimstones, they can perform a spell to banish a troll. They must banish all the trolls to win, but if a player ends their turn and all children have been taken, the players lose. Players use movement cards to move the characters between the gems; it is possible to plan sequences of movements to get the characters to align again. Before each player's turn, an event card reveals if a child has been snatched or other forest inhabitants, some friend and some foe to the players, have been active that turn. —description from the publisher | P95: ["Jonathan McGarvey", "Julia Schiller"] | Q95: ["Cheeky Parrot Games"] | R95: ["Action Queue", "Cooperative Game", "Dice Rolling", "Hand Management", "Pick-up and Deliver"] | S95: ["Tim Kings-Lynne"] | T95: 7.6 | W95: 5 | X95: 8 | Y95: TRUE | Z95: TRUE | AA95: Co-op | AB95: =COUNTIF(OWNED[bgg_id],library_data[[#This Row],[bgg_id]]) -> 1
A96: 95 | B96: Gloomhaven | C96: Adventure, Exploration, Fantasy, Fighting, Miniatures | D96: 2017 | E96: 1 | F96: 4 | G96: 60 | H96: 120 | I96: /thumbs/95-gloomhaven.jpg | J96: https://cf.geekdo-images.com/sZYp_3BTDGjh2unaZfZmuA__original/img/7d-lj5Gd1e8PFnD97LYFah2c45M=/0x0/filters:format(jpeg)/pic2437871.jpg | K96: 2025-09-16T22:48:17.896691 | L96: 174430 | M96: 95-gloomhaven.jpg | N96: COOP_ADVENTURE | O96: Gloomhaven is a game of Euro-inspired tactical combat in a persistent world of shifting motives. Players will take on the roles of wandering adventurers with their own special sets of skills and their own reasons for traveling to this dark corner of the world. Players must work together out of necessity to clear out menacing dungeons and forgotten ruins. In the process, they will enhance their abilities with experience and loot, discover new locations to explore and plunder, and expand an ever-branching story fueled by the decisions they make. This is a game with a persistent and changing world that is ideally played over many game sessions. After a scenario, players will make decisions about what to do next, which will determine how the story continues, kind of like a “Choose Your Own Adventure” book. Playing through a scenario is a co-operative affair where players will fight against automated monsters using an innovative card system to determine the order of play and what a player does on their turn. Each turn, a player chooses two cards to play out of their hand. The number on the top card determines their initiative for the round. Each card also has a top and bottom power, and when it is a player’s turn in the initiative order, they determine whether to use the top power of one card and the bottom power of the other, or vice-versa. Players must be careful, though, because over time they will permanently lose cards from their hands. If they take too long to clear a dungeon, they may end up exhausted and be forced to retreat. | P96: ["Isaac Childres"] | Q96: ["Cephalofair Games", "Albi", "Albi Polska", "Arclight Games", "Feuerland Spiele", "Gal\u00e1pagos Jogos", "Games Warehouse", "G\u00e9m Klub Kft.", "Hobby World", "Korea Boardgames", "MYBG Co., Ltd."] | R96: ["Action Queue", "Action Retrieval", "Campaign / Battle Card Driven", "Card Play Conflict Resolution", "Communication Limits", "Cooperative Game", "Critical Hits and Failures", "Deck Construction", "Grid Movement", "Hand Management", "Hexagon Grid", "Legacy Game", "Line of Sight", "Modular Board", "Multi-Use Cards", "Narrative Choice / Paragraph", "Once-Per-Game Abilities", "Role Playing", "Scenario / Mission / Campaign Game", "Simultaneous Action Selection", "Solo / Solitaire Game", "Storytelling", "Tags", "Variable Player Powers"] | S96: ["Alexandr Elichev", "Josh T. McDowell", "Alvaro Nebot"] | T96: 8.55478 | U96: 3.9148 | V96: 4 | W96: 65686 | X96: 14 | Y96: TRUE | Z96: FALSE | AA96: Thematic • Strategy | AB96: =COUNTIF(OWNED[bgg_id],library_data[[#This Row],[bgg_id]]) -> 1
A97: 96 | B97: Hanabi | C97: Card Game, Deduction, Memory | D97: 2010 | E97: 2 | F97: 5 | G97: 25 | H97: 25 | I97: /thumbs/96-hanabi.jpg | J97: https://cf.geekdo-images.com/JDVksMwfcqoem1k_xtZrOA__original/img/5vNHZiTEhK4aRDuGXv5KImp9cmQ=/0x0/filters:format(jpeg)/pic2007286.jpg | K97: 2025-09-16T22:48:18.417324 | L97: 98778 | M97: 96-hanabi.jpg | N97: COOP_ADVENTURE | O97: Hanabi—named for the Japanese word for "fireworks"—is a cooperative game in which players try to create the perfect fireworks show by placing the cards on the table in the right order. (In Japanese, hanabi is written as èŠ±ç«; these are the ideograms flower and fire, respectively.) The card deck consists of five different colors of cards, numbered 1–5 in each color. For each color, the players try to place a row in the correct order from 1–5. Sounds easy, right? Well, not quite, as in this game you hold your cards so that they're visible only to other players. To assist other players in playing a card, you must give them hints regarding the numbers or the colors of their cards. Players must act as a team to avoid errors and to finish the fireworks display before they run out of cards. An extra suit of cards, rainbow colored, is also provided for advanced or variant play. Hanabi was originally published as part of Hanabi & Ikebana. | P97: ["Antoine Bauza"] | Q97: ["ABACUSSPIELE", "Cocktail Games", "Les 12 Singes", "asmodee", "Brain Games", "Broadway Toys LTD", "Buly Games", "Competo / Marektoy", "cutia.ro", "Enigma (Bergsala Enigma)", "Gal\u00e1pagos Jogos", "Games7Days", "G\u00e9m Klub Kft.", "Ghenos Games", "Happy Baobab", "Hobby Japan", "Interlude", "Kaissa Chess & Games", "Lifestyle Boardgames Ltd", "Oliphante", "PaperGames (III)", "R&R Games", "Rebel Sp. z o.o.", "REXhry", "Spin Master Ltd.", "Swan Panasia Co., Ltd."] | R97: ["Communication Limits", "Cooperative Game", "Hand Management", "Memory", "Ordering", "Set Collection"] | S97: ["Antoine Bauza", "G\u00e9rald Guerlais", "Laura Michaud", "Albertine Ralenti"] | T97: 7.03141 | U97: 1.6908 | V97: 581 | W97: 51227 | X97: 8 | Y97: TRUE | Z97: FALSE | AA97: Family | AB97: =COUNTIF(OWNED[bgg_id],library_data[[#This Row],[bgg_id]]) -> 1
A98: 97 | B98: Herd Mentality | C98: Animals, Party Game | D98: 2020 | E98: 4 | F98: 20 | G98: 20 | H98: 30 | I98: /thumbs/97-herd-mentality.png | J98: https://cf.geekdo-images.com/85hYrpSl9Aoh2TgMf4CiDA__original/img/QPcr2EfpZjJzvNGjfQZwRbs-kMo=/0x0/filters:format(png)/pic5509026.png | K98: 2025-09-16T22:48:18.904529 | L98: 311322 | M98: 97-herd-mentality.png | N98: PARTY_ICEBREAKERS | O98: This is a party game for families, friends and cow rustlers. The aim of the game is simple: think like the herd and write down the same answers as your friends. If your answer is part of the majority, you all win cows. Yeehaw! If everyone else writes an answer that is matched by at least one other person, but yours is the odd one out, then you land the angry Pink Cow, and your herd of cows is worthless until you can offload it onto someone else. The first player to collect eight cows wins. | P98: ["Rich Coombes", "Dan Penn"] | Q98: ["Big Potato Games", "Anv\u00e4ndbart Litet F\u00f6retag", "Desyllas Games", "Gigamic", "Hobby World", "Mega Bleu", "Mercurio", "Randolph", "Reflexshop", "Rozum", "ToyCo"] | R98: ["Hot Potato", "Voting"] | S98: ["Robin Sowden Garc\u00eda"] | T98: 6.62047 | U98: 1 | V98: 2526 | W98: 3102 | X98: 10 | Y98: FALSE | Z98: FALSE | AA98: Party | AB98: =COUNTIF(OWNED[bgg_id],library_data[[#This Row],[bgg_id]]) -> 1
A99: 98 | B99: Hoard | C99: Card Game, Fantasy | D99: 2014 | E99: 2 | F99: 6 | G99: 10 | H99: 45 | I99: /thumbs/98-hoard.png | J99: https://cf.geekdo-images.com/-t184dGXfs_Gl2glwdkWtg__original/img/b_8n8RXbBdRsxC3pHizDVwftu7A=/0x0/filters:format(png)/pic3007776.png | K99: 2025-09-16T22:48:19.385826 | L99: 180471 | M99: 98-hoard.png | N99: GATEWAY_STRATEGY | O99: Can you gather and secure more treasure than your fellow-adventurers from the Hoard of the sleeping dragon? Can you defend yourself from their attacks and perhaps perpetrate a few of your own? And can you end the hunt at the most opportune time, perhaps by actually wakening the fearsome beast? Hoard is a dynamic game of hand management, set collection, and press-your-luck. Each turn players take one of four possible actions: 1) roll a custom die and move to take a new card, 2) secure a set of treasures or add to an existing set to score points, 3) affect the dragon, who wakes in stages from his tail to his head, by playing cards that soothe or rouse him, or 4) use a sword on an opponent or capture a used sword with a shield. The board is composed of 12 facedown cards surrounding the dragon. It changes as players remove and replace the cards. Dice rolls between 1-5 enable clockwise or counterclockwise movement and the special symbol allows access to all but one of the cards, so it is a game that rewards memory. Hoard is meant to be played in rounds, with scoring tokens obviating the need for pencil and paper scorekeeping. | P99: ["Tim Kings-Lynne", "Julia Schiller"] | Q99: ["(Self-Published)", "Cheeky Parrot Games", "Mirakulus"] | R99: ["Hand Management", "Memory", "Push Your Luck", "Score-and-Reset Game", "Set Collection"] | S99: ["Tim Kings-Lynne"] | T99: 6.41278 | U99: 1.2222 | V99: 11218 | W99: 257 | X99: 6 | Y99: FALSE | Z99: TRUE | AA99: Set Collection | AB99: =COUNTIF(OWNED[bgg_id],library_data[[#This Row],[bgg_id]]) -> 1
A100: 99 | B100: Horrified | C100: Horror, Movies / TV / Radio theme | D100: 2019 | E100: 1 | F100: 5 | G100: 60 | H100: 60 | I100: /thumbs/99-horrified.jpg | J100: https://cf.geekdo-images.com/SoClIcwjDo_iZs0idVikDw__original/img/TEprFkOM3G_u2HnUvh05WITeXbg=/0x0/filters:format(jpeg)/pic4848330.jpg | K100: 2025-09-16T22:48:19.866542 | L100: 282524 | M100: 99-horrified.jpg | N100: COOP_ADVENTURE | O100: Imagine living in a place so wretched that it's not plagued by one, two, or even three monsters — but seven of the most horrifying fiends! In this game, you'll come face to face with them all as you work together to rid the town of the maniacal or misunderstood creatures - before it's too late. Horrified is a co-operative game where players battle the classic Universal movie monsters. Players win or lose together. Players win when all Monsters are defeated but will lose if the Terror track reaches the skull space OR the Monster deck is empty when a card is needing to be drawn. On a player’s turn, they will do their Hero phase actions. Then the Monsters act in the Monster phase. Event cards determine which monster is in play. Horrified includes high-quality sculpted miniatures (Frankenstein, The Bride of Frankenstein, The Wolf Man, Dracula, The Mummy, The Invisible Man, Creature from the Black Lagoon). Its innovative, easy-to-learn, cooperative gameplay has players working together against the monsters with varying levels of difficulty. Just as each monster is unique, they require different strategies and tactics to be defeated. —description from the publisher | P100: ["Prospero Hall", "Peter Lee"] | Q100: ["Ravensburger"] | R100: ["Action Points", "Cooperative Game", "Dice Rolling", "Pick-up and Deliver", "Point to Point Movement", "Solo / Solitaire Game", "Variable Player Powers", "Variable Set-up"] | S100: ["Prospero Hall"] | T100: 7.60608 | U100: 2.0184 | V100: 228 | W100: 18902 | X100: 10 | Y100: TRUE | Z100: FALSE | AA100: Family • Thematic | AB100: =COUNTIF(OWNED[bgg_id],library_data[[#This Row],[bgg_id]]) -> 1
A101: 100 | B101: Infernal Wagon | C101: American West, Card Game, Party Game, Real-time | D101: 2022 | E101: 2 | F101: 5 | H101: 7 | I101: /thumbs/100-infernal-wagon.jpg | J101: https://cf.geekdo-images.com/VQGfh1TGelec_hEKGkioBg__original/img/ZAH2m-x0jV3YGxWGckfN7upEvZY=/0x0/filters:format(jpeg)/pic6745725.jpg | K101: 2025-09-16T22:48:20.356629 | L101: 358805 | M101: 100-infernal-wagon.jpg | N101: COOP_ADVENTURE | O101: Oh no, the mine is collapsing! Hurry, get in the wagon and head towards the exit! Infernal Wagon is an intensely fun cooperative game in which players must work together to create a path to the exit… before time runs out! But be careful: each card played has a high chance of triggering devastating effects! A game of Infernal Wagon plays in 7 minutes at most, until one of the end game conditions is met. In this cooperative game, all players win or lose together. At the start of the game, place the 3 starting cards and the wagon on the last one. There is no turn order: when the time is right, the player with the best card plays and activates its effect. They draw a card and any other player can take a turn (in the 2 players variant, you can play 2 cards consecutively). Once a card is played, move the wagon onto it. Place the exit card in the 7 minutes time span to win the game! —description from the publisher | P101: ["Alexandre Emerit", "Florian Fay"] | Q101: ["IELLO", "TCG Factory"] | R101: ["Cooperative Game", "Race", "Real-Time", "Speed Matching", "Tile Placement"] | S101: ["Thomas Brissot"] | T101: 6.3972 | U101: 1.1667 | V101: 9608 | W101: 268 | X101: 7 | Y101: TRUE | Z101: FALSE | AA101: Party | AB101: =COUNTIF(OWNED[bgg_id],library_data[[#This Row],[bgg_id]]) -> 1
A102: 101 | B102: Jaipur | C102: Arabian, Card Game, Economic | D102: 2009 | E102: 2 | F102: 2 | G102: 30 | H102: 30 | I102: /thumbs/101-jaipur.jpg | J102: https://cf.geekdo-images.com/_LTujSe_o16nvjDC-J0seA__original/img/zUnAdsgt4dCxvtoRDc_9DHbic0M=/0x0/filters:format(jpeg)/pic5100947.jpg | K102: 2025-09-16T22:48:20.838831 | L102: 54043 | M102: 101-jaipur.jpg | N102: GATEWAY_STRATEGY | O102: You are one of the two most powerful traders in the city of Jaipur, the capital of Rajasthan, but that's not enough for you because only the merchant with two "seals of excellence" will have the privilege of being invited to the Maharaja's court. You are therefore going to have to do better than your direct competitor by buying, exchanging, and selling at better prices, all while keeping an eye on both your camel herds. Jaipur is a fast-paced card game, a blend of tactics, risk and luck. On your turn, you can either take or sell cards. If you take cards, you have to choose between taking all the camels, taking one card from the market, or swapping 2-5 cards between the market and your cards. If you sell cards, you get to sell only one type of good, and you receive as many chips for that good as the number of cards you sold. The chips' values decrease as the game progresses, so you'd better hurry! On the other hand, you receive increasingly high rewards for selling three, four, or five cards of the same good at a time, so you'd better wait! You can't sell camels, but they're paramount for trading and they're also worth a little something at the end of the round, enough sometimes to secure the win, so you have to use them smartly. | P102: ["S\u00e9bastien Pauchon"] | Q102: ["GameWorks S\u00e0RL", "Space Cowboys", "ADC Blackfire Entertainment", "Boardgame Space", "cutia.ro", "Esdevium", "Gal\u00e1pagos Jogos", "G\u00e9m Klub Kft.", "Hobby Japan", "KADABRA", "Kaissa Chess & Games", "Korea Boardgames", "Lord of Boards", "Rebel Sp. z o.o.", "Siam Board Games", "Yes Papa Games"] | R102: ["End Game Bonuses", "Hand Management", "Hidden Victory Points", "Market", "Open Drafting", "Race", "Score-and-Reset Game", "Set Collection", "Sudden Death Ending", "Turn Order: Progressive", "Variable Set-up"] | S102: ["Vincent Dutrait", "Alexandre Roche"] | T102: 7.48248 | U102: 1.4621 | V102: 199 | W102: 56044 | X102: 10 | Y102: FALSE | Z102: FALSE | AA102: Family | AB102: =COUNTIF(OWNED[bgg_id],library_data[[#This Row],[bgg_id]]) -> 1
A103: 102 | B103: Jungle Speed | C103: Action / Dexterity, Card Game, Party Game, Real-time | D103: 1997 | E103: 2 | F103: 10 | G103: 10 | H103: 10 | I103: /thumbs/102-jungle-speed.jpg | J103: https://cf.geekdo-images.com/pb553nZgH3akaF24MzT7nA__original/img/YVxlSoQ5q-8w4FMn8hM6Gz4nCNg=/0x0/filters:format(jpeg)/pic4659199.jpg | K103: 2025-09-16T22:48:21.341290 | L103: 8098 | M103: 102-jungle-speed.jpg | N103: PARTY_ICEBREAKERS | O103: In Jungle Speed, you must rely on your keen sense of observation and quick reflexes. It requires a steady hand -- which can be hard to maintain during the many fits of maniacal laughter! The wooden Totem sits in the middle of the table, waiting for the player with the fastest reflexes to snatch it up and win the game. Each player is dealt a hand of cards. In order to win you must be the first player to get rid of all of your cards. Each turn, all of the players reveal one of their cards. If two cards are identical, those players must make a grab for the Totem. The faster player then gives their cards to their unfortunate adversary. To add to the difficulty, certain cards are almost identical, which can trick a hapless player into grabbing the Totem by mistake -- a grave error. Other cards force all players to make a grab at once, change the method of play, or otherwise add to the difficulty. Jungle Jam, ÐœÐµÐ´Ð²ÐµÐ´, and Prawo DÅ¼ungli are unauthorized reproductions of Jungle Speed/Arriba! | P103: ["Thomas Vuarchex", "Pierrick Yakovenko"] | Q103: ["asmodee", "(Unknown)", "Asterion Press", "Boardgame Space", "Cr\u00f3mola", "FoxMind Israel", "Gal\u00e1pagos Jogos", "G\u00e9m Klub Kft.", "Gibsons", "Goldsieber Spiele", "Hobby Japan", "Inter Hobby Co., Ltd.", "KADABRA", "Kaissa Chess & Games", "Korea Boardgames", "Lautapelit.fi", "Lifestyle Boardgames Ltd", "Nordic Games ehf", "Piatnik", "Ponva d.o.o.", "Rebel Sp. z o.o.", "Swan Panasia Co., Ltd.", "Tactic", "Top Toys", "Week End Games", "Y.E.S. A/S", "Zygomatic", "\u0406\u0433\u0440\u043e\u043c\u0430\u0433"] | R103: ["Pattern Recognition", "Speed Matching"] | S103: ["Franz Vohwinkel", "Thomas Vuarchex", "Pierrick Yakovenko"] | T103: 6.45754 | U103: 1.1296 | V103: 1976 | W103: 14038 | X103: 7 | Y103: FALSE | Z103: FALSE | AA103: Party | AB103: =COUNTIF(OWNED[bgg_id],library_data[[#This Row],[bgg_id]]) -> 1
A104: 103 | B104: Just One | C104: Deduction, Party Game, Word Game | D104: 2018 | E104: 3 | F104: 7 | G104: 20 | H104: 60 | I104: /thumbs/103-just-one.png | J104: https://cf.geekdo-images.com/74haNunMBn85beBi-yIKwA__original/img/hA22qL6nZxchA8FMTIfhLMcI53I=/0x0/filters:format(png)/pic8669313.png | K104: 2025-09-16T22:48:21.828365 | L104: 254640 | M104: 103-just-one.png | N104: PARTY_ICEBREAKERS | O104: Just One is a co-operative party game in which you all play together to get the best score! Your goal each round is to get one player — the active player — to guess a mystery word based on the clues given by teammates. Can you achieve a perfect score by guessing all the mystery words? In more detail, everyone who is not the active player sees the mystery word, then each player independently writes a clue on their personal easel. Once everyone has finished, you reveal the clues to one another. All identical clues are removed from play, so try to be original! After eliminating duplicate clues, reveal the remaining clues to the active player. If they correctly guess the mystery word, your team scores a point. If they decline to guess, you don't score the current card. If they guess wrong, you don't score the current card and you lose one of the points you had already scored. Thus, be original, but not so original that you don't help the active player guess correctly! | P104: ["Ludovic Roudy", "Bruno Sautter"] | Q104: ["Repos Production", "ADC Blackfire Entertainment", "Arclight Games", "Brain Games", "CoolPlay", "FoxMind Israel", "Fun Consortium", "Gal\u00e1pagos Jogos", "Geekach LLC", "G\u00e9m Klub Kft.", "GoKids \u73a9\u6a02\u5c0f\u5b50", "Happy Baobab", "Kaissa Chess & Games", "Korea Boardgames", "Lifestyle Boardgames Ltd", "Mald\u00f3n", "Morapiaf", "Nordic Games ehf", "Rebel Sp. z o.o."] | R104: ["Communication Limits", "Cooperative Game", "Deduction", "Score-and-Reset Game"] | S104: ["\u00c9ric Azagury", "Florian Poullet"] | T104: 7.59945 | U104: 1.0361 | V104: 155 | W104: 32708 | X104: 8 | Y104: TRUE | Z104: FALSE | AA104: Party | AB104: =COUNTIF(OWNED[bgg_id],library_data[[#This Row],[bgg_id]]) -> 1
A105: 104 | B105: Kiitos | C105: Card Game, Word Game | D105: 2020 | E105: 2 | F105: 4 | G105: 45 | H105: 60 | I105: /thumbs/104-kiitos.png | J105: https://cf.geekdo-images.com/-OTABDc2MzNsSoqTdk_Ldw__original/img/aMcNzbymAo5ewhYcT_aq8fxysTo=/0x0/filters:format(png)/pic8879814.png | K105: 2025-09-16T22:48:37.966953 | L105: 300509 | M105: 104-kiitos.png | N105: PARTY_ICEBREAKERS | O105: Kiitos is a fast-tempo, card-based word game with novel, simple rules and deep, emergent game play. Can you make a word with the letters in your hand, and what letters that may or may not be in your opponents’? Players start by playing one letter of a word and saying a target word. Then subsequent players build up the target word, either playing the next letter if they can, or by changing the target word dynamically if it can’t be continued. Can your word be finished for positive points, or can you trap your opponent into not being able to play and force them to pick up the unfinished word for negative points? Can you outwit your player with cleverness? If your opponent finishes your word for you say “Kiitos”, the Finnish word for thank-you. The rules change dynamically as the game is played and the game play switches between two modes: Kiitos which builds up words from left to right, and Super-Kiitos which builds up words at either end. Dubious words can be challenged. Fake words are OK if you can get them past your opponent unchallenged. Kiitos edge-case tests the dictionary like no other game. It’s a word game that feels somewhat like a trick-taking game, with a bit of deduction and bluffing. Lateral thinking and clever strategising are rewarded, sometimes. Luck can make or break your strategies. The target word can change 5 or more times just in the one hand. —description from the designer | P105: ["Matthew Thredgold"] | Q105: ["Ludogix"] | R105: ["Hand Management"] | S105: [] | T105: 7.3729 | U105: 1.7143 | V105: 10858 | W105: 107 | X105: 12 | Y105: FALSE | Z105: FALSE | AA105: Strategy | AB105: =COUNTIF(OWNED[bgg_id],library_data[[#This Row],[bgg_id]]) -> 1
A106: 105 | B106: Kingdomino | C106: Abstract Strategy, Medieval, Puzzle, Territory Building | D106: 2016 | E106: 2 | F106: 4 | G106: 15 | H106: 25 | I106: /thumbs/105-kingdomino.png | J106: https://cf.geekdo-images.com/c0m3gwZTcfKoLI63ASio8g__original/img/HT6NQPT0cSFcZXjSewtjTO_NBAE=/0x0/filters:format(png)/pic8443569.png | K106: 2025-09-16T22:48:38.483286 | L106: 204583 | M106: 105-kingdomino.png | N106: GATEWAY_STRATEGY | O106: In Kingdomino, you are a lord seeking new lands in which to expand your kingdom. You must explore all the lands, including wheat fields, lakes, and mountains, in order to spot the best plots, while competing with other lords to acquire them first. The game uses tiles with two sections, similar to Dominoes. Each turn, each player will select a new domino to connect to their existing kingdom, making sure at least one of its sides connects to a matching terrain type already in play. The order of who picks first depends on which tile was previously chosen, with better tiles forcing players to pick later in the next round. The game ends when each player has completed a 5x5 grid (or failed to do so), and points are counted based on number of connecting tiles and valuable crown symbols. | P106: ["Bruno Cathala"] | Q106: ["Blue Orange (EU)", "Blue Orange Games", "(Unknown)", "Bur\u00f3", "Coiledspring Games", "Fantasmagoria", "Feelindigo", "FoxGames", "FoxMind Israel", "Games Factory Publishing", "G\u00e9m Klub Kft.", "Ghenos Games", "Le Grand Massif", "Happy Baobab", "KADABRA", "Kaissa Chess & Games", "Lautapelit.fi", "Lifestyle Boardgames Ltd", "MEBO Games", "MINDOK", "MIPL", "Oliphante", "PaperGames (III)", "Pegasus Spiele", "Pridemage Games", "Swan Panasia Co., Ltd.", "\u30c6\u30f3\u30c7\u30a4\u30ba\u30b2\u30fc\u30e0\u30ba (TendaysGames)", "White Goblin Games"] | R106: ["Enclosure", "Open Drafting", "Tile Placement", "Turn Order: Claim Action"] | S106: ["Cyril Bouquet", "Pauline Detraz", "Hervine Galliou"] | T106: 7.29382 | U106: 1.233 | V106: 318 | W106: 51295 | X106: 8 | Y106: FALSE | Z106: FALSE | AA106: Family | AB106: =COUNTIF(OWNED[bgg_id],library_data[[#This Row],[bgg_id]]) -> 1
A107: 106 | B107: Kingdomino Duel | C107: Dice, Medieval | D107: 2019 | E107: 2 | F107: 2 | G107: 20 | H107: 20 | I107: /thumbs/106-kingdomino-duel.jpg | J107: https://cf.geekdo-images.com/Tygk_sCQEIpa7PUxsl2TmA__original/img/JbxNf6L8DvSJzi6SSSa9EFK8xaM=/0x0/filters:format(jpeg)/pic4783810.jpg | K107: 2025-09-16T22:48:38.976652 | L107: 281960 | M107: 106-kingdomino-duel.jpg | N107: GATEWAY_STRATEGY | O107: Roll the dice, choose the ones you want, and put them together in pairs to create your dominoes. Domino by domino, fill in your map while entrusting the territories of your kingdom to loyal dignitaries. Gather favors from wizards in order to cast powerful spells that will allow you to rule without having to share. Kingdomino Duel is a standalone game that preserves the essence of the acclaimed original Kingdomino. In this game, instead of adding dominoes to your kingdom, you will choose two dice to combine into a single "domino" that must then be drawn into your kingdom. —description from the publisher | P107: ["Bruno Cathala", "Ludovic Maublanc"] | Q107: ["Blue Orange (EU)", "Blue Orange Games", "Coiledspring Games", "FoxGames", "Happy Baobab", "Lautapelit.fi", "Lifestyle Boardgames Ltd", "PaperGames (III)", "Spilbr\u00e6t.dk", "Swan Panasia Co., Ltd."] | R107: ["Dice Rolling", "End Game Bonuses", "Paper-and-Pencil"] | S107: ["Cyril Bouquet"] | T107: 6.68437 | U107: 1.5128 | V107: 2551 | W107: 2477 | X107: 8 | Y107: FALSE | Z107: FALSE | AA107: Family | AB107: =COUNTIF(OWNED[bgg_id],library_data[[#This Row],[bgg_id]]) -> 1
A108: 107 | B108: Komodo | C108: Animals, Math, Negotiation, Territory Building | D108: 2012 | E108: 2 | F108: 4 | G108: 45 | H108: 45 | I108: /thumbs/107-komodo.jpg | J108: https://cf.geekdo-images.com/dgaRvaxKKXTgUm51UthTmQ__original/img/lu8RyTWC3xti8NbC4bPwABRw5Ao=/0x0/filters:format(jpeg)/pic6713136.jpg | K108: 2025-09-16T22:48:39.772173 | L108: 124992 | M108: 107-komodo.jpg | N108: GATEWAY_STRATEGY | O108: In the strategic tile-laying game Komodo, players are zoologists attempting to build new habitats for Australasian animals imperilled by an incoming asteroid. Each player holds two animal cards stating the type and amount of terrain needed, five multi-terrain tiles, and wild cards. On a turn, they may lay up to three tiles, place one or both of their animals in free-form contiguous blocks of appropriate terrain, and use all or some of their wild cards. The starter tile has two blocks of each of the four terrain types: forest, grassland, desert and water. The number of blocks of terrain needed by an animal is equivalent to the number of points you can score by placing it. When the tile supply is exhausted, each player takes a final turn, then loses points for any unplaced animals still in hand. The player with the highest score wins. Komodo can be played competitively in both basic or strategic mode. In the former, wild cards are obtained randomly; in the latter, players can choose their wild cards. Actions permitted by a wild card include: releasing animals to free up their terrain; bartering or stealing terrain tiles; remodeling tiles already placed; and forcing an exchange of animals. In the cooperative version of Komodo, all 32 animals must be housed and each player must place at least one animal during their turn. The game is played open-handed, and the wild cards hinder the players. | P108: ["Amanda Milne", "Julia Schiller"] | Q108: ["SchilMil Games, Ltd."] | R108: ["Cooperative Game", "Hand Management", "Modular Board", "Open Drafting", "Tile Placement"] | S108: ["Aaron Barron", "Amanda Milne", "Sam Turner"] | T108: 6.50652 | U108: 2.3333 | V108: 19641 | W108: 46 | X108: 8 | Y108: TRUE | Z108: TRUE | AA108: Family • Strategy | AB108: =COUNTIF(OWNED[bgg_id],library_data[[#This Row],[bgg_id]]) -> 1
A109: 108 | B109: Lanterns: The Harvest Festival | C109: Abstract Strategy | D109: 2015 | E109: 2 | F109: 4 | G109: 30 | H109: 30 | I109: /thumbs/108-lanterns-the-harvest-festival.png | J109: https://cf.geekdo-images.com/JmY4nVWwW98qEn0NRbKdTw__original/img/a5OqnY-e8hhVO1IHp6wZKnXHWlY=/0x0/filters:format(png)/pic2372790.png | K109: 2025-09-16T22:48:40.314077 | L109: 160851 | M109: 108-lanterns-the-harvest-festival.png | N109: GATEWAY_STRATEGY | O109: The harvest is in, and the artisans are hard at work preparing for the upcoming festival. Decorate the palace lake with floating lanterns and compete to become the most honored artisan when the festival begins. In Lanterns: The Harvest Festival, players have a hand of tiles depicting various color arrangements of floating lanterns, as well as an inventory of individual lantern cards of specific colors. When you place a tile, all players (you and your opponents) receive a lantern card corresponding to the color on the side of the tile facing them. Place carefully to earn cards and other bonuses for yourself, while also looking to deny your opponents. Players gain honor by dedicating sets of lantern cards — three pairs, for example, or all seven colors — and the player with the most honor at the end of the game wins. | P109: ["Christopher Chung"] | Q109: ["Foxtrot Games", "Renegade Game Studios", "Broadway Toys LTD", "CrowD Games", "Devir", "Games Factory Publishing", "Korea Boardgames", "Lex Games", "Matagot", "Pegasus Spiele", "White Goblin Games"] | R109: ["Hand Management", "Pattern Building", "Set Collection", "Tile Placement"] | S109: ["Christopher Chung", "Alexey Kot", "Beth Sobel"] | T109: 6.86062 | U109: 1.5435 | V109: 1056 | W109: 11818 | X109: 8 | Y109: FALSE | Z109: FALSE | AA109: Family | AB109: =COUNTIF(OWNED[bgg_id],library_data[[#This Row],[bgg_id]]) -> 1
A110: 109 | B110: Lindyhop | C110: Card Game | D110: 2023 | E110: 2 | F110: 2 | G110: 15 | H110: 30 | I110: /thumbs/109-lindyhop.png | J110: https://cf.geekdo-images.com/V5NWK66oZZHydpvTWP7IrQ__original/img/Ps__dDB3dNUNx0Hwy1gxhQo-f0s=/0x0/filters:format(png)/pic7823579.png | K110: 2025-09-16T22:48:40.815424 | L110: 367829 | M110: 109-lindyhop.png | N110: PARTY_ICEBREAKERS | O110: In Lindyhop, a co-operative trick-taking game about swing dancing, players start by dealing out the music cards to create the song to which they will dance. Players then play tricks as dance moves to progress through the song, picking up points as they go. Some of the cards have powers, but these powers activate only on specific parts of the music — and you can't discuss what each player has in their hand. Try to beat your score each dance, but if you run out of dance cards before the music finishes, you score nothing! —description from the publisher | P110: ["Mark Kaneko", "James Smeal"] | Q110: ["Flat Cap Games"] | R110: ["Cooperative Game", "Trick-taking"] | S110: ["Ben Corlett"] | T110: 7.03824 | V110: 20408 | W110: 34 | X110: 10 | Y110: TRUE | Z110: TRUE | AA110: Co-op | AB110: =COUNTIF(OWNED[bgg_id],library_data[[#This Row],[bgg_id]]) -> 1
A111: 110 | B111: Little Town | C111: City Building, Medieval | D111: 2017 | E111: 2 | F111: 4 | G111: 30 | H111: 60 | I111: /thumbs/110-little-town.jpg | J111: https://cf.geekdo-images.com/PhNY4VQAob6x4GjWHmbTsQ__original/img/dyyphqMmGF-imUTnPvyJQap3LoM=/0x0/filters:format(jpeg)/pic4624124.jpg | K111: 2025-09-16T22:48:41.304913 | L111: 241266 | M111: 110-little-town.jpg | N111: GATEWAY_STRATEGY | O111: In Little Town, you lead a team of architects and must dispatch workers to the town, collect resources and money, build buildings, and develop this little town. In the game, which lasts four rounds, you can acquire resources such as wood, stones, fish, and wheat from the surrounding squares by putting workers on the board, with three workers being placed each round. When you place a worker, you acquire the resources available in all eight surrounding spaces. You can build buildings by using these resources, and you — or any other player — can gain the effect of the building when place a worker next to it; if you place next to a building owned by another, however, you must pay them a coin before you can collect those resources. Players collect victory points by using the powers of buildings, by constructing buildings, and by achieving goals dealt to them at the beginning of the game. After four rounds, whoever has the most victory points wins. —description from the publisher | P111: ["Shun Taguchi", "Aya Taguchi"] | Q111: ["Studio GG", "Arclight Games", "BoardBros", "Bur\u00f3", "GoKids \u73a9\u6a02\u5c0f\u5b50", "IELLO", "Korea Boardgames", "Lavka Games", "Mancalamaro", "Portal Games", "Reflexshop", "Siam Board Games", "Switch Games", "TCG Factory", "\u0406\u0433\u0440\u043e\u043c\u0430\u0433"] | R111: ["Contracts", "Tile Placement", "Worker Placement"] | S111: ["Sabrina Miramon", "Aya Taguchi", "\u305f\u304b\u307f\u307e\u3053\u3068 (Makoto Takami)"] | T111: 7.15307 | U111: 1.9496 | V111: 1135 | W111: 4604 | X111: 10 | Y111: FALSE | Z111: FALSE | AA111: Family | AB111: =COUNTIF(OWNED[bgg_id],library_data[[#This Row],[bgg_id]]) -> 1
A112: 111 | B112: Love Letter | C112: Card Game, Deduction, Renaissance | D112: 2019 | E112: 2 | F112: 6 | G112: 20 | H112: 20 | I112: /thumbs/111-love-letter.png | J112: https://cf.geekdo-images.com/V7WQjhAh0AatPXTYOrXtCQ__original/img/peOFPtAkzWUSpOSVTJu3pTDv2ck=/0x0/filters:format(png)/pic4766499.png | K112: 2025-09-16T22:48:41.809575 | L112: 277085 | M112: 111-love-letter.png | N112: PARTY_ICEBREAKERS | O112: The noble Princess is looking for an ideal partner and confidant to help with her royal duties when she one day assumes the throne. You must prove your worth and gain her trust by enlisting allies, friends, and family of the Princess to carry a letter of intent to her. Can you earn the Princess' trust and become her confidant? Playing cards one at a time, players in Love Letter use the abilities of these key people in the Princess' life to outwit their opponents and successfully deliver their letter and gain her favor. Players must utilize each character's special skill to avoid being caught and successfully deliver their letter to the Princess. Once a set number of favor tokens are acquired, that player wins and becomes the Princess' confidant. This 2019 edition of Love Letter features new artwork by Citadels artist Andrew Bosley, screen-printed tokens, and two new characters (five cards in total) that allow for games with up to six players. When played, the Chancellor (value 6) allows you to draw two new cards, add those to your hand, then place two cards of your choice on the bottom of the deck. The Spy (value 0) wins you a favor token if you were the only player to play or discard a spy during the round. —description from the publisher | P112: ["Seiji Kanai", "Justin Kemppainen", "Alexandar Ortloff-Tang"] | Q112: ["Z-Man Games", "ADC Blackfire Entertainment", "asmodee", "Boardgame Space", "BoardM Factory", "Delta Vision Publishing", "FoxMind Israel", "Gal\u00e1pagos Jogos", "Hobby World", "Korea Boardgames", "Lord of Boards", "Popcorn Games", "Rebel Sp. z o.o.", "Siam Board Games"] | R112: ["Deduction", "Hand Management", "Player Elimination", "Score-and-Reset Game", "Take That"] | S112: ["Andrew Bosley", "Samuel R. Shimota"] | T112: 7.50896 | U112: 1.1139 | V112: 327 | W112: 13852 | X112: 10 | Y112: FALSE | Z112: FALSE | AA112: Party • Family | AB112: =COUNTIF(OWNED[bgg_id],library_data[[#This Row],[bgg_id]]) -> 1
A113: 112 | B113: Mage Knight Board Game | C113: Adventure, Exploration, Fantasy, Fighting | D113: 2011 | E113: 1 | F113: 4 | G113: 60 | H113: 240 | I113: /thumbs/112-mage-knight-board-game.jpg | J113: https://cf.geekdo-images.com/DUO2hz9AlLOH8p9ED-lCWg__original/img/PDDH38Vf9NEB_4ODURxcJKNBfVQ=/0x0/filters:format(jpeg)/pic1083380.jpg | K113: 2025-09-16T22:48:53.309755 | L113: 96848 | M113: 112-mage-knight-board-game.jpg | N113: CORE_STRATEGY | O113: The Mage Knight board game puts you in control of one of four powerful Mage Knights as you explore (and conquer) a corner of the Mage Knight universe under the control of the Atlantean Empire. Build your army, fill your deck with powerful spells and actions, explore caves and dungeons, and eventually conquer powerful cities controlled by this once-great faction! In competitive scenarios, opposing players may be powerful allies, but only one will be able to claim the land as their own. In cooperative scenarios, the players win or lose as a group. Solo rules are also included. Combining elements of RPGs, deck-building, and traditional board games the Mage Knight board game captures the rich history of the Mage Knight universe in a self-contained gaming experience. | P113: ["Vlaada Chv\u00e1til"] | Q113: ["WizKids (I)", "asmodee", "Giochi Uniti", "Intrafin Games", "Lacerta", "NECA", "Pegasus Spiele", "REXhry"] | R113: ["Card Play Conflict Resolution", "Cooperative Game", "Deck, Bag, and Pool Building", "Dice Rolling", "Grid Movement", "Hand Management", "Hexagon Grid", "Modular Board", "Multi-Use Cards", "Open Drafting", "Role Playing", "Scenario / Mission / Campaign Game", "Solo / Solitaire Game", "Tags", "Turn Order: Claim Action", "Variable Player Powers"] | S113: ["J. Lonnee", "Chris Raimo", "Milan Vavro\u0148"] | T113: 8.079 | U113: 4.3733 | V113: 40 | W113: 34591 | X113: 14 | Y113: TRUE | Z113: FALSE | AA113: Thematic • Strategy | AB113: =COUNTIF(OWNED[bgg_id],library_data[[#This Row],[bgg_id]]) -> 1
A114: 113 | B114: Manifest | C114: Nautical, Pirates, Transportation | D114: 2014 | E114: 2 | F114: 5 | G114: 45 | H114: 90 | I114: /thumbs/113-manifest.jpg | J114: https://cf.geekdo-images.com/vgG5uGO2RIqozSklzzAbQA__original/img/UQku2OmxD__AIoOJOnsgO_rdmTM=/0x0/filters:format(jpeg)/pic1897286.jpg | K114: 2025-09-16T22:48:53.802928 | L114: 152471 | M114: 113-manifest.jpg | N114: CORE_STRATEGY | O114: It's the roaring '20s and there's a fortune to be made steaming across the wild oceans. To succeed, you'll need a captain's steady nerve and the help of Lady Luck to land your cargo where it's needed. You have ships full of passengers and precious cargo, but can you outrun pirate robbers, terrifying storms and a stock market crash that might devalue your goods? Manifest is a game of cargo ships, sea scoundrels, and nautical mayhem. Win points for your shipping company by completing Contracts. Pick up the required goods or passengers at their source, then navigate the high seas to deliver them to their destination. With a choice of private and public contracts and multi-purpose action cards, there are many paths to victory, and some "take that" options to make sure your opponents don't steal the limelight. Manifest can be played in two ways: Standard and Expert. The Standard game is the introductory and family game. The Expert game builds on this, with a deck-buying and building mechanism replacing the blind card draw, thus adding another level of strategy that confident players may prefer. | P114: ["Amanda Milne", "Julia Schiller"] | Q114: ["SchilMil Games, Ltd."] | R114: ["Deck, Bag, and Pool Building", "Dice Rolling", "Hand Management", "Pick-up and Deliver", "Point to Point Movement", "Take That"] | S114: ["Amanda Milne", "Franz Vohwinkel"] | T114: 6.45372 | U114: 2.8182 | V114: 13516 | W114: 121 | X114: 13 | Y114: FALSE | Z114: TRUE | AA114: Strategy | AB114: =COUNTIF(OWNED[bgg_id],library_data[[#This Row],[bgg_id]]) -> 1
A115: 114 | B115: Meadow | C115: Animals, Card Game, Environmental, Puzzle | D115: 2021 | E115: 1 | F115: 4 | G115: 60 | H115: 90 | I115: /thumbs/114-meadow.jpg | J115: https://cf.geekdo-images.com/9r3qdPijtgoIN24PxFU2gw__original/img/tHQTKwwk4N8J5fpWhsoE8t0FQhw=/0x0/filters:format(jpeg)/pic5894745.jpg | K115: 2025-09-16T22:48:54.375867 | L115: 314491 | M115: 114-meadow.jpg | N115: GATEWAY_STRATEGY | O115: Meadow is an engaging set collection game with over two hundred unique cards containing hand-painted watercolor illustrations. In the game, players take the role of explorers competing for the title of the most skilled nature observer. To win, they collect cards with the most valuable species, landscapes, and discoveries. Their journey is led by passion, a curiosity of the world, an inquiring mind, and a desire to discover the mysteries of nature. The competition continues at the bonfire where the players race to fulfill the goals of their adventures. In this medium-weight board game for 1-4 players, you take turns placing path tokens on one of the two boards. Placing a token on the main board allows the player to get cards, but playing them requires meeting certain requirements. Playing a token on the bonfire board activates special actions (which helps to implement a chosen strategy) and gives the opportunity to achieve goals that provide additional points. Throughout the game, players collect cards in their meadow and surroundings area. At the end, the player with the most points on cards and on the bonfire board wins. Meadow also includes envelopes with additional cards to open at specific moments... | P115: ["Klemens Kalicki"] | Q115: ["Rebel Studio", "ADC Blackfire Entertainment", "Arclight Games", "Gal\u00e1pagos Jogos", "Games4you", "G\u00e9m Klub Kft.", "Hobby Game Mall", "Hobby World", "Rebel Sp. z o.o.", "\u0406\u0433\u0440\u043e\u043c\u0430\u0433"] | R115: ["Hand Management", "Layering", "Open Drafting", "Set Collection", "Solo / Solitaire Game", "Worker Placement, Different Worker Types"] | S115: ["Karolina Kijak", "Katarzyna Fiebiger"] | T115: 7.70961 | U115: 2.2469 | V115: 212 | W115: 12868 | X115: 10 | Y115: FALSE | Z115: FALSE | AA115: Family • Strategy | AB115: =COUNTIF(OWNED[bgg_id],library_data[[#This Row],[bgg_id]]) -> 1
A116: 115 | B116: Meeple Circus | C116: Action / Dexterity, Animals, Real-time | D116: 2017 | E116: 2 | F116: 5 | G116: 45 | H116: 45 | I116: /thumbs/115-meeple-circus.jpg | J116: https://cf.geekdo-images.com/jmdwGVSEsYR9WQ8_Cjjlhg__original/img/WdVD5izYS30uZdZdQSOUSc2lB4w=/0x0/filters:format(jpeg)/pic3895016.jpg | K116: 2025-09-16T22:48:54.865911 | L116: 193214 | M116: 115-meeple-circus.jpg | N116: KIDS_FAMILIES | O116: Let the show begin! You have only one goal in Meeple Circus: Entertain the audience. The competition is tough, but you can create the most amazing circus by proposing incredible acts! Acrobats, horses, and many accessories are at your disposal. Be sure to undertake a good rehearsal, then with your remarkable dexterity, you can give them the show of their lifetime. Once the circus music starts, all eyes will be upon you! In short, Meeple Circus is a dexterity game in which you do what all gamers do when setting up a game: Pile up your meeples! | P116: ["C\u00e9dric Millet"] | Q116: ["Matagot", "Arclight Games", "Ergo Ludo Editions", "Gemblo Company", "Gen-X Games", "Ghenos Games", "Hobby Game Mall", "Lavka Games", "Mandoo Games", "Pegasus Spiele", "Surfin' Meeple", "Tower Tactic Games"] | R116: ["Open Drafting", "Pattern Building", "Push Your Luck", "Real-Time", "Stacking and Balancing"] | S116: ["Angelina Costamagna", "Mathieu Leyssenne", "Sabrina Tobal"] | T116: 7.01672 | U116: 1.4035 | V116: 1089 | W116: 6217 | X116: 8 | Y116: FALSE | Z116: FALSE | AA116: Family | AB116: =COUNTIF(OWNED[bgg_id],library_data[[#This Row],[bgg_id]]) -> 1
A117: 116 | B117: Mermaid Island | C117: Children's Game | D117: 2011 | E117: 2 | F117: 6 | G117: 15 | H117: 15 | I117: /thumbs/116-mermaid-island.jpg | J117: https://cf.geekdo-images.com/1ist092d5nP-fGl6YR4ZAQ__original/img/dx2UgQcGG1XFsddSK4oCnDoIINE=/0x0/filters:format(jpeg)/pic1001627.jpg | K117: 2025-09-16T22:48:55.362688 | L117: 94486 | M117: 116-mermaid-island.jpg | N117: KIDS_FAMILIES | O117: Watch out, Mermaids! The Sea Witch is on the move! The object of the game is to move all 3 mermaids from start to Mermaid Island before the Sea Witch gets there. Because Mermaid Island is a cooperative game players play any of the mermaid tokens - no one player has a single mermaid she is trying to get back to the island. Players take turns spinning the spinner and moving a mermaid or the Sea Witch. Mermaids move 1 or 2 spaces at a time and can take the bridge short cuts. The Sea Witch moves only 1 space at a time and always goes the long way around. If the Sea Witch lands on a mermaid, the mermaid must go back to start. But mermaids can collect wand tokens which move the Sea Witch back one space. Players decide together when to use the wands and which mermaids to move to keep the mermaids going. Looks deceptively simple, but is a lively and strategic game of chase! Components: 1 game board 3 mermaid tokens 1 sea witch with stand 4 wand tokens 1 spinner | P117: [] | Q117: ["Magellan", "Peaceable Kingdom"] | R117: ["Cooperative Game"] | S117: ["Cynthia Jabar"] | T117: 5.08224 | U117: 1 | V117: 27790 | W117: 107 | X117: 5 | Y117: TRUE | Z117: FALSE | AA117: Family | AB117: =COUNTIF(OWNED[bgg_id],library_data[[#This Row],[bgg_id]]) -> 1
A118: 117 | B118: Modern Art | C118: Card Game, Economic | D118: 1992 | E118: 3 | F118: 5 | G118: 45 | H118: 45 | I118: /thumbs/117-modern-art.png | J118: https://cf.geekdo-images.com/wLto-xaabHwKQe_Bc4iD1Q__original/img/s3Gai8XBTVfWFFlYpL4XF3kIlWU=/0x0/filters:format(png)/pic3458036.png | K118: 2025-09-16T22:48:55.865241 | L118: 118 | M118: 117-modern-art.png | N118: GATEWAY_STRATEGY | O118: Buying and selling paintings can be a very lucrative business. Five different artists have produced a bunch of paintings, and it's the player's task to be both the buyer and the seller, hopefully making a profit in both roles. He does this by putting a painting from his hand up for auction each turn. He gets the money if some other player buys it, but must pay the bank if he buys it for himself. After each round, paintings are valued by the number of paintings of that type that were sold. The broker with the most cash after four rounds is the winner. Part of the Knizia auction trilogy. | P118: ["Reiner Knizia"] | Q118: ["Hans im Gl\u00fcck", "Arrakis Games", "CMON Global Limited", "DiceTree Games", "Drosselmeyer & Co. Ltd.", "Fractal Juegos", "Gal\u00e1pagos Jogos", "GeGe Co. Ltd.", "Kaissa Chess & Games", "Land of Beautiful Mind (\u0633\u0631\u0632\u0645\u06cc\u0646 \u0630\u0647\u0646 \u0632\u06cc\u0628\u0627)", "Lautapelit.fi", "Lavka Games", "Lighthouse Games", "Matagot", "Mayfair Games", "New Games Order, LLC", "Odysseia Jogos", "Oink Games", "Pegasus Spiele", "Phantasia Co., Ltd", "Rebel Sp. z o.o.", "Wargames Club Publishing", "WoodCat"] | R118: ["Auction / Bidding", "Auction: English", "Auction: Once Around", "Auction: Sealed Bid", "Auction: Turn Order Until Pass", "Commodity Speculation", "Hand Management", "Victory Points as a Resource"] | S118: ["Carole Carrion", "Manuel Carvalho", "Chen Cheng-po", "Mike Doyle (I)", "Pete Fenlon", "Gianfranco Giordano", "Paul Laane", "Ramon Martins", "Daniel Melim", "Rafael Silveira", "Sigrid Thaler", "Zeilbeck & Natzeck Design Company"] | T118: 7.51884 | U118: 2.2845 | V118: 216 | W118: 24488 | X118: 10 | Y118: FALSE | Z118: FALSE | AA118: Strategy | AB118: =COUNTIF(OWNED[bgg_id],library_data[[#This Row],[bgg_id]]) -> 1
A119: 118 | B119: My First Bohnanza | C119: Card Game, Children's Game, Farming | D119: 2015 | E119: 3 | F119: 5 | G119: 30 | H119: 30 | I119: /thumbs/118-my-first-bohnanza.jpg | J119: https://cf.geekdo-images.com/UbQPqXChcoPKW-reUv7yJQ__original/img/x43XjBiXZs7FmUz4_ZilwYPxZlQ=/0x0/filters:format(jpeg)/pic2522755.jpg | K119: 2025-09-16T22:48:56.371105 | L119: 171419 | M119: 118-my-first-bohnanza.jpg | N119: KIDS_FAMILIES | O119: My First Bohnanza serves as both an introduction to Bohnanza and as a children's game in its own right, with the goal of the game being the same as its parent: Have the most Talers at the end of play. As in the original Bohnanza, the game includes multiple types of beans, with each bean having a number on it to indicate how many copies are in the game as well as a "beanometer" at the bottom of the card to show you how many cards of this type you need to harvest in order to collect Talers. My First Bohnanza has simplified beanometers, with four types of beans having only a single exchange value — e.g., five Gemeine (common) beans get you one Taler — and six types of beans having two exchange values. Games with the youngest players (or newcomers to the Bohnanza universe) should use the single beanometer cards with the other cards forming a Taler stack. To play, each player gets five cards, which they lay in a face-up row, and a beanfield tile that shows spots for two types of beans. On a turn, a player must plant the first (leftmost) card in one of her fields and she can choose to plant a second. Players try to group cards of the same type in the same field, but they can cover beans of different types, if needed. The player then reveals two cards from the deck and either keeps them or trades them (and cards from her hand, if desired) for cards held by other players; all traded cards must be planted. To end her turn, the player draws three cards and adds them to her row. As soon as a player has the proper number of bean cards in order in one of her fields, she harvests them, placing these cards in the discard pile and collecting a Taler from the stack. If those cards covered beans of another type, she can then start building on those beans again. After going through the deck 1-3 times (depending on the number of players), the game ends and whoever has the most Talers wins. Once players have played My First Bohnanza a few times, you can swap the single beanometer ca | P119: ["Heike Kiefer", "Uwe Rosenberg", "Hayo Siemsen"] | Q119: ["AMIGO", "Rio Grande Games"] | R119: ["Hand Management", "Trading"] | S119: ["Bj\u00f6rn Pertoft"] | T119: 6.60364 | U119: 1.3077 | V119: 8678 | W119: 246 | X119: 4 | Y119: FALSE | Z119: FALSE | AA119: Children's • Family | AB119: =COUNTIF(OWNED[bgg_id],library_data[[#This Row],[bgg_id]]) -> 1
A120: 119 | B120: My First Castle Panic | C120: Children's Game, Fantasy | D120: 2019 | E120: 1 | F120: 4 | G120: 20 | H120: 20 | I120: /thumbs/119-my-first-castle-panic.jpg | J120: https://cf.geekdo-images.com/jacehOaTJlMKMEl5RKZuGw__original/img/MgHPbS6FUyonnCgnTZJqWFbbF0g=/0x0/filters:format(jpeg)/pic4472950.jpg | K120: 2025-09-16T22:48:56.885207 | L120: 267314 | M120: 119-my-first-castle-panic.jpg | N120: KIDS_FAMILIES | O120: My First Castle Panic, like its predecessor Castle Panic, is a co-operative game in which players work together to defend their castle, but this game removes the reading requirement of the earlier one and fosters the development of educational skills, such as identifying colors and shapes, problem solving, and turn taking. In the game, monsters follow a single path toward a single, large, eye-catching castle, which is protected by one wall. Each step toward the castle is identified by a color and a shape. Players hold cards in their hands with cute defenders who also have a color and shape. When a card is played that matches the location of the monster, that monster is captured and thrown in the dungeon. Tension builds as more monsters are placed and move along the path toward the castle. If the castle is destroyed, the players lose; if it still stands when all the monsters are in the dungeon, the players win. | P120: ["Justin De Witt"] | Q120: ["Fireside Games", "64 Ounce Games", "ADC Blackfire Entertainment", "Gal\u00e1pagos Jogos", "Hobby World", "Space Cow"] | R120: ["Cooperative Game", "Hand Management", "Matching", "Solo / Solitaire Game"] | S120: ["Cam Kendell"] | T120: 6.4111 | U120: 1.1143 | V120: 4798 | W120: 1220 | X120: 4 | Y120: TRUE | Z120: FALSE | AA120: Children's | AB120: =COUNTIF(OWNED[bgg_id],library_data[[#This Row],[bgg_id]]) -> 1
A121: 120 | B121: My First Stone Age | C121: Children's Game, Memory, Prehistoric | D121: 2016 | E121: 2 | F121: 4 | G121: 15 | H121: 15 | I121: /thumbs/120-my-first-stone-age.jpg | J121: https://cf.geekdo-images.com/H1aCQoaq0H9Qt91hOgc3Sw__original/img/WFYWAb7gD96COGI6JW10XCd_vPI=/0x0/filters:format(jpeg)/pic9005688.jpg | K121: 2025-09-16T22:48:57.381832 | L121: 191004 | M121: 120-my-first-stone-age.jpg | N121: KIDS_FAMILIES | O121: Travel to the past with Jonon and Jada, two stone age children, to rediscover how the first humans settled the world around them. In My First Stone Age, a children's version of the Stone Age family game, the players collect goods and build their own settlement. Players first explore the location of forest tokens surrounding the village. Flipping a forest token over indicates the movement of the player's meeple to an action spot on the board. Gather or trade resources, visit the construction site or get a helper token for the kid's dog Guff who will fetch any resource when it's time to build a hut. The construction site is where huts can be build. Each requires a different set of resources. A visit the to construction site also resets the forest tokens: Flip the tokens back over and swap a couple of them to introduce some challenge. Use your memory to find the fastest paths to gather resources and built 3 huts before everyone else to be the winner of My First Stone Age. | P121: ["Marco Teubner"] | Q121: ["Hans im Gl\u00fcck", "999 Games", "Bard Centrum Gier", "Devir", "Filosofia \u00c9ditions", "Giochi Uniti", "Hobby World", "Lautapelit.fi", "MINDOK", "Piatnik", "Swan Panasia Co., Ltd.", "Z-Man Games"] | R121: ["Memory", "Set Collection"] | S121: ["Michael Menzel"] | T121: 6.61249 | U121: 1.1286 | V121: 2590 | W121: 2915 | X121: 5 | Y121: FALSE | Z121: FALSE | AA121: Children's | AB121: =COUNTIF(OWNED[bgg_id],library_data[[#This Row],[bgg_id]]) -> 1
A122: 121 | B122: Mysterium Park | C122: Deduction, Murder / Mystery, Party Game | D122: 2020 | E122: 2 | F122: 6 | G122: 30 | H122: 45 | I122: /thumbs/121-mysterium-park.jpg | J122: https://cf.geekdo-images.com/U2CYPYgIEC1cLF45Rh0UGw__original/img/472oJ1mqGHWxFxuOsnXFiZBshUc=/0x0/filters:format(jpeg)/pic5581038.jpg | K122: 2025-09-16T22:48:57.880655 | L122: 301767 | M122: 121-mysterium-park.jpg | N122: COOP_ADVENTURE | O122: Welcome to Mysterium Park! Its cotton candies, its circus, its dark secrets... The park’s former director has disappeared, but the investigation came to nothing. Since that night, weird things are happening on the fairground. As psychics, you’re convinced that a ghost haunts this carnival... You’re now intent on giving it a chance to reveal the truth. In this cooperative stand-alone game, the ghost sends visions with illustrated cards. The psychics try to interpret them in order to rule out certain suspects and locations. Then, they’ll seize their only chance to piece together what happened to the director. You have only six nights before the carnival leaves town... Open your minds and find the truth! Set in the lights of a 1950's US fairground, Mysterium Park shares the same core mechanism with the famous award-winning game it reimplements, though bringing a different approach: it is smaller and faster, thanks to very quick setup and simplified rules. Mysterium is a milestone in immersive and eye-catching experiences close to role-playing; with Mysterium Park, you can enjoy the heart of it in a more condensed way. — description from the publisher | P122: ["Oleksandr Nevskiy", "Oleg Sidorenko"] | Q122: ["Libellud", "Gal\u00e1pagos Jogos", "G\u00e9m Klub Kft.", "Hobby Japan", "Rebel Sp. z o.o."] | R122: ["Communication Limits", "Cooperative Game", "Pattern Recognition", "Roles with Asymmetric Information", "Storytelling"] | S122: ["Xavier Collette", "Ma\u00ebva da Silva", "M81 Studio"] | T122: 7.01689 | U122: 1.4316 | V122: 1243 | W122: 5281 | X122: 10 | Y122: TRUE | Z122: FALSE | AA122: Thematic • Family | AB122: =COUNTIF(OWNED[bgg_id],library_data[[#This Row],[bgg_id]]) -> 1
A123: 122 | B123: Ni no Kuni II: The Board Game | C123: City Building, Dice, Fantasy, Video Game Theme | D123: 2019 | E123: 1 | F123: 4 | G123: 30 | H123: 30 | I123: /thumbs/122-ni-no-kuni-ii-the-board-game.jpg | J123: https://cf.geekdo-images.com/8Ffxk6KCux8_ktrtMQ2HsQ__original/img/2lnQrb98vvM4nJgoXhivzcOvdsQ=/0x0/filters:format(jpeg)/pic4862891.jpg | K123: 2025-09-16T22:48:58.368774 | L123: 285125 | M123: 122-ni-no-kuni-ii-the-board-game.jpg | N123: CORE_STRATEGY | O123: Welcome Higgledies and Heroes to Ni no Kuni II: The Board Game, a fun, cooperative kingdom-building game for 1-4 players. You must work together to go on quests, defeat monsters, and grow your kingdom before the forces of evil can overcome you. Smart choices and a little luck will be needed to build the brightest kingdom possible to stand as a symbol of unity against evil. Can you build your kingdom well enough to overcome the darkness? —description from the publisher | P123: ["Bryce Johnston", "Steve Margetson"] | Q123: ["Steamforged Games Ltd."] | R123: ["Cooperative Game", "Dice Rolling"] | S123: ["Hiroyuki Maeda", "Hiroshi Matsuyama", "Yoshiyuki Momose", "Nobuyuki Yanai"] | T123: 6.38811 | U123: 1.6 | V123: 12500 | W123: 206 | X123: 14 | Y123: TRUE | Z123: FALSE | AA123: Co-op | AB123: =COUNTIF(OWNED[bgg_id],library_data[[#This Row],[bgg_id]]) -> 1
A124: 123 | B124: No Mercy for Monsters | C124: Children's Game, Party Game | D124: 2020 | E124: 1 | F124: 6 | G124: 20 | I124: /thumbs/123-no-mercy-for-monsters.jpg | J124: https://cf.geekdo-images.com/r0FDGwFOsoQ94jYYjY7EjQ__original/img/51G-5q0C3OI-Rgs-oRx-OTQmLSs=/0x0/filters:format(jpeg)/pic5493417.jpg | K124: 2025-09-16T22:48:58.912733 | L124: 299574 | M124: 123-no-mercy-for-monsters.jpg | N124: KIDS_FAMILIES | O124: You are playing with your friends in a quiet and peaceful neighborhood when you catch monsters trying to break into a house! Fortunately, the family living there is absent, and you’re an expert at monster-kicking. You don’t have your equipment but are determined to knock them out one by one using balls, socks, or buckets of water! No Mercy for Monsters is a co-operative game in which players team up to knock down the monsters before all the hidden tokens run out. | P124: ["J\u00e9r\u00f4me Soleil", "Emilie Soleil"] | Q124: ["Helvetiq"] | R124: ["Cooperative Game", "Dice Rolling"] | S124: ["Kasia Fryza"] | T124: 6.51333 | U124: 1 | V124: 21035 | W124: 45 | X124: 4 | Y124: TRUE | Z124: FALSE | AA124: Party | AB124: =COUNTIF(OWNED[bgg_id],library_data[[#This Row],[bgg_id]]) -> 1
A125: 124 | B125: No Thanks! | C125: Card Game | D125: 2004 | E125: 3 | F125: 7 | G125: 20 | H125: 20 | I125: /thumbs/124-no-thanks.png | J125: https://cf.geekdo-images.com/JSAs8aMopjf8P9JXwTMV7w__original/img/pm0ioQ1vNabJExMgcXwB2oMIalY=/0x0/filters:format(png)/pic9005058.png | K125: 2025-09-16T22:49:10.222588 | L125: 12942 | M125: 124-no-thanks.png | N125: PARTY_ICEBREAKERS | O125: No Thanks! is a card game designed to be as simple as it is engaging. The rules are simple. Each turn, players have two options: play one of their chips to avoid picking up the current face-up card pick up the face-up card (along with any chips that have already been played on that card) and turn over the next card However, the choices aren't so easy as players compete to have the lowest score at the end of the game. The deck of cards is numbered from 3 to 35, with each card counting for a number of points equal to its face value. Runs of two or more cards only count as the lowest value in the run - but nine cards are removed from the deck before starting, so be careful looking for connectors. Each chip is worth -1 point, but they can be even more valuable by allowing you to avoid drawing that unwanted card. The first versions of the game supported up to five players, but the German 2011 edition supports up to seven (simply by increasing the number of chips). This game was originally published in Germany in 2004 by Amigo as Geschenkt ...ist noch zu teuer!, meaning Even given as a gift, it is still too expensive!. Amigo's 2006 international edition, titled No Merci! (a delightful multi-lingual pun), had rules in several languages, including English. The game has subsequently been released in other countries under an assortment of names. The German 2024 edition includes additional cards to allow for play with variant rules. | P125: ["Thorsten Gimmler"] | Q125: ["AMIGO", "999 Games", "asmodee", "Boardgame Space", "Broadway Toys LTD", "Dal Negro", "Dr. Wood Challenge Centre", "Fractal Juegos", "G3", "Gigamic", "KADABRA", "Kaissa Chess & Games", "Kikigagne?", "Korea Boardgames", "Lautapelit.fi", "Lifestyle Boardgames Ltd", "Mayfair Games", "Mercurio", "M\u00f6bius Games", "Morapiaf", "PaperGames (III)", "Piatnik", "Rebel Sp. z o.o.", "REXhry", "Shafir Games (\u05d4\u05de\u05e9\u05d7\u05e7\u05d9\u05dd \u05e9\u05dc \u05d7\u05d9\u05d9\u05dd \u05e9\u05e4\u05d9\u05e8)", "Studio Supernova", "Swan Panasia Co., Ltd.", "Venner\u00f8d Forlag AS", "VR Distribution", "Z-Man Games", "\u0406\u0433\u0440\u043e\u043c\u0430\u0433"] | R125: ["Auction / Bidding", "Closed Economy Auction", "Push Your Luck", "Score-and-Reset Game", "Set Collection"] | S125: ["Oliver Freudenreich", "Dennis Lohausen", "Atelier L\u00f6wentor"] | T125: 7.08051 | U125: 1.1315 | V125: 543 | W125: 29493 | X125: 8 | Y125: FALSE | Z125: FALSE | AA125: Family | AB125: =COUNTIF(OWNED[bgg_id],library_data[[#This Row],[bgg_id]]) -> 1
